Workbook
Name FDSFER: #REF!
Name FER: #REF!
Name MATRIZ: #REF!

Sheet PU
A1: LOGOS SECURITIZADORA | J1: Data de Vencimento: | K1: 46241
A2: 16ª Série da 1ª Emissão (18C0722274) | J2: Data de Emissão: | K2: 43171
A3: dC | B3: dJ | C3: DATA | D3: VNe | E3: Fator IPCA | F3: VNa | G3: FatorJuros | H3: JUROS | I3: PU | J3: Valor Nominal Emissão: | K3: 10000 | M3: 2300000
G4: 0.085 | J4: Início da Rentabilidade | K4: 43175 | M4: 1.15
A5: 0 | B5: 0 | C5: =K2 | D5: =TRUNC(($K$3),8) | E5: 1 | F5: =TRUNC((D5*E5),8) | G5: =ROUND(((ROUND((1+$G$4)^TRUNC((1*30/360),9),9))^TRUNC((B5/31),9)),9) | H5: =TRUNC((F5*G5-F5),8) | I5: =F5+H5 | M5: 30/10/2025 23:53:03
A6: 0 | B6: 0 | C6: =C5+1 | D6: =IF(DAY(C6)=DAY($K$1+1),TRUNC(($D$5),8),D5) | E6: 1 | F6: =TRUNC((D6*E6),8) | G6: =ROUND(((1+$G$4)^(30/360))^(B6/31),9) | H6: =TRUNC((F6*G6-F6),8) | I6: =F6+H6
A7: 0 | B7: 0 | C7: =C6+1 | D7: =IF(DAY(C7)=DAY($K$1+1),TRUNC(($D$5),8),D6) | E7: 1 | F7: =TRUNC((D7*E7),8) | G7: =ROUND(((1+$G$4)^(30/360))^(B7/31),9) | H7: =TRUNC((F7*G7-F7),8) | I7: =F7+H7
A8: 0 | B8: 0 | C8: =C7+1 | D8: =IF(DAY(C8)=DAY($K$1+1),TRUNC(($D$5),8),D7) | E8: 1 | F8: =TRUNC((D8*E8),8) | G8: =ROUND(((1+$G$4)^(30/360))^(B8/31),9) | H8: =TRUNC((F8*G8-F8),8) | I8: =F8+H8
A9: 0 | B9: 0 | C9: =C8+1 | D9: =IF(DAY(C9)=DAY($K$1+1),TRUNC(($D$5),8),D8) | E9: 1 | F9: =TRUNC((D9*E9),8) | G9: =ROUND(((1+$G$4)^(30/360))^(B9/31),9) | H9: =TRUNC((F9*G9-F9),8) | I9: =F9+H9
A10: =IF(DAY(C10)=DAY($K$1+1),1,A9+1) | B10: =IF(DAY(C10)=DAY($K$1+1),1,B9+1) | C10: =C9+1 | D10: =IF(DAY(C10)=DAY($K$1+1),TRUNC(($D$5),8),D9) | E10: =TRUNC(((1+IPCA!#REF!))^(A10/22),8) | F10: =TRUNC((D10*E10),8) | G10: =ROUND(((1+$G$4)^(30/360))^(B10/31),9) | H10: =TRUNC((F10*G10-F10),8) | I10: =F10+H10
A11: =IF(DAY(C11)=DAY($K$1+1),1,A10+1) | B11: =IF(DAY(C11)=DAY($K$1+1),1,B10+1) | C11: =C10+1 | D11: =IF(DAY(C11)=DAY($K$1+1),TRUNC(($D$5),8),D10) | E11: =TRUNC(((1+IPCA!#REF!))^(A11/22),8) | F11: =TRUNC((D11*E11),8) | G11: =ROUND(((1+$G$4)^(30/360))^(B11/31),9) | H11: =TRUNC((F11*G11-F11),8) | I11: =F11+H11
A12: =IF(DAY(C12)=DAY($K$1+1),1,A11+1) | B12: =IF(DAY(C12)=DAY($K$1+1),1,B11+1) | C12: =C11+1 | D12: =IF(DAY(C12)=DAY($K$1+1),TRUNC(($D$5),8),D11) | E12: =TRUNC(((1+IPCA!#REF!))^(A12/22),8) | F12: =TRUNC((D12*E12),8) | G12: =ROUND(((1+$G$4)^(30/360))^(B12/31),9) | H12: =TRUNC((F12*G12-F12),8) | I12: =F12+H12
A13: =IF(DAY(C13)=DAY($K$1+1),1,A12+1) | B13: =IF(DAY(C13)=DAY($K$1+1),1,B12+1) | C13: =C12+1 | D13: =IF(DAY(C13)=DAY($K$1+1),TRUNC(($D$5),8),D12) | E13: =TRUNC(((1+IPCA!#REF!))^(A13/22),8) | F13: =TRUNC((D13*E13),8) | G13: =ROUND(((1+$G$4)^(30/360))^(B13/31),9) | H13: =TRUNC((F13*G13-F13),8) | I13: =F13+H13
A14: =IF(DAY(C14)=DAY($K$1+1),1,A13+1) | B14: =IF(DAY(C14)=DAY($K$1+1),1,B13+1) | C14: =C13+1 | D14: =IF(DAY(C14)=DAY($K$1+1),TRUNC(($D$5),8),D13) | E14: =TRUNC(((1+IPCA!#REF!))^(A14/22),8) | F14: =TRUNC((D14*E14),8) | G14: =ROUND(((1+$G$4)^(30/360))^(B14/31),9) | H14: =TRUNC((F14*G14-F14),8) | I14: =F14+H14
A15: =IF(DAY(C15)=DAY($K$1+1),1,A14+1) | B15: =IF(DAY(C15)=DAY($K$1+1),1,B14+1) | C15: =C14+1 | D15: =IF(DAY(C15)=DAY($K$1+1),TRUNC(($D$5),8),D14) | E15: =TRUNC(((1+IPCA!#REF!))^(A15/22),8) | F15: =TRUNC((D15*E15),8) | G15: =ROUND(((1+$G$4)^(30/360))^(B15/31),9) | H15: =TRUNC((F15*G15-F15),8) | I15: =F15+H15
A16: =IF(DAY(C16)=DAY($K$1+1),1,A15+1) | B16: =IF(DAY(C16)=DAY($K$1+1),1,B15+1) | C16: =C15+1 | D16: =IF(DAY(C16)=DAY($K$1+1),TRUNC(($D$5),8),D15) | E16: =TRUNC(((1+IPCA!#REF!))^(A16/22),8) | F16: =TRUNC((D16*E16),8) | G16: =ROUND(((1+$G$4)^(30/360))^(B16/31),9) | H16: =TRUNC((F16*G16-F16),8) | I16: =F16+H16
A17: =IF(DAY(C17)=DAY($K$1+1),1,A16+1) | B17: =IF(DAY(C17)=DAY($K$1+1),1,B16+1) | C17: =C16+1 | D17: =IF(DAY(C17)=DAY($K$1+1),TRUNC(($D$5),8),D16) | E17: =TRUNC(((1+IPCA!#REF!))^(A17/22),8) | F17: =TRUNC((D17*E17),8) | G17: =ROUND(((1+$G$4)^(30/360))^(B17/31),9) | H17: =TRUNC((F17*G17-F17),8) | I17: =F17+H17
A18: =IF(DAY(C18)=DAY($K$1+1),1,A17+1) | B18: =IF(DAY(C18)=DAY($K$1+1),1,B17+1) | C18: =C17+1 | D18: =IF(DAY(C18)=DAY($K$1+1),TRUNC(($D$5),8),D17) | E18: =TRUNC(((1+IPCA!#REF!))^(A18/22),8) | F18: =TRUNC((D18*E18),8) | G18: =ROUND(((1+$G$4)^(30/360))^(B18/31),9) | H18: =TRUNC((F18*G18-F18),8) | I18: =F18+H18
A19: =IF(DAY(C19)=DAY($K$1+1),1,A18+1) | B19: =IF(DAY(C19)=DAY($K$1+1),1,B18+1) | C19: =C18+1 | D19: =IF(DAY(C19)=DAY($K$1+1),TRUNC(($D$5),8),D18) | E19: =TRUNC(((1+IPCA!#REF!))^(A19/22),8) | F19: =TRUNC((D19*E19),8) | G19: =ROUND(((1+$G$4)^(30/360))^(B19/31),9) | H19: =TRUNC((F19*G19-F19),8) | I19: =F19+H19
A20: =IF(DAY(C20)=DAY($K$1+1),1,A19+1) | B20: =IF(DAY(C20)=DAY($K$1+1),1,B19+1) | C20: =C19+1 | D20: =IF(DAY(C20)=DAY($K$1+1),TRUNC(($D$5),8),D19) | E20: =TRUNC(((1+IPCA!#REF!))^(A20/22),8) | F20: =TRUNC((D20*E20),8) | G20: =ROUND(((1+$G$4)^(30/360))^(B20/(EDATE(C20-A20,1)-(C20-A20))),9) | H20: =TRUNC((F20*G20-F20),8) | I20: =F20+H20
A21: =IF(DAY(C21)=DAY($K$1+1),1,A20+1) | B21: =IF(DAY(C21)=DAY($K$1+1),1,B20+1) | C21: =C20+1 | D21: =IF(DAY(C21)=DAY($K$1+1),TRUNC(($D$5),8),D20) | E21: =TRUNC(((1+IPCA!#REF!))^(A21/22),8) | F21: =TRUNC((D21*E21),8) | G21: =ROUND(((1+$G$4)^(30/360))^(B21/(EDATE(C21-A21,1)-(C21-A21))),9) | H21: =TRUNC((F21*G21-F21),8) | I21: =F21+H21
A22: =IF(DAY(C22)=DAY($K$1+1),1,A21+1) | B22: =IF(DAY(C22)=DAY($K$1+1),1,B21+1) | C22: =C21+1 | D22: =IF(DAY(C22)=DAY($K$1+1),TRUNC(($D$5),8),D21) | E22: =TRUNC(((1+IPCA!#REF!))^(A22/22),8) | F22: =TRUNC((D22*E22),8) | G22: =ROUND(((1+$G$4)^(30/360))^(B22/(EDATE(C22-A22,1)-(C22-A22))),9) | H22: =TRUNC((F22*G22-F22),8) | I22: =F22+H22
A23: =IF(DAY(C23)=DAY($K$1+1),1,A22+1) | B23: =IF(DAY(C23)=DAY($K$1+1),1,B22+1) | C23: =C22+1 | D23: =IF(DAY(C23)=DAY($K$1+1),TRUNC(($D$5),8),D22) | E23: =TRUNC(((1+IPCA!#REF!))^(A23/22),8) | F23: =TRUNC((D23*E23),8) | G23: =ROUND(((1+$G$4)^(30/360))^(B23/(EDATE(C23-A23,1)-(C23-A23))),9) | H23: =TRUNC((F23*G23-F23),8) | I23: =F23+H23
A24: =IF(DAY(C24)=DAY($K$1+1),1,A23+1) | B24: =IF(DAY(C24)=DAY($K$1+1),1,B23+1) | C24: =C23+1 | D24: =IF(DAY(C24)=DAY($K$1+1),TRUNC(($D$5),8),D23) | E24: =TRUNC(((1+IPCA!#REF!))^(A24/22),8) | F24: =TRUNC((D24*E24),8) | G24: =ROUND(((1+$G$4)^(30/360))^(B24/(EDATE(C24-A24,1)-(C24-A24))),9) | H24: =TRUNC((F24*G24-F24),8) | I24: =F24+H24
A25: =IF(DAY(C25)=DAY($K$1+1),1,A24+1) | B25: =IF(DAY(C25)=DAY($K$1+1),1,B24+1) | C25: =C24+1 | D25: =IF(DAY(C25)=DAY($K$1+1),TRUNC(($D$5),8),D24) | E25: =TRUNC(((1+IPCA!#REF!))^(A25/22),8) | F25: =TRUNC((D25*E25),8) | G25: =ROUND(((1+$G$4)^(30/360))^(B25/(EDATE(C25-A25,1)-(C25-A25))),9) | H25: =TRUNC((F25*G25-F25),8) | I25: =F25+H25
A26: =IF(DAY(C26)=DAY($K$1+1),1,A25+1) | B26: =IF(DAY(C26)=DAY($K$1+1),1,B25+1) | C26: =C25+1 | D26: =IF(DAY(C26)=DAY($K$1+1),TRUNC(($D$5),8),D25) | E26: =TRUNC(((1+IPCA!#REF!))^(A26/22),8) | F26: =TRUNC((D26*E26),8) | G26: =ROUND(((1+$G$4)^(30/360))^(B26/(EDATE(C26-A26,1)-(C26-A26))),9) | H26: =TRUNC((F26*G26-F26),8) | I26: =F26+H26
A27: =IF(DAY(C27)=DAY($K$1+1),1,A26+1) | B27: =IF(DAY(C27)=DAY($K$1+1),1,B26+1) | C27: =C26+1 | D27: =IF(DAY(C27)=DAY($K$1+1),TRUNC(($D$5),8),D26) | E27: =TRUNC(((1+IPCA!#REF!))^(A27/22),8) | F27: =TRUNC((D27*E27),8) | G27: =ROUND(((1+$G$4)^(30/360))^(B27/(EDATE(C27-A27,1)-(C27-A27))),9) | H27: =TRUNC((F27*G27-F27),8) | I27: =F27+H27
A28: =IF(DAY(C28)=DAY($K$1+1),1,A27+1) | B28: =IF(DAY(C28)=DAY($K$1+1),1,B27+1) | C28: =C27+1 | D28: =IF(DAY(C28)=DAY($K$1+1),TRUNC(($D$5),8),D27) | E28: =TRUNC(((1+IPCA!#REF!))^(A28/22),8) | F28: =TRUNC((D28*E28),8) | G28: =ROUND(((1+$G$4)^(30/360))^(B28/(EDATE(C28-A28,1)-(C28-A28))),9) | H28: =TRUNC((F28*G28-F28),8) | I28: =F28+H28
A29: =IF(DAY(C29)=DAY($K$1+1),1,A28+1) | B29: =IF(DAY(C29)=DAY($K$1+1),1,B28+1) | C29: =C28+1 | D29: =IF(DAY(C29)=DAY($K$1+1),TRUNC(($D$5),8),D28) | E29: =TRUNC(((1+IPCA!#REF!))^(A29/22),8) | F29: =TRUNC((D29*E29),8) | G29: =ROUND(((1+$G$4)^(30/360))^(B29/(EDATE(C29-A29,1)-(C29-A29))),9) | H29: =TRUNC((F29*G29-F29),8) | I29: =F29+H29
A30: =IF(DAY(C30)=DAY($K$1+1),1,A29+1) | B30: =IF(DAY(C30)=DAY($K$1+1),1,B29+1) | C30: =C29+1 | D30: =IF(DAY(C30)=DAY($K$1+1),TRUNC(($D$5),8),D29) | E30: =TRUNC(((1+IPCA!#REF!))^(A30/22),8) | F30: =TRUNC((D30*E30),8) | G30: =ROUND(((1+$G$4)^(30/360))^(B30/(EDATE(C30-A30,1)-(C30-A30))),9) | H30: =TRUNC((F30*G30-F30),8) | I30: =F30+H30 | J30: JUROS | K30: AMORTIZAÇÃO | L30: AMEX | M30: RESIDUAL
A31: =IF(DAY(C31)=DAY($K$1+1),1,A30+1) | B31: =IF(DAY(C31)=DAY($K$1+1),1,B30+1) | C31: =C30+1 | D31: =IF(DAY(C31)=DAY($K$1+1),TRUNC(($D$5),8),D30) | E31: =TRUNC(((1+IPCA!#REF!))^(A31/22),8) | F31: =TRUNC((D31*E31),8) | G31: =ROUND(((1+$G$4)^(30/360))^(B31/(EDATE(C31-A31,1)-(C31-A31))),9) | H31: =TRUNC((F31*G31-F31),8) | I31: =F31+H31 | J31: =H31 | K31: 0 | L31: =L32/1540 | M31: =I31-J31-K31-L31
A32: =IF(DAY(C32)=DAY($K$1+1),1,A31+1) | B32: =IF(DAY(C32)=DAY($K$1+1),1,B31+1) | C32: =C31+1 | D32: =M31 | E32: =TRUNC(((1+IPCA!#REF!))^(A32/30),8) | F32: =TRUNC((D32*E32),8) | G32: =ROUND(((1+$G$4)^(30/360))^(B32/(EDATE(C32-A32,1)-(C32-A32))),9) | H32: =TRUNC((F32*G32-F32),8) | I32: =F32+H32 | J32: =J31*1540 | K32: =K31*1540 | L32: =(147598.16*0.7) | M32: =M31*1540
A33: =IF(DAY(C33)=DAY($K$1+1),1,A32+1) | B33: =IF(DAY(C33)=DAY($K$1+1),1,B32+1) | C33: =C32+1 | D33: =IF(DAY(C33)=DAY($K$1+1),TRUNC(($D$5),8),D32) | E33: =TRUNC(((1+IPCA!#REF!))^(A33/30),8) | F33: =TRUNC((D33*E33),8) | G33: =ROUND(((1+$G$4)^(30/360))^(B33/(EDATE(C33-A33,1)-(C33-A33))),9) | H33: =TRUNC((F33*G33-F33),8) | I33: =F33+H33
A34: =IF(DAY(C34)=DAY($K$1+1),1,A33+1) | B34: =IF(DAY(C34)=DAY($K$1+1),1,B33+1) | C34: =C33+1 | D34: =IF(DAY(C34)=DAY($K$1+1),TRUNC(($D$5),8),D33) | E34: =TRUNC(((1+IPCA!#REF!))^(A34/30),8) | F34: =TRUNC((D34*E34),8) | G34: =ROUND(((1+$G$4)^(30/360))^(B34/(EDATE(C34-A34,1)-(C34-A34))),9) | H34: =TRUNC((F34*G34-F34),8) | I34: =F34+H34 | J34: =SUM(J32:K32) | K34: TOTAL PMT
A35: =IF(DAY(C35)=DAY($K$1+1),1,A34+1) | B35: =IF(DAY(C35)=DAY($K$1+1),1,B34+1) | C35: =C34+1 | D35: =IF(DAY(C35)=DAY($K$1+1),TRUNC(($D$5),8),D34) | E35: =TRUNC(((1+IPCA!#REF!))^(A35/30),8) | F35: =TRUNC((D35*E35),8) | G35: =ROUND(((1+$G$4)^(30/360))^(B35/(EDATE(C35-A35,1)-(C35-A35))),9) | H35: =TRUNC((F35*G35-F35),8) | I35: =F35+H35 | J35: =SUM(J32:L32)
A36: =IF(DAY(C36)=DAY($K$1+1),1,A35+1) | B36: =IF(DAY(C36)=DAY($K$1+1),1,B35+1) | C36: =C35+1 | D36: =IF(DAY(C36)=DAY($K$1+1),TRUNC(($D$5),8),D35) | E36: =TRUNC(((1+IPCA!#REF!))^(A36/30),8) | F36: =TRUNC((D36*E36),8) | G36: =ROUND(((1+$G$4)^(30/360))^(B36/(EDATE(C36-A36,1)-(C36-A36))),9) | H36: =TRUNC((F36*G36-F36),8) | I36: =F36+H36
A37: =IF(DAY(C37)=DAY($K$1+1),1,A36+1) | B37: =IF(DAY(C37)=DAY($K$1+1),1,B36+1) | C37: =C36+1 | D37: =IF(DAY(C37)=DAY($K$1+1),TRUNC(($D$5),8),D36) | E37: =TRUNC(((1+IPCA!#REF!))^(A37/30),8) | F37: =TRUNC((D37*E37),8) | G37: =ROUND(((1+$G$4)^(30/360))^(B37/(EDATE(C37-A37,1)-(C37-A37))),9) | H37: =TRUNC((F37*G37-F37),8) | I37: =F37+H37
A38: =IF(DAY(C38)=DAY($K$1+1),1,A37+1) | B38: =IF(DAY(C38)=DAY($K$1+1),1,B37+1) | C38: =C37+1 | D38: =IF(DAY(C38)=DAY($K$1+1),TRUNC(($D$5),8),D37) | E38: =TRUNC(((1+IPCA!#REF!))^(A38/30),8) | F38: =TRUNC((D38*E38),8) | G38: =ROUND(((1+$G$4)^(30/360))^(B38/(EDATE(C38-A38,1)-(C38-A38))),9) | H38: =TRUNC((F38*G38-F38),8) | I38: =F38+H38
A39: =IF(DAY(C39)=DAY($K$1+1),1,A38+1) | B39: =IF(DAY(C39)=DAY($K$1+1),1,B38+1) | C39: =C38+1 | D39: =IF(DAY(C39)=DAY($K$1+1),TRUNC(($D$5),8),D38) | E39: =TRUNC(((1+IPCA!#REF!))^(A39/30),8) | F39: =TRUNC((D39*E39),8) | G39: =ROUND(((1+$G$4)^(30/360))^(B39/(EDATE(C39-A39,1)-(C39-A39))),9) | H39: =TRUNC((F39*G39-F39),8) | I39: =F39+H39
A40: =IF(DAY(C40)=DAY($K$1+1),1,A39+1) | B40: =IF(DAY(C40)=DAY($K$1+1),1,B39+1) | C40: =C39+1 | D40: =IF(DAY(C40)=DAY($K$1+1),TRUNC(($D$5),8),D39) | E40: =TRUNC(((1+IPCA!#REF!))^(A40/30),8) | F40: =TRUNC((D40*E40),8) | G40: =ROUND(((1+$G$4)^(30/360))^(B40/(EDATE(C40-A40,1)-(C40-A40))),9) | H40: =TRUNC((F40*G40-F40),8) | I40: =F40+H40
A41: =IF(DAY(C41)=DAY($K$1+1),1,A40+1) | B41: =IF(DAY(C41)=DAY($K$1+1),1,B40+1) | C41: =C40+1 | D41: =IF(DAY(C41)=DAY($K$1+1),TRUNC(($D$5),8),D40) | E41: =TRUNC(((1+IPCA!#REF!))^(A41/30),8) | F41: =TRUNC((D41*E41),8) | G41: =ROUND(((1+$G$4)^(30/360))^(B41/(EDATE(C41-A41,1)-(C41-A41))),9) | H41: =TRUNC((F41*G41-F41),8) | I41: =F41+H41
A42: =IF(DAY(C42)=DAY($K$1+1),1,A41+1) | B42: =IF(DAY(C42)=DAY($K$1+1),1,B41+1) | C42: =C41+1 | D42: =IF(DAY(C42)=DAY($K$1+1),TRUNC(($D$5),8),D41) | E42: =TRUNC(((1+IPCA!#REF!))^(A42/30),8) | F42: =TRUNC((D42*E42),8) | G42: =ROUND(((1+$G$4)^(30/360))^(B42/(EDATE(C42-A42,1)-(C42-A42))),9) | H42: =TRUNC((F42*G42-F42),8) | I42: =F42+H42
A43: =IF(DAY(C43)=DAY($K$1+1),1,A42+1) | B43: =IF(DAY(C43)=DAY($K$1+1),1,B42+1) | C43: =C42+1 | D43: =IF(DAY(C43)=DAY($K$1+1),TRUNC(($D$5),8),D42) | E43: =TRUNC(((1+IPCA!#REF!))^(A43/30),8) | F43: =TRUNC((D43*E43),8) | G43: =ROUND(((1+$G$4)^(30/360))^(B43/(EDATE(C43-A43,1)-(C43-A43))),9) | H43: =TRUNC((F43*G43-F43),8) | I43: =F43+H43
A44: =IF(DAY(C44)=DAY($K$1+1),1,A43+1) | B44: =IF(DAY(C44)=DAY($K$1+1),1,B43+1) | C44: =C43+1 | D44: =IF(DAY(C44)=DAY($K$1+1),TRUNC(($D$5),8),D43) | E44: =TRUNC(((1+IPCA!#REF!))^(A44/30),8) | F44: =TRUNC((D44*E44),8) | G44: =ROUND(((1+$G$4)^(30/360))^(B44/(EDATE(C44-A44,1)-(C44-A44))),9) | H44: =TRUNC((F44*G44-F44),8) | I44: =F44+H44
A45: =IF(DAY(C45)=DAY($K$1+1),1,A44+1) | B45: =IF(DAY(C45)=DAY($K$1+1),1,B44+1) | C45: =C44+1 | D45: =IF(DAY(C45)=DAY($K$1+1),TRUNC(($D$5),8),D44) | E45: =TRUNC(((1+IPCA!#REF!))^(A45/30),8) | F45: =TRUNC((D45*E45),8) | G45: =ROUND(((1+$G$4)^(30/360))^(B45/(EDATE(C45-A45,1)-(C45-A45))),9) | H45: =TRUNC((F45*G45-F45),8) | I45: =F45+H45
A46: =IF(DAY(C46)=DAY($K$1+1),1,A45+1) | B46: =IF(DAY(C46)=DAY($K$1+1),1,B45+1) | C46: =C45+1 | D46: =IF(DAY(C46)=DAY($K$1+1),TRUNC(($D$5),8),D45) | E46: =TRUNC(((1+IPCA!#REF!))^(A46/30),8) | F46: =TRUNC((D46*E46),8) | G46: =ROUND(((1+$G$4)^(30/360))^(B46/(EDATE(C46-A46,1)-(C46-A46))),9) | H46: =TRUNC((F46*G46-F46),8) | I46: =F46+H46
A47: =IF(DAY(C47)=DAY($K$1+1),1,A46+1) | B47: =IF(DAY(C47)=DAY($K$1+1),1,B46+1) | C47: =C46+1 | D47: =IF(DAY(C47)=DAY($K$1+1),TRUNC(($D$5),8),D46) | E47: =TRUNC(((1+IPCA!#REF!))^(A47/30),8) | F47: =TRUNC((D47*E47),8) | G47: =ROUND(((1+$G$4)^(30/360))^(B47/(EDATE(C47-A47,1)-(C47-A47))),9) | H47: =TRUNC((F47*G47-F47),8) | I47: =F47+H47
... A58: =IF(DAY(C58)=DAY($K$1+1),1,A57+1) | B58: =IF(DAY(C58)=DAY($K$1+1),1,B57+1) | C58: =C57+1 | D58: =IF(DAY(C58)=DAY($K$1+1),TRUNC(($D$5),8),D57) | E58: =TRUNC(((1+IPCA!#REF!))^(A58/30),8) | F58: =TRUNC((D58*E58),8) | G58: =ROUND(((1+$G$4)^(30/360))^(B58/(EDATE(C58-A58,1)-(C58-A58))),9) | H58: =TRUNC((F58*G58-F58),8) | I58: =F58+H58
A59: =IF(DAY(C59)=DAY($K$1+1),1,A58+1) | B59: =IF(DAY(C59)=DAY($K$1+1),1,B58+1) | C59: =C58+1 | D59: =IF(DAY(C59)=DAY($K$1+1),TRUNC(($D$5),8),D58) | E59: =TRUNC(((1+IPCA!#REF!))^(A59/30),8) | F59: =TRUNC((D59*E59),8) | G59: =ROUND(((1+$G$4)^(30/360))^(B59/(EDATE(C59-A59,1)-(C59-A59))),9) | H59: =TRUNC((F59*G59-F59),8) | I59: =F59+H59 | J59: CRI Integralizado: | K59: 1540
A60: =IF(DAY(C60)=DAY($K$1+1),1,A59+1) | B60: =IF(DAY(C60)=DAY($K$1+1),1,B59+1) | C60: =C59+1 | D60: =IF(DAY(C60)=DAY($K$1+1),TRUNC(($D$5),8),D59) | E60: =TRUNC(((1+IPCA!#REF!))^(A60/30),8) | F60: =TRUNC((D60*E60),8) | G60: =ROUND(((1+$G$4)^(30/360))^(B60/(EDATE(C60-A60,1)-(C60-A60))),9) | H60: =TRUNC((F60*G60-F60),8) | I60: =F60+H60 | J60: JUROS | K60: AMORTIZAÇÃO | L60: AMEX | M60: RESIDUAL
A61: =IF(DAY(C61)=DAY($K$1+1),1,A60+1) | B61: =IF(DAY(C61)=DAY($K$1+1),1,B60+1) | C61: =C60+1 | D61: =IF(DAY(C61)=DAY($K$1+1),TRUNC(($D$5),8),D60) | E61: =TRUNC(((1+IPCA!#REF!))^(A61/30),8) | F61: =TRUNC((D61*E61),8) | G61: =ROUND(((1+$G$4)^(30/360))^(B61/(EDATE(C61-A61,1)-(C61-A61))),9) | H61: =TRUNC((F61*G61-F61),8) | I61: =F61+H61 | J61: =H61 | K61: =F61*'Amort TS'!#REF! | L61: 0 | M61: =I61-J61-K61-L61
A62: =IF(DAY(C62)=DAY($K$1+1),1,A61+1) | B62: =IF(DAY(C62)=DAY($K$1+1),1,B61+1) | C62: =C61+1 | D62: =M61 | E62: =TRUNC(((1+IPCA!#REF!))^(A62/31),8) | F62: =TRUNC((D62*E62),8) | G62: =ROUND(((1+$G$4)^(30/360))^(B62/(EDATE(C62-A62,1)-(C62-A62))),9) | H62: =TRUNC((F62*G62-F62),8) | I62: =F62+H62 | J62: =J61*1540 | K62: =K61*1540 | L62: 0 | M62: =M61*1540
A63: =IF(DAY(C63)=DAY($K$1+1),1,A62+1) | B63: =IF(DAY(C63)=DAY($K$1+1),1,B62+1) | C63: =C62+1 | D63: =IF(DAY(C63)=DAY($K$1+1),TRUNC(($D$5),8),D62) | E63: =TRUNC(((1+IPCA!#REF!))^(A63/31),8) | F63: =TRUNC((D63*E63),8) | G63: =ROUND(((1+$G$4)^(30/360))^(B63/(EDATE(C63-A63,1)-(C63-A63))),9) | H63: =TRUNC((F63*G63-F63),8) | I63: =F63+H63
A64: =IF(DAY(C64)=DAY($K$1+1),1,A63+1) | B64: =IF(DAY(C64)=DAY($K$1+1),1,B63+1) | C64: =C63+1 | D64: =IF(DAY(C64)=DAY($K$1+1),TRUNC(($D$5),8),D63) | E64: =TRUNC(((1+IPCA!#REF!))^(A64/31),8) | F64: =TRUNC((D64*E64),8) | G64: =ROUND(((1+$G$4)^(30/360))^(B64/(EDATE(C64-A64,1)-(C64-A64))),9) | H64: =TRUNC((F64*G64-F64),8) | I64: =F64+H64 | J64: =SUM(J62:K62) | K64: TOTAL PMT
A65: =IF(DAY(C65)=DAY($K$1+1),1,A64+1) | B65: =IF(DAY(C65)=DAY($K$1+1),1,B64+1) | C65: =C64+1 | D65: =IF(DAY(C65)=DAY($K$1+1),TRUNC(($D$5),8),D64) | E65: =TRUNC(((1+IPCA!#REF!))^(A65/31),8) | F65: =TRUNC((D65*E65),8) | G65: =ROUND(((1+$G$4)^(30/360))^(B65/(EDATE(C65-A65,1)-(C65-A65))),9) | H65: =TRUNC((F65*G65-F65),8) | I65: =F65+H65 | J65: =SUM(J62:L62)
A66: =IF(DAY(C66)=DAY($K$1+1),1,A65+1) | B66: =IF(DAY(C66)=DAY($K$1+1),1,B65+1) | C66: =C65+1 | D66: =IF(DAY(C66)=DAY($K$1+1),TRUNC(($D$5),8),D65) | E66: =TRUNC(((1+IPCA!#REF!))^(A66/31),8) | F66: =TRUNC((D66*E66),8) | G66: =ROUND(((1+$G$4)^(30/360))^(B66/(EDATE(C66-A66,1)-(C66-A66))),9) | H66: =TRUNC((F66*G66-F66),8) | I66: =F66+H66
A67: =IF(DAY(C67)=DAY($K$1+1),1,A66+1) | B67: =IF(DAY(C67)=DAY($K$1+1),1,B66+1) | C67: =C66+1 | D67: =IF(DAY(C67)=DAY($K$1+1),TRUNC(($D$5),8),D66) | E67: =TRUNC(((1+IPCA!#REF!))^(A67/31),8) | F67: =TRUNC((D67*E67),8) | G67: =ROUND(((1+$G$4)^(30/360))^(B67/(EDATE(C67-A67,1)-(C67-A67))),9) | H67: =TRUNC((F67*G67-F67),8) | I67: =F67+H67
A68: =IF(DAY(C68)=DAY($K$1+1),1,A67+1) | B68: =IF(DAY(C68)=DAY($K$1+1),1,B67+1) | C68: =C67+1 | D68: =IF(DAY(C68)=DAY($K$1+1),TRUNC(($D$5),8),D67) | E68: =TRUNC(((1+IPCA!#REF!))^(A68/31),8) | F68: =TRUNC((D68*E68),8) | G68: =ROUND(((1+$G$4)^(30/360))^(B68/(EDATE(C68-A68,1)-(C68-A68))),9) | H68: =TRUNC((F68*G68-F68),8) | I68: =F68+H68
A69: =IF(DAY(C69)=DAY($K$1+1),1,A68+1) | B69: =IF(DAY(C69)=DAY($K$1+1),1,B68+1) | C69: =C68+1 | D69: =IF(DAY(C69)=DAY($K$1+1),TRUNC(($D$5),8),D68) | E69: =TRUNC(((1+IPCA!#REF!))^(A69/31),8) | F69: =TRUNC((D69*E69),8) | G69: =ROUND(((1+$G$4)^(30/360))^(B69/(EDATE(C69-A69,1)-(C69-A69))),9) | H69: =TRUNC((F69*G69-F69),8) | I69: =F69+H69
A70: =IF(DAY(C70)=DAY($K$1+1),1,A69+1) | B70: =IF(DAY(C70)=DAY($K$1+1),1,B69+1) | C70: =C69+1 | D70: =IF(DAY(C70)=DAY($K$1+1),TRUNC(($D$5),8),D69) | E70: =TRUNC(((1+IPCA!#REF!))^(A70/31),8) | F70: =TRUNC((D70*E70),8) | G70: =ROUND(((1+$G$4)^(30/360))^(B70/(EDATE(C70-A70,1)-(C70-A70))),9) | H70: =TRUNC((F70*G70-F70),8) | I70: =F70+H70
A71: =IF(DAY(C71)=DAY($K$1+1),1,A70+1) | B71: =IF(DAY(C71)=DAY($K$1+1),1,B70+1) | C71: =C70+1 | D71: =IF(DAY(C71)=DAY($K$1+1),TRUNC(($D$5),8),D70) | E71: =TRUNC(((1+IPCA!#REF!))^(A71/31),8) | F71: =TRUNC((D71*E71),8) | G71: =ROUND(((1+$G$4)^(30/360))^(B71/(EDATE(C71-A71,1)-(C71-A71))),9) | H71: =TRUNC((F71*G71-F71),8) | I71: =F71+H71
A72: =IF(DAY(C72)=DAY($K$1+1),1,A71+1) | B72: =IF(DAY(C72)=DAY($K$1+1),1,B71+1) | C72: =C71+1 | D72: =IF(DAY(C72)=DAY($K$1+1),TRUNC(($D$5),8),D71) | E72: =TRUNC(((1+IPCA!#REF!))^(A72/31),8) | F72: =TRUNC((D72*E72),8) | G72: =ROUND(((1+$G$4)^(30/360))^(B72/(EDATE(C72-A72,1)-(C72-A72))),9) | H72: =TRUNC((F72*G72-F72),8) | I72: =F72+H72
A73: =IF(DAY(C73)=DAY($K$1+1),1,A72+1) | B73: =IF(DAY(C73)=DAY($K$1+1),1,B72+1) | C73: =C72+1 | D73: =IF(DAY(C73)=DAY($K$1+1),TRUNC(($D$5),8),D72) | E73: =TRUNC(((1+IPCA!#REF!))^(A73/31),8) | F73: =TRUNC((D73*E73),8) | G73: =ROUND(((1+$G$4)^(30/360))^(B73/(EDATE(C73-A73,1)-(C73-A73))),9) | H73: =TRUNC((F73*G73-F73),8) | I73: =F73+H73
A74: =IF(DAY(C74)=DAY($K$1+1),1,A73+1) | B74: =IF(DAY(C74)=DAY($K$1+1),1,B73+1) | C74: =C73+1 | D74: =IF(DAY(C74)=DAY($K$1+1),TRUNC(($D$5),8),D73) | E74: =TRUNC(((1+IPCA!#REF!))^(A74/31),8) | F74: =TRUNC((D74*E74),8) | G74: =ROUND(((1+$G$4)^(30/360))^(B74/(EDATE(C74-A74,1)-(C74-A74))),9) | H74: =TRUNC((F74*G74-F74),8) | I74: =F74+H74
A75: =IF(DAY(C75)=DAY($K$1+1),1,A74+1) | B75: =IF(DAY(C75)=DAY($K$1+1),1,B74+1) | C75: =C74+1 | D75: =IF(DAY(C75)=DAY($K$1+1),TRUNC(($D$5),8),D74) | E75: =TRUNC(((1+IPCA!#REF!))^(A75/31),8) | F75: =TRUNC((D75*E75),8) | G75: =ROUND(((1+$G$4)^(30/360))^(B75/(EDATE(C75-A75,1)-(C75-A75))),9) | H75: =TRUNC((F75*G75-F75),8) | I75: =F75+H75
A76: =IF(DAY(C76)=DAY($K$1+1),1,A75+1) | B76: =IF(DAY(C76)=DAY($K$1+1),1,B75+1) | C76: =C75+1 | D76: =IF(DAY(C76)=DAY($K$1+1),TRUNC(($D$5),8),D75) | E76: =TRUNC(((1+IPCA!#REF!))^(A76/31),8) | F76: =TRUNC((D76*E76),8) | G76: =ROUND(((1+$G$4)^(30/360))^(B76/(EDATE(C76-A76,1)-(C76-A76))),9) | H76: =TRUNC((F76*G76-F76),8) | I76: =F76+H76
A77: =IF(DAY(C77)=DAY($K$1+1),1,A76+1) | B77: =IF(DAY(C77)=DAY($K$1+1),1,B76+1) | C77: =C76+1 | D77: =IF(DAY(C77)=DAY($K$1+1),TRUNC(($D$5),8),D76) | E77: =TRUNC(((1+IPCA!#REF!))^(A77/31),8) | F77: =TRUNC((D77*E77),8) | G77: =ROUND(((1+$G$4)^(30/360))^(B77/(EDATE(C77-A77,1)-(C77-A77))),9) | H77: =TRUNC((F77*G77-F77),8) | I77: =F77+H77
... A89: =IF(DAY(C89)=DAY($K$1+1),1,A88+1) | B89: =IF(DAY(C89)=DAY($K$1+1),1,B88+1) | C89: =C88+1 | D89: =IF(DAY(C89)=DAY($K$1+1),TRUNC(($D$5),8),D88) | E89: =TRUNC(((1+IPCA!#REF!))^(A89/31),8) | F89: =TRUNC((D89*E89),8) | G89: =ROUND(((1+$G$4)^(30/360))^(B89/(EDATE(C89-A89,1)-(C89-A89))),9) | H89: =TRUNC((F89*G89-F89),8) | I89: =F89+H89
A90: =IF(DAY(C90)=DAY($K$1+1),1,A89+1) | B90: =IF(DAY(C90)=DAY($K$1+1),1,B89+1) | C90: =C89+1 | D90: =IF(DAY(C90)=DAY($K$1+1),TRUNC(($D$5),8),D89) | E90: =TRUNC(((1+IPCA!#REF!))^(A90/31),8) | F90: =TRUNC((D90*E90),8) | G90: =ROUND(((1+$G$4)^(30/360))^(B90/(EDATE(C90-A90,1)-(C90-A90))),9) | H90: =TRUNC((F90*G90-F90),8) | I90: =F90+H90 | J90: CRI Integralizado: | K90: 1540
A91: =IF(DAY(C91)=DAY($K$1+1),1,A90+1) | B91: =IF(DAY(C91)=DAY($K$1+1),1,B90+1) | C91: =C90+1 | D91: =IF(DAY(C91)=DAY($K$1+1),TRUNC(($D$5),8),D90) | E91: =TRUNC(((1+IPCA!#REF!))^(A91/31),8) | F91: =TRUNC((D91*E91),8) | G91: =ROUND(((1+$G$4)^(30/360))^(B91/(EDATE(C91-A91,1)-(C91-A91))),9) | H91: =TRUNC((F91*G91-F91),8) | I91: =F91+H91 | J91: JUROS | K91: AMORTIZAÇÃO | L91: AMEX | M91: RESIDUAL
A92: =IF(DAY(C92)=DAY($K$1+1),1,A91+1) | B92: =IF(DAY(C92)=DAY($K$1+1),1,B91+1) | C92: =C91+1 | D92: =IF(DAY(C92)=DAY($K$1+1),TRUNC(($D$5),8),D91) | E92: =TRUNC(((1+IPCA!#REF!))^(A92/31),8) | F92: =TRUNC((D92*E92),8) | G92: =ROUND(((1+$G$4)^(30/360))^(B92/(EDATE(C92-A92,1)-(C92-A92))),9) | H92: =TRUNC((F92*G92-F92),8) | I92: =F92+H92 | J92: =H92 | K92: =F92*'Amort TS'!#REF! | L92: =L93/1540 | M92: =I92-J92-K92-L92
A93: =IF(DAY(C93)=DAY($K$1+1),1,A92+1) | B93: =IF(DAY(C93)=DAY($K$1+1),1,B92+1) | C93: =C92+1 | D93: =M92 | E93: =TRUNC(((1+IPCA!#REF!))^(A93/30),8) | F93: =TRUNC((D93*E93),8) | G93: =ROUND(((1+$G$4)^(30/360))^(B93/(EDATE(C93-A93,1)-(C93-A93))),9) | H93: =TRUNC((F93*G93-F93),8) | I93: =F93+H93 | J93: =J92*1540 | K93: =K92*1540 | L93: 70000 | M93: =M92*1540
A94: =IF(DAY(C94)=DAY($K$1+1),1,A93+1) | B94: =IF(DAY(C94)=DAY($K$1+1),1,B93+1) | C94: =C93+1 | D94: =IF(DAY(C94)=DAY($K$1+1),TRUNC(($D$5),8),D93) | E94: =TRUNC(((1+IPCA!#REF!))^(A94/30),8) | F94: =TRUNC((D94*E94),8) | G94: =ROUND(((1+$G$4)^(30/360))^(B94/(EDATE(C94-A94,1)-(C94-A94))),9) | H94: =TRUNC((F94*G94-F94),8) | I94: =F94+H94
A95: =IF(DAY(C95)=DAY($K$1+1),1,A94+1) | B95: =IF(DAY(C95)=DAY($K$1+1),1,B94+1) | C95: =C94+1 | D95: =IF(DAY(C95)=DAY($K$1+1),TRUNC(($D$5),8),D94) | E95: =TRUNC(((1+IPCA!#REF!))^(A95/30),8) | F95: =TRUNC((D95*E95),8) | G95: =ROUND(((1+$G$4)^(30/360))^(B95/(EDATE(C95-A95,1)-(C95-A95))),9) | H95: =TRUNC((F95*G95-F95),8) | I95: =F95+H95 | J95: =SUM(J93:K93) | K95: TOTAL PMT
A96: =IF(DAY(C96)=DAY($K$1+1),1,A95+1) | B96: =IF(DAY(C96)=DAY($K$1+1),1,B95+1) | C96: =C95+1 | D96: =IF(DAY(C96)=DAY($K$1+1),TRUNC(($D$5),8),D95) | E96: =TRUNC(((1+IPCA!#REF!))^(A96/30),8) | F96: =TRUNC((D96*E96),8) | G96: =ROUND(((1+$G$4)^(30/360))^(B96/(EDATE(C96-A96,1)-(C96-A96))),9) | H96: =TRUNC((F96*G96-F96),8) | I96: =F96+H96
A97: =IF(DAY(C97)=DAY($K$1+1),1,A96+1) | B97: =IF(DAY(C97)=DAY($K$1+1),1,B96+1) | C97: =C96+1 | D97: =IF(DAY(C97)=DAY($K$1+1),TRUNC(($D$5),8),D96) | E97: =TRUNC(((1+IPCA!#REF!))^(A97/30),8) | F97: =TRUNC((D97*E97),8) | G97: =ROUND(((1+$G$4)^(30/360))^(B97/(EDATE(C97-A97,1)-(C97-A97))),9) | H97: =TRUNC((F97*G97-F97),8) | I97: =F97+H97
A98: =IF(DAY(C98)=DAY($K$1+1),1,A97+1) | B98: =IF(DAY(C98)=DAY($K$1+1),1,B97+1) | C98: =C97+1 | D98: =IF(DAY(C98)=DAY($K$1+1),TRUNC(($D$5),8),D97) | E98: =TRUNC(((1+IPCA!#REF!))^(A98/30),8) | F98: =TRUNC((D98*E98),8) | G98: =ROUND(((1+$G$4)^(30/360))^(B98/(EDATE(C98-A98,1)-(C98-A98))),9) | H98: =TRUNC((F98*G98-F98),8) | I98: =F98+H98
A99: =IF(DAY(C99)=DAY($K$1+1),1,A98+1) | B99: =IF(DAY(C99)=DAY($K$1+1),1,B98+1) | C99: =C98+1 | D99: =IF(DAY(C99)=DAY($K$1+1),TRUNC(($D$5),8),D98) | E99: =TRUNC(((1+IPCA!#REF!))^(A99/30),8) | F99: =TRUNC((D99*E99),8) | G99: =ROUND(((1+$G$4)^(30/360))^(B99/(EDATE(C99-A99,1)-(C99-A99))),9) | H99: =TRUNC((F99*G99-F99),8) | I99: =F99+H99
A100: =IF(DAY(C100)=DAY($K$1+1),1,A99+1) | B100: =IF(DAY(C100)=DAY($K$1+1),1,B99+1) | C100: =C99+1 | D100: =IF(DAY(C100)=DAY($K$1+1),TRUNC(($D$5),8),D99) | E100: =TRUNC(((1+IPCA!#REF!))^(A100/30),8) | F100: =TRUNC((D100*E100),8) | G100: =ROUND(((1+$G$4)^(30/360))^(B100/(EDATE(C100-A100,1)-(C100-A100))),9) | H100: =TRUNC((F100*G100-F100),8) | I100: =F100+H100
A101: =IF(DAY(C101)=DAY($K$1+1),1,A100+1) | B101: =IF(DAY(C101)=DAY($K$1+1),1,B100+1) | C101: =C100+1 | D101: =IF(DAY(C101)=DAY($K$1+1),TRUNC(($D$5),8),D100) | E101: =TRUNC(((1+IPCA!#REF!))^(A101/30),8) | F101: =TRUNC((D101*E101),8) | G101: =ROUND(((1+$G$4)^(30/360))^(B101/(EDATE(C101-A101,1)-(C101-A101))),9) | H101: =TRUNC((F101*G101-F101),8) | I101: =F101+H101
A102: =IF(DAY(C102)=DAY($K$1+1),1,A101+1) | B102: =IF(DAY(C102)=DAY($K$1+1),1,B101+1) | C102: =C101+1 | D102: =IF(DAY(C102)=DAY($K$1+1),TRUNC(($D$5),8),D101) | E102: =TRUNC(((1+IPCA!#REF!))^(A102/30),8) | F102: =TRUNC((D102*E102),8) | G102: =ROUND(((1+$G$4)^(30/360))^(B102/(EDATE(C102-A102,1)-(C102-A102))),9) | H102: =TRUNC((F102*G102-F102),8) | I102: =F102+H102
A103: =IF(DAY(C103)=DAY($K$1+1),1,A102+1) | B103: =IF(DAY(C103)=DAY($K$1+1),1,B102+1) | C103: =C102+1 | D103: =IF(DAY(C103)=DAY($K$1+1),TRUNC(($D$5),8),D102) | E103: =TRUNC(((1+IPCA!#REF!))^(A103/30),8) | F103: =TRUNC((D103*E103),8) | G103: =ROUND(((1+$G$4)^(30/360))^(B103/(EDATE(C103-A103,1)-(C103-A103))),9) | H103: =TRUNC((F103*G103-F103),8) | I103: =F103+H103
A104: =IF(DAY(C104)=DAY($K$1+1),1,A103+1) | B104: =IF(DAY(C104)=DAY($K$1+1),1,B103+1) | C104: =C103+1 | D104: =IF(DAY(C104)=DAY($K$1+1),TRUNC(($D$5),8),D103) | E104: =TRUNC(((1+IPCA!#REF!))^(A104/30),8) | F104: =TRUNC((D104*E104),8) | G104: =ROUND(((1+$G$4)^(30/360))^(B104/(EDATE(C104-A104,1)-(C104-A104))),9) | H104: =TRUNC((F104*G104-F104),8) | I104: =F104+H104
A105: =IF(DAY(C105)=DAY($K$1+1),1,A104+1) | B105: =IF(DAY(C105)=DAY($K$1+1),1,B104+1) | C105: =C104+1 | D105: =IF(DAY(C105)=DAY($K$1+1),TRUNC(($D$5),8),D104) | E105: =TRUNC(((1+IPCA!#REF!))^(A105/30),8) | F105: =TRUNC((D105*E105),8) | G105: =ROUND(((1+$G$4)^(30/360))^(B105/(EDATE(C105-A105,1)-(C105-A105))),9) | H105: =TRUNC((F105*G105-F105),8) | I105: =F105+H105
A106: =IF(DAY(C106)=DAY($K$1+1),1,A105+1) | B106: =IF(DAY(C106)=DAY($K$1+1),1,B105+1) | C106: =C105+1 | D106: =IF(DAY(C106)=DAY($K$1+1),TRUNC(($D$5),8),D105) | E106: =TRUNC(((1+IPCA!#REF!))^(A106/30),8) | F106: =TRUNC((D106*E106),8) | G106: =ROUND(((1+$G$4)^(30/360))^(B106/(EDATE(C106-A106,1)-(C106-A106))),9) | H106: =TRUNC((F106*G106-F106),8) | I106: =F106+H106
A107: =IF(DAY(C107)=DAY($K$1+1),1,A106+1) | B107: =IF(DAY(C107)=DAY($K$1+1),1,B106+1) | C107: =C106+1 | D107: =IF(DAY(C107)=DAY($K$1+1),TRUNC(($D$5),8),D106) | E107: =TRUNC(((1+IPCA!#REF!))^(A107/30),8) | F107: =TRUNC((D107*E107),8) | G107: =ROUND(((1+$G$4)^(30/360))^(B107/(EDATE(C107-A107,1)-(C107-A107))),9) | H107: =TRUNC((F107*G107-F107),8) | I107: =F107+H107
... A119: =IF(DAY(C119)=DAY($K$1+1),1,A118+1) | B119: =IF(DAY(C119)=DAY($K$1+1),1,B118+1) | C119: =C118+1 | D119: =IF(DAY(C119)=DAY($K$1+1),TRUNC(($D$5),8),D118) | E119: =TRUNC(((1+IPCA!#REF!))^(A119/30),8) | F119: =TRUNC((D119*E119),8) | G119: =ROUND(((1+$G$4)^(30/360))^(B119/(EDATE(C119-A119,1)-(C119-A119))),9) | H119: =TRUNC((F119*G119-F119),8) | I119: =F119+H119
A120: =IF(DAY(C120)=DAY($K$1+1),1,A119+1) | B120: =IF(DAY(C120)=DAY($K$1+1),1,B119+1) | C120: =C119+1 | D120: =IF(DAY(C120)=DAY($K$1+1),TRUNC(($D$5),8),D119) | E120: =TRUNC(((1+IPCA!#REF!))^(A120/30),8) | F120: =TRUNC((D120*E120),8) | G120: =ROUND(((1+$G$4)^(30/360))^(B120/(EDATE(C120-A120,1)-(C120-A120))),9) | H120: =TRUNC((F120*G120-F120),8) | I120: =F120+H120 | J120: CRI Integralizado: | K120: 1540
A121: =IF(DAY(C121)=DAY($K$1+1),1,A120+1) | B121: =IF(DAY(C121)=DAY($K$1+1),1,B120+1) | C121: =C120+1 | D121: =IF(DAY(C121)=DAY($K$1+1),TRUNC(($D$5),8),D120) | E121: =TRUNC(((1+IPCA!#REF!))^(A121/30),8) | F121: =TRUNC((D121*E121),8) | G121: =ROUND(((1+$G$4)^(30/360))^(B121/(EDATE(C121-A121,1)-(C121-A121))),9) | H121: =TRUNC((F121*G121-F121),8) | I121: =F121+H121 | J121: JUROS | K121: AMORTIZAÇÃO | L121: AMEX | M121: RESIDUAL
A122: =IF(DAY(C122)=DAY($K$1+1),1,A121+1) | B122: =IF(DAY(C122)=DAY($K$1+1),1,B121+1) | C122: =C121+1 | D122: =IF(DAY(C122)=DAY($K$1+1),TRUNC(($D$5),8),D121) | E122: =TRUNC(((1+IPCA!#REF!))^(A122/30),8) | F122: =TRUNC((D122*E122),8) | G122: =ROUND(((1+$G$4)^(30/360))^(B122/(EDATE(C122-A122,1)-(C122-A122))),9) | H122: =TRUNC((F122*G122-F122),8) | I122: =F122+H122 | J122: =H122 | K122: =F122*'Amort TS'!#REF! | L122: 0 | M122: =I122-J122-K122-L122
A123: =IF(DAY(C123)=DAY($K$1+1),1,A122+1) | B123: =IF(DAY(C123)=DAY($K$1+1),1,B122+1) | C123: =C122+1 | D123: =M122 | E123: =TRUNC(((1+IPCA!#REF!))^(A123/31),8) | F123: =TRUNC((D123*E123),8) | G123: =ROUND(((1+$G$4)^(30/360))^(B123/(EDATE(C123-A123,1)-(C123-A123))),9) | H123: =TRUNC((F123*G123-F123),8) | I123: =F123+H123 | J123: =J122*1540 | K123: =K122*1540 | L123: 0 | M123: =M122*1540
A124: =IF(DAY(C124)=DAY($K$1+1),1,A123+1) | B124: =IF(DAY(C124)=DAY($K$1+1),1,B123+1) | C124: =C123+1 | D124: =IF(DAY(C124)=DAY($K$1+1),TRUNC(($D$5),8),D123) | E124: =TRUNC(((1+IPCA!#REF!))^(A124/31),8) | F124: =TRUNC((D124*E124),8) | G124: =ROUND(((1+$G$4)^(30/360))^(B124/(EDATE(C124-A124,1)-(C124-A124))),9) | H124: =TRUNC((F124*G124-F124),8) | I124: =F124+H124
A125: =IF(DAY(C125)=DAY($K$1+1),1,A124+1) | B125: =IF(DAY(C125)=DAY($K$1+1),1,B124+1) | C125: =C124+1 | D125: =IF(DAY(C125)=DAY($K$1+1),TRUNC(($D$5),8),D124) | E125: =TRUNC(((1+IPCA!#REF!))^(A125/31),8) | F125: =TRUNC((D125*E125),8) | G125: =ROUND(((1+$G$4)^(30/360))^(B125/(EDATE(C125-A125,1)-(C125-A125))),9) | H125: =TRUNC((F125*G125-F125),8) | I125: =F125+H125 | J125: =SUM(J123:K123) | K125: TOTAL PMT
A126: =IF(DAY(C126)=DAY($K$1+1),1,A125+1) | B126: =IF(DAY(C126)=DAY($K$1+1),1,B125+1) | C126: =C125+1 | D126: =IF(DAY(C126)=DAY($K$1+1),TRUNC(($D$5),8),D125) | E126: =TRUNC(((1+IPCA!#REF!))^(A126/31),8) | F126: =TRUNC((D126*E126),8) | G126: =ROUND(((1+$G$4)^(30/360))^(B126/(EDATE(C126-A126,1)-(C126-A126))),9) | H126: =TRUNC((F126*G126-F126),8) | I126: =F126+H126
A127: =IF(DAY(C127)=DAY($K$1+1),1,A126+1) | B127: =IF(DAY(C127)=DAY($K$1+1),1,B126+1) | C127: =C126+1 | D127: =IF(DAY(C127)=DAY($K$1+1),TRUNC(($D$5),8),D126) | E127: =TRUNC(((1+IPCA!#REF!))^(A127/31),8) | F127: =TRUNC((D127*E127),8) | G127: =ROUND(((1+$G$4)^(30/360))^(B127/(EDATE(C127-A127,1)-(C127-A127))),9) | H127: =TRUNC((F127*G127-F127),8) | I127: =F127+H127
A128: =IF(DAY(C128)=DAY($K$1+1),1,A127+1) | B128: =IF(DAY(C128)=DAY($K$1+1),1,B127+1) | C128: =C127+1 | D128: =IF(DAY(C128)=DAY($K$1+1),TRUNC(($D$5),8),D127) | E128: =TRUNC(((1+IPCA!#REF!))^(A128/31),8) | F128: =TRUNC((D128*E128),8) | G128: =ROUND(((1+$G$4)^(30/360))^(B128/(EDATE(C128-A128,1)-(C128-A128))),9) | H128: =TRUNC((F128*G128-F128),8) | I128: =F128+H128
A129: =IF(DAY(C129)=DAY($K$1+1),1,A128+1) | B129: =IF(DAY(C129)=DAY($K$1+1),1,B128+1) | C129: =C128+1 | D129: =IF(DAY(C129)=DAY($K$1+1),TRUNC(($D$5),8),D128) | E129: =TRUNC(((1+IPCA!#REF!))^(A129/31),8) | F129: =TRUNC((D129*E129),8) | G129: =ROUND(((1+$G$4)^(30/360))^(B129/(EDATE(C129-A129,1)-(C129-A129))),9) | H129: =TRUNC((F129*G129-F129),8) | I129: =F129+H129
A130: =IF(DAY(C130)=DAY($K$1+1),1,A129+1) | B130: =IF(DAY(C130)=DAY($K$1+1),1,B129+1) | C130: =C129+1 | D130: =IF(DAY(C130)=DAY($K$1+1),TRUNC(($D$5),8),D129) | E130: =TRUNC(((1+IPCA!#REF!))^(A130/31),8) | F130: =TRUNC((D130*E130),8) | G130: =ROUND(((1+$G$4)^(30/360))^(B130/(EDATE(C130-A130,1)-(C130-A130))),9) | H130: =TRUNC((F130*G130-F130),8) | I130: =F130+H130
A131: =IF(DAY(C131)=DAY($K$1+1),1,A130+1) | B131: =IF(DAY(C131)=DAY($K$1+1),1,B130+1) | C131: =C130+1 | D131: =IF(DAY(C131)=DAY($K$1+1),TRUNC(($D$5),8),D130) | E131: =TRUNC(((1+IPCA!#REF!))^(A131/31),8) | F131: =TRUNC((D131*E131),8) | G131: =ROUND(((1+$G$4)^(30/360))^(B131/(EDATE(C131-A131,1)-(C131-A131))),9) | H131: =TRUNC((F131*G131-F131),8) | I131: =F131+H131
A132: =IF(DAY(C132)=DAY($K$1+1),1,A131+1) | B132: =IF(DAY(C132)=DAY($K$1+1),1,B131+1) | C132: =C131+1 | D132: =IF(DAY(C132)=DAY($K$1+1),TRUNC(($D$5),8),D131) | E132: =TRUNC(((1+IPCA!#REF!))^(A132/31),8) | F132: =TRUNC((D132*E132),8) | G132: =ROUND(((1+$G$4)^(30/360))^(B132/(EDATE(C132-A132,1)-(C132-A132))),9) | H132: =TRUNC((F132*G132-F132),8) | I132: =F132+H132
...

Sheet 22F1187231
B1: LOGOS SECURITIZADORA | K1: Data de Vencimento: | L1: 48908 | N1: 1ª Integralização:
B2: 46ª Série da 1ª Emissão (22F1187231) | K2: Data de Emissão: | L2: 44739 | N2: 44754
B3: dC | C3: dJ | D3: DATA | E3: VNe | F3: Fator IPCA | G3: VNa | H3: FatorJuros | I3: JUROS | J3: PU | K3: Valor Nominal Emissão: | L3: 1 | N3: 1113210
H4: 0.095 | K4: Início da Rentabilidade | L4: 44754 | M4: (J + A)
A5: 1 | B5: 0 | C5: 0 | D5: 44753 | E5: 1 | F5: =TRUNC(((1+VLOOKUP(A5,IPCA!$A$2:$C$140,3,0)))^(C5/30),8) | G5: =TRUNC((E5*F5),8) | H5: =ROUND(((1+$H$4)^(30/360))^(C5/30),9) | I5: =TRUNC((G5*H5-G5),8) | J5: =G5+I5
A6: 1 | B6: =IF(DAY(D6)=DAY($L$1+1),1,B5+1) | C6: =IF(DAY(D6)=DAY($L$1+1),1,C5+1) | D6: =D5+1 | E6: 1 | F6: =TRUNC(((1+VLOOKUP(A6,IPCA!$A$2:$C$140,3,0)))^(C6/30),8) | G6: =TRUNC((E6*F6),8) | H6: =ROUND(((1+$H$4)^(30/360))^(C6/30),9) | I6: =TRUNC((G6*H6-G6),8) | J6: =G6+I6 | K6: Cri Integralizado | L6: 1113210
A7: =IF(DAY(D7)=DAY($L$1+1),A6+1,A6) | B7: =IF(DAY(D7)=DAY($L$1+1),1,B6+1) | C7: =IF(DAY(D7)=DAY($L$1+1),1,C6+1) | D7: =D6+1 | E7: =IF(DAY(D7)=DAY($L$1+1),TRUNC((N6),8),E6) | F7: =TRUNC(((1+VLOOKUP(A7,IPCA!$A$2:$C$140,3,0)))^(C7/30),8) | G7: =TRUNC((E7*F7),8) | H7: =ROUND(((1+$H$4)^(30/360))^(C7/30),9) | I7: =TRUNC((G7*H7-G7),8) | J7: =G7+I7
A8: =IF(DAY(D8)=DAY($L$1+1),A7+1,A7) | B8: =IF(DAY(D8)=DAY($L$1+1),1,B7+1) | C8: =IF(DAY(D8)=DAY($L$1+1),1,C7+1) | D8: =D7+1 | E8: =IF(DAY(D8)=DAY($L$1+1),TRUNC((N7),8),E7) | F8: =TRUNC(((1+VLOOKUP(A8,IPCA!$A$2:$C$140,3,0)))^(C8/30),8) | G8: =TRUNC((E8*F8),8) | H8: =ROUND(((1+$H$4)^(30/360))^(C8/30),9) | I8: =TRUNC((G8*H8-G8),8) | J8: =G8+I8
A9: =IF(DAY(D9)=DAY($L$1+1),A8+1,A8) | B9: =IF(DAY(D9)=DAY($L$1+1),1,B8+1) | C9: =IF(DAY(D9)=DAY($L$1+1),1,C8+1) | D9: =D8+1 | E9: =IF(DAY(D9)=DAY($L$1+1),TRUNC((N8),8),E8) | F9: =TRUNC(((1+VLOOKUP(A9,IPCA!$A$2:$C$140,3,0)))^(C9/30),8) | G9: =TRUNC((E9*F9),8) | H9: =ROUND(((1+$H$4)^(30/360))^(C9/30),9) | I9: =TRUNC((G9*H9-G9),8) | J9: =G9+I9
A10: =IF(DAY(D10)=DAY($L$1+1),A9+1,A9) | B10: =IF(DAY(D10)=DAY($L$1+1),1,B9+1) | C10: =IF(DAY(D10)=DAY($L$1+1),1,C9+1) | D10: =D9+1 | E10: =IF(DAY(D10)=DAY($L$1+1),TRUNC((N9),8),E9) | F10: =TRUNC(((1+VLOOKUP(A10,IPCA!$A$2:$C$140,3,0)))^(C10/30),8) | G10: =TRUNC((E10*F10),8) | H10: =ROUND(((1+$H$4)^(30/360))^(C10/30),9) | I10: =TRUNC((G10*H10-G10),8) | J10: =G10+I10
A11: =IF(DAY(D11)=DAY($L$1+1),A10+1,A10) | B11: =IF(DAY(D11)=DAY($L$1+1),1,B10+1) | C11: =IF(DAY(D11)=DAY($L$1+1),1,C10+1) | D11: =D10+1 | E11: =IF(DAY(D11)=DAY($L$1+1),TRUNC((N10),8),E10) | F11: =TRUNC(((1+VLOOKUP(A11,IPCA!$A$2:$C$140,3,0)))^(C11/30),8) | G11: =TRUNC((E11*F11),8) | H11: =ROUND(((1+$H$4)^(30/360))^(C11/30),9) | I11: =TRUNC((G11*H11-G11),8) | J11: =G11+I11
A12: =IF(DAY(D12)=DAY($L$1+1),A11+1,A11) | B12: =IF(DAY(D12)=DAY($L$1+1),1,B11+1) | C12: =IF(DAY(D12)=DAY($L$1+1),1,C11+1) | D12: =D11+1 | E12: =IF(DAY(D12)=DAY($L$1+1),TRUNC((N11),8),E11) | F12: =TRUNC(((1+VLOOKUP(A12,IPCA!$A$2:$C$140,3,0)))^(C12/30),8) | G12: =TRUNC((E12*F12),8) | H12: =ROUND(((1+$H$4)^(30/360))^(C12/30),9) | I12: =TRUNC((G12*H12-G12),8) | J12: =G12+I12 | K12: Cri Integralizado | L12: 668088
A13: =IF(DAY(D13)=DAY($L$1+1),A12+1,A12) | B13: =IF(DAY(D13)=DAY($L$1+1),1,B12+1) | C13: =IF(DAY(D13)=DAY($L$1+1),1,C12+1) | D13: =D12+1 | E13: =IF(DAY(D13)=DAY($L$1+1),TRUNC((N12),8),E12) | F13: =TRUNC(((1+VLOOKUP(A13,IPCA!$A$2:$C$140,3,0)))^(C13/30),8) | G13: =TRUNC((E13*F13),8) | H13: =ROUND(((1+$H$4)^(30/360))^(C13/30),9) | I13: =TRUNC((G13*H13-G13),8) | J13: =G13+I13
A14: =IF(DAY(D14)=DAY($L$1+1),A13+1,A13) | B14: =IF(DAY(D14)=DAY($L$1+1),1,B13+1) | C14: =IF(DAY(D14)=DAY($L$1+1),1,C13+1) | D14: =D13+1 | E14: =IF(DAY(D14)=DAY($L$1+1),TRUNC((N13),8),E13) | F14: =TRUNC(((1+VLOOKUP(A14,IPCA!$A$2:$C$140,3,0)))^(C14/30),8) | G14: =TRUNC((E14*F14),8) | H14: =ROUND(((1+$H$4)^(30/360))^(C14/30),9) | I14: =TRUNC((G14*H14-G14),8) | J14: =G14+I14
A15: =IF(DAY(D15)=DAY($L$1+1),A14+1,A14) | B15: =IF(DAY(D15)=DAY($L$1+1),1,B14+1) | C15: =IF(DAY(D15)=DAY($L$1+1),1,C14+1) | D15: =D14+1 | E15: =IF(DAY(D15)=DAY($L$1+1),TRUNC((N14),8),E14) | F15: =TRUNC(((1+VLOOKUP(A15,IPCA!$A$2:$C$140,3,0)))^(C15/30),8) | G15: =TRUNC((E15*F15),8) | H15: =ROUND(((1+$H$4)^(30/360))^(C15/30),9) | I15: =TRUNC((G15*H15-G15),8) | J15: =G15+I15
A16: =IF(DAY(D16)=DAY($L$1+1),A15+1,A15) | B16: =IF(DAY(D16)=DAY($L$1+1),1,B15+1) | C16: =IF(DAY(D16)=DAY($L$1+1),1,C15+1) | D16: =D15+1 | E16: =IF(DAY(D16)=DAY($L$1+1),TRUNC((N15),8),E15) | F16: =TRUNC(((1+VLOOKUP(A16,IPCA!$A$2:$C$140,3,0)))^(C16/30),8) | G16: =TRUNC((E16*F16),8) | H16: =ROUND(((1+$H$4)^(30/360))^(C16/30),9) | I16: =TRUNC((G16*H16-G16),8) | J16: =G16+I16
A17: =IF(DAY(D17)=DAY($L$1+1),A16+1,A16) | B17: =IF(DAY(D17)=DAY($L$1+1),1,B16+1) | C17: =IF(DAY(D17)=DAY($L$1+1),1,C16+1) | D17: =D16+1 | E17: =IF(DAY(D17)=DAY($L$1+1),TRUNC((N16),8),E16) | F17: =TRUNC(((1+VLOOKUP(A17,IPCA!$A$2:$C$140,3,0)))^(C17/30),8) | G17: =TRUNC((E17*F17),8) | H17: =ROUND(((1+$H$4)^(30/360))^(C17/30),9) | I17: =TRUNC((G17*H17-G17),8) | J17: =G17+I17 | K17: Cri Integralizado | L17: =1113210+L12
A18: =IF(DAY(D18)=DAY($L$1+1),A17+1,A17) | B18: =IF(DAY(D18)=DAY($L$1+1),1,B17+1) | C18: =IF(DAY(D18)=DAY($L$1+1),1,C17+1) | D18: =D17+1 | E18: =IF(DAY(D18)=DAY($L$1+1),TRUNC((N17),8),E17) | F18: =TRUNC(((1+VLOOKUP(A18,IPCA!$A$2:$C$140,3,0)))^(C18/30),8) | G18: =TRUNC((E18*F18),8) | H18: =ROUND(((1+$H$4)^(30/360))^(C18/30),9) | I18: =TRUNC((G18*H18-G18),8) | J18: =G18+I18 | K18: JUROS | L18: AMORTIZAÇÃO | M18: AMEX | N18: RESIDUAL
A19: =IF(DAY(D19)=DAY($L$1+1),A18+1,A18) | B19: =IF(DAY(D19)=DAY($L$1+1),1,B18+1) | C19: =IF(DAY(D19)=DAY($L$1+1),1,C18+1) | D19: =D18+1 | E19: =IF(DAY(D19)=DAY($L$1+1),TRUNC((N18),8),E18) | F19: =TRUNC(((1+VLOOKUP(A19,IPCA!$A$2:$C$140,3,0)))^(C19/30),8) | G19: =TRUNC((E19*F19),8) | H19: =ROUND(((1+$H$4)^(30/360))^(C19/30),9) | I19: =TRUNC((G19*H19-G19),8) | J19: =G19+I19 | K19: 0 | L19: 0 | M19: 0 | N19: 1100000
A20: =IF(DAY(D20)=DAY($L$1+1),A19+1,A19) | B20: =IF(DAY(D20)=DAY($L$1+1),1,B19+1) | C20: =IF(DAY(D20)=DAY($L$1+1),1,C19+1) | D20: =D19+1 | E20: =IF(DAY(D20)=DAY($L$1+1),TRUNC((N19),8),E19) | F20: =TRUNC(((1+VLOOKUP(A20,IPCA!$A$2:$C$140,3,0)))^(C20/(EDATE(D20-C20,1)-(D20-C20))),8) | G20: =TRUNC((E20*F20),8) | H20: =ROUND(((1+$H$4)^(30/360))^(C20/(EDATE(D20-B20,1)-(D20-B20))),9) | I20: =TRUNC((G20*H20-G20),8) | J20: =G20+I20 | K20: =K19*L17 | L20: =L19*L17 | M20: =M19*L17 | N20: =N19*L17
A21: =IF(DAY(D21)=DAY($L$1+1),A20+1,A20) | B21: =IF(DAY(D21)=DAY($L$1+1),1,B20+1) | C21: =IF(DAY(D21)=DAY($L$1+1),1,C20+1) | D21: =D20+1 | E21: =IF(DAY(D21)=DAY($L$1+1),TRUNC((N20),8),E20) | F21: =TRUNC(((1+VLOOKUP(A21,IPCA!$A$2:$C$140,3,0)))^(C21/(EDATE(D21-C21,1)-(D21-C21))),8) | G21: =TRUNC((E21*F21),8) | H21: =ROUND(((1+$H$4)^(30/360))^(C21/(EDATE(D21-B21,1)-(D21-B21))),9) | I21: =TRUNC((G21*H21-G21),8) | J21: =G21+I21
A22: =IF(DAY(D22)=DAY($L$1+1),A21+1,A21) | B22: =IF(DAY(D22)=DAY($L$1+1),1,B21+1) | C22: =IF(DAY(D22)=DAY($L$1+1),1,C21+1) | D22: =D21+1 | E22: =IF(DAY(D22)=DAY($L$1+1),TRUNC((#REF!),8),E21) | F22: =TRUNC(((1+VLOOKUP(A22,IPCA!$A$2:$C$140,3,0)))^(C22/(EDATE(D22-C22,1)-(D22-C22))),8) | G22: =TRUNC((E22*F22),8) | H22: =ROUND(((1+$H$4)^(30/360))^(C22/(EDATE(D22-B22,1)-(D22-B22))),9) | I22: =TRUNC((G22*H22-G22),8) | J22: =G22+I22
A23: =IF(DAY(D23)=DAY($L$1+1),A22+1,A22) | B23: =IF(DAY(D23)=DAY($L$1+1),1,B22+1) | C23: =IF(DAY(D23)=DAY($L$1+1),1,C22+1) | D23: =D22+1 | E23: =IF(DAY(D23)=DAY($L$1+1),TRUNC((#REF!),8),E22) | F23: =TRUNC(((1+VLOOKUP(A23,IPCA!$A$2:$C$140,3,0)))^(C23/(EDATE(D23-C23,1)-(D23-C23))),8) | G23: =TRUNC((E23*F23),8) | H23: =ROUND(((1+$H$4)^(30/360))^(C23/(EDATE(D23-B23,1)-(D23-B23))),9) | I23: =TRUNC((G23*H23-G23),8) | J23: =G23+I23 | K23: 1.006196
A24: =IF(DAY(D24)=DAY($L$1+1),A23+1,A23) | B24: =IF(DAY(D24)=DAY($L$1+1),1,B23+1) | C24: =IF(DAY(D24)=DAY($L$1+1),1,C23+1) | D24: =D23+1 | E24: =IF(DAY(D24)=DAY($L$1+1),TRUNC((#REF!),8),E23) | F24: =TRUNC(((1+VLOOKUP(A24,IPCA!$A$2:$C$140,3,0)))^(C24/(EDATE(D24-C24,1)-(D24-C24))),8) | G24: =TRUNC((E24*F24),8) | H24: =ROUND(((1+$H$4)^(30/360))^(C24/(EDATE(D24-B24,1)-(D24-B24))),9) | I24: =TRUNC((G24*H24-G24),8) | J24: =G24+I24 | K24: =J20-K23
A25: =IF(DAY(D25)=DAY($L$1+1),A24+1,A24) | B25: =IF(DAY(D25)=DAY($L$1+1),1,B24+1) | C25: =IF(DAY(D25)=DAY($L$1+1),1,C24+1) | D25: =D24+1 | E25: =IF(DAY(D25)=DAY($L$1+1),TRUNC((#REF!),8),E24) | F25: =TRUNC(((1+VLOOKUP(A25,IPCA!$A$2:$C$140,3,0)))^(C25/(EDATE(D25-C25,1)-(D25-C25))),8) | G25: =TRUNC((E25*F25),8) | H25: =ROUND(((1+$H$4)^(30/360))^(C25/(EDATE(D25-B25,1)-(D25-B25))),9) | I25: =TRUNC((G25*H25-G25),8) | J25: =G25+I25
A26: =IF(DAY(D26)=DAY($L$1+1),A25+1,A25) | B26: =IF(DAY(D26)=DAY($L$1+1),1,B25+1) | C26: =IF(DAY(D26)=DAY($L$1+1),1,C25+1) | D26: =D25+1 | E26: =IF(DAY(D26)=DAY($L$1+1),TRUNC((#REF!),8),E25) | F26: =TRUNC(((1+VLOOKUP(A26,IPCA!$A$2:$C$140,3,0)))^(C26/(EDATE(D26-C26,1)-(D26-C26))),8) | G26: =TRUNC((E26*F26),8) | H26: =ROUND(((1+$H$4)^(30/360))^(C26/(EDATE(D26-B26,1)-(D26-B26))),9) | I26: =TRUNC((G26*H26-G26),8) | J26: =G26+I26
A27: =IF(DAY(D27)=DAY($L$1+1),A26+1,A26) | B27: =IF(DAY(D27)=DAY($L$1+1),1,B26+1) | C27: =IF(DAY(D27)=DAY($L$1+1),1,C26+1) | D27: =D26+1 | E27: =IF(DAY(D27)=DAY($L$1+1),TRUNC((#REF!),8),E26) | F27: =TRUNC(((1+VLOOKUP(A27,IPCA!$A$2:$C$140,3,0)))^(C27/(EDATE(D27-C27,1)-(D27-C27))),8) | G27: =TRUNC((E27*F27),8) | H27: =ROUND(((1+$H$4)^(30/360))^(C27/(EDATE(D27-B27,1)-(D27-B27))),9) | I27: =TRUNC((G27*H27-G27),8) | J27: =G27+I27
A28: =IF(DAY(D28)=DAY($L$1+1),A27+1,A27) | B28: =IF(DAY(D28)=DAY($L$1+1),1,B27+1) | C28: =IF(DAY(D28)=DAY($L$1+1),1,C27+1) | D28: =D27+1 | E28: =IF(DAY(D28)=DAY($L$1+1),TRUNC((#REF!),8),E27) | F28: =TRUNC(((1+VLOOKUP(A28,IPCA!$A$2:$C$140,3,0)))^(C28/(EDATE(D28-C28,1)-(D28-C28))),8) | G28: =TRUNC((E28*F28),8) | H28: =ROUND(((1+$H$4)^(30/360))^(C28/(EDATE(D28-B28,1)-(D28-B28))),9) | I28: =TRUNC((G28*H28-G28),8) | J28: =G28+I28
A29: =IF(DAY(D29)=DAY($L$1+1),A28+1,A28) | B29: =IF(DAY(D29)=DAY($L$1+1),1,B28+1) | C29: =IF(DAY(D29)=DAY($L$1+1),1,C28+1) | D29: =D28+1 | E29: =IF(DAY(D29)=DAY($L$1+1),TRUNC((#REF!),8),E28) | F29: =TRUNC(((1+VLOOKUP(A29,IPCA!$A$2:$C$140,3,0)))^(C29/(EDATE(D29-C29,1)-(D29-C29))),8) | G29: =TRUNC((E29*F29),8) | H29: =ROUND(((1+$H$4)^(30/360))^(C29/(EDATE(D29-B29,1)-(D29-B29))),9) | I29: =TRUNC((G29*H29-G29),8) | J29: =G29+I29
A30: =IF(DAY(D30)=DAY($L$1+1),A29+1,A29) | B30: =IF(DAY(D30)=DAY($L$1+1),1,B29+1) | C30: =IF(DAY(D30)=DAY($L$1+1),1,C29+1) | D30: =D29+1 | E30: =IF(DAY(D30)=DAY($L$1+1),TRUNC((#REF!),8),E29) | F30: =TRUNC(((1+VLOOKUP(A30,IPCA!$A$2:$C$140,3,0)))^(C30/(EDATE(D30-C30,1)-(D30-C30))),8) | G30: =TRUNC((E30*F30),8) | H30: =ROUND(((1+$H$4)^(30/360))^(C30/(EDATE(D30-B30,1)-(D30-B30))),9) | I30: =TRUNC((G30*H30-G30),8) | J30: =G30+I30
A31: =IF(DAY(D31)=DAY($L$1+1),A30+1,A30) | B31: =IF(DAY(D31)=DAY($L$1+1),1,B30+1) | C31: =IF(DAY(D31)=DAY($L$1+1),1,C30+1) | D31: =D30+1 | E31: =IF(DAY(D31)=DAY($L$1+1),TRUNC((N30),8),E30) | F31: =TRUNC(((1+VLOOKUP(A31,IPCA!$A$2:$C$140,3,0)))^(C31/(EDATE(D31-C31,1)-(D31-C31))),8) | G31: =TRUNC((E31*F31),8) | H31: =ROUND(((1+$H$4)^(30/360))^(C31/(EDATE(D31-B31,1)-(D31-B31))),9) | I31: =TRUNC((G31*H31-G31),8) | J31: =G31+I31
A32: =IF(DAY(D32)=DAY($L$1+1),A31+1,A31) | B32: =IF(DAY(D32)=DAY($L$1+1),1,B31+1) | C32: =IF(DAY(D32)=DAY($L$1+1),1,C31+1) | D32: =D31+1 | E32: =IF(DAY(D32)=DAY($L$1+1),TRUNC((N31),8),E31) | F32: =TRUNC(((1+VLOOKUP(A32,IPCA!$A$2:$C$140,3,0)))^(C32/(EDATE(D32-C32,1)-(D32-C32))),8) | G32: =TRUNC((E32*F32),8) | H32: =ROUND(((1+$H$4)^(30/360))^(C32/(EDATE(D32-B32,1)-(D32-B32))),9) | I32: =TRUNC((G32*H32-G32),8) | J32: =G32+I32
A33: =IF(DAY(D33)=DAY($L$1+1),A32+1,A32) | B33: =IF(DAY(D33)=DAY($L$1+1),1,B32+1) | C33: =IF(DAY(D33)=DAY($L$1+1),1,C32+1) | D33: =D32+1 | E33: =IF(DAY(D33)=DAY($L$1+1),TRUNC((N32),8),E32) | F33: =TRUNC(((1+VLOOKUP(A33,IPCA!$A$2:$C$140,3,0)))^(C33/(EDATE(D33-C33,1)-(D33-C33))),8) | G33: =TRUNC((E33*F33),8) | H33: =ROUND(((1+$H$4)^(30/360))^(C33/(EDATE(D33-B33,1)-(D33-B33))),9) | I33: =TRUNC((G33*H33-G33),8) | J33: =G33+I33
A34: =IF(DAY(D34)=DAY($L$1+1),A33+1,A33) | B34: =IF(DAY(D34)=DAY($L$1+1),1,B33+1) | C34: =IF(DAY(D34)=DAY($L$1+1),1,C33+1) | D34: =D33+1 | E34: =IF(DAY(D34)=DAY($L$1+1),TRUNC((N33),8),E33) | F34: =TRUNC(((1+VLOOKUP(A34,IPCA!$A$2:$C$140,3,0)))^(C34/(EDATE(D34-C34,1)-(D34-C34))),8) | G34: =TRUNC((E34*F34),8) | H34: =ROUND(((1+$H$4)^(30/360))^(C34/(EDATE(D34-B34,1)-(D34-B34))),9) | I34: =TRUNC((G34*H34-G34),8) | J34: =G34+I34
A35: =IF(DAY(D35)=DAY($L$1+1),A34+1,A34) | B35: =IF(DAY(D35)=DAY($L$1+1),1,B34+1) | C35: =IF(DAY(D35)=DAY($L$1+1),1,C34+1) | D35: =D34+1 | E35: =IF(DAY(D35)=DAY($L$1+1),TRUNC((N34),8),E34) | F35: =TRUNC(((1+VLOOKUP(A35,IPCA!$A$2:$C$140,3,0)))^(C35/(EDATE(D35-C35,1)-(D35-C35))),8) | G35: =TRUNC((E35*F35),8) | H35: =ROUND(((1+$H$4)^(30/360))^(C35/(EDATE(D35-B35,1)-(D35-B35))),9) | I35: =TRUNC((G35*H35-G35),8) | J35: =G35+I35
A36: =IF(DAY(D36)=DAY($L$1+1),A35+1,A35) | B36: =IF(DAY(D36)=DAY($L$1+1),1,B35+1) | C36: =IF(DAY(D36)=DAY($L$1+1),1,C35+1) | D36: =D35+1 | E36: =IF(DAY(D36)=DAY($L$1+1),TRUNC((N35),8),E35) | F36: =TRUNC(((1+VLOOKUP(A36,IPCA!$A$2:$C$140,3,0)))^(C36/(EDATE(D36-C36,1)-(D36-C36))),8) | G36: =TRUNC((E36*F36),8) | H36: =ROUND(((1+$H$4)^(30/360))^(C36/(EDATE(D36-B36,1)-(D36-B36))),9) | I36: =TRUNC((G36*H36-G36),8) | J36: =G36+I36
A37: =IF(DAY(D37)=DAY($L$1+1),A36+1,A36) | B37: =IF(DAY(D37)=DAY($L$1+1),1,B36+1) | C37: =IF(DAY(D37)=DAY($L$1+1),1,C36+1) | D37: =D36+1 | E37: =IF(DAY(D37)=DAY($L$1+1),TRUNC((N36),8),E36) | F37: =TRUNC(((1+VLOOKUP(A37,IPCA!$A$2:$C$140,3,0)))^(C37/(EDATE(D37-C37,1)-(D37-C37))),8) | G37: =TRUNC((E37*F37),8) | H37: =ROUND(((1+$H$4)^(30/360))^(C37/(EDATE(D37-B37,1)-(D37-B37))),9) | I37: =TRUNC((G37*H37-G37),8) | J37: =G37+I37
A38: =IF(DAY(D38)=DAY($L$1+1),A37+1,A37) | B38: =IF(DAY(D38)=DAY($L$1+1),1,B37+1) | C38: =IF(DAY(D38)=DAY($L$1+1),1,C37+1) | D38: =D37+1 | E38: =IF(DAY(D38)=DAY($L$1+1),TRUNC((N37),8),E37) | F38: =TRUNC(((1+VLOOKUP(A38,IPCA!$A$2:$C$140,3,0)))^(C38/(EDATE(D38-C38,1)-(D38-C38))),8) | G38: =TRUNC((E38*F38),8) | H38: =ROUND(((1+$H$4)^(30/360))^(C38/(EDATE(D38-B38,1)-(D38-B38))),9) | I38: =TRUNC((G38*H38-G38),8) | J38: =G38+I38
A39: =IF(DAY(D39)=DAY($L$1+1),A38+1,A38) | B39: =IF(DAY(D39)=DAY($L$1+1),1,B38+1) | C39: =IF(DAY(D39)=DAY($L$1+1),1,C38+1) | D39: =D38+1 | E39: =IF(DAY(D39)=DAY($L$1+1),TRUNC((N38),8),E38) | F39: =TRUNC(((1+VLOOKUP(A39,IPCA!$A$2:$C$140,3,0)))^(C39/(EDATE(D39-C39,1)-(D39-C39))),8) | G39: =TRUNC((E39*F39),8) | H39: =ROUND(((1+$H$4)^(30/360))^(C39/(EDATE(D39-B39,1)-(D39-B39))),9) | I39: =TRUNC((G39*H39-G39),8) | J39: =G39+I39
A40: =IF(DAY(D40)=DAY($L$1+1),A39+1,A39) | B40: =IF(DAY(D40)=DAY($L$1+1),1,B39+1) | C40: =IF(DAY(D40)=DAY($L$1+1),1,C39+1) | D40: =D39+1 | E40: =IF(DAY(D40)=DAY($L$1+1),TRUNC((N39),8),E39) | F40: =TRUNC(((1+VLOOKUP(A40,IPCA!$A$2:$C$140,3,0)))^(C40/(EDATE(D40-C40,1)-(D40-C40))),8) | G40: =TRUNC((E40*F40),8) | H40: =ROUND(((1+$H$4)^(30/360))^(C40/(EDATE(D40-B40,1)-(D40-B40))),9) | I40: =TRUNC((G40*H40-G40),8) | J40: =G40+I40
A41: =IF(DAY(D41)=DAY($L$1+1),A40+1,A40) | B41: =IF(DAY(D41)=DAY($L$1+1),1,B40+1) | C41: =IF(DAY(D41)=DAY($L$1+1),1,C40+1) | D41: =D40+1 | E41: =IF(DAY(D41)=DAY($L$1+1),TRUNC((N40),8),E40) | F41: =TRUNC(((1+VLOOKUP(A41,IPCA!$A$2:$C$140,3,0)))^(C41/(EDATE(D41-C41,1)-(D41-C41))),8) | G41: =TRUNC((E41*F41),8) | H41: =ROUND(((1+$H$4)^(30/360))^(C41/(EDATE(D41-B41,1)-(D41-B41))),9) | I41: =TRUNC((G41*H41-G41),8) | J41: =G41+I41
A42: =IF(DAY(D42)=DAY($L$1+1),A41+1,A41) | B42: =IF(DAY(D42)=DAY($L$1+1),1,B41+1) | C42: =IF(DAY(D42)=DAY($L$1+1),1,C41+1) | D42: =D41+1 | E42: =IF(DAY(D42)=DAY($L$1+1),TRUNC((N41),8),E41) | F42: =TRUNC(((1+VLOOKUP(A42,IPCA!$A$2:$C$140,3,0)))^(C42/(EDATE(D42-C42,1)-(D42-C42))),8) | G42: =TRUNC((E42*F42),8) | H42: =ROUND(((1+$H$4)^(30/360))^(C42/(EDATE(D42-B42,1)-(D42-B42))),9) | I42: =TRUNC((G42*H42-G42),8) | J42: =G42+I42
... A47: =IF(DAY(D47)=DAY($L$1+1),A46+1,A46) | B47: =IF(DAY(D47)=DAY($L$1+1),1,B46+1) | C47: =IF(DAY(D47)=DAY($L$1+1),1,C46+1) | D47: =D46+1 | E47: =IF(DAY(D47)=DAY($L$1+1),TRUNC((N46),8),E46) | F47: =TRUNC(((1+VLOOKUP(A47,IPCA!$A$2:$C$140,3,0)))^(C47/(EDATE(D47-C47,1)-(D47-C47))),8) | G47: =TRUNC((E47*F47),8) | H47: =ROUND(((1+$H$4)^(30/360))^(C47/(EDATE(D47-B47,1)-(D47-B47))),9) | I47: =TRUNC((G47*H47-G47),8) | J47: =G47+I47
A48: =IF(DAY(D48)=DAY($L$1+1),A47+1,A47) | B48: =IF(DAY(D48)=DAY($L$1+1),1,B47+1) | C48: =IF(DAY(D48)=DAY($L$1+1),1,C47+1) | D48: =D47+1 | E48: =IF(DAY(D48)=DAY($L$1+1),TRUNC((N47),8),E47) | F48: =TRUNC(((1+VLOOKUP(A48,IPCA!$A$2:$C$140,3,0)))^(C48/(EDATE(D48-C48,1)-(D48-C48))),8) | G48: =TRUNC((E48*F48),8) | H48: =ROUND(((1+$H$4)^(30/360))^(C48/(EDATE(D48-B48,1)-(D48-B48))),9) | I48: =TRUNC((G48*H48-G48),8) | J48: =G48+I48 | K48: Cri Integralizado | L48: =L17
A49: =IF(DAY(D49)=DAY($L$1+1),A48+1,A48) | B49: =IF(DAY(D49)=DAY($L$1+1),1,B48+1) | C49: =IF(DAY(D49)=DAY($L$1+1),1,C48+1) | D49: =D48+1 | E49: =IF(DAY(D49)=DAY($L$1+1),TRUNC((N48),8),E48) | F49: =TRUNC(((1+VLOOKUP(A49,IPCA!$A$2:$C$140,3,0)))^(C49/(EDATE(D49-C49,1)-(D49-C49))),8) | G49: =TRUNC((E49*F49),8) | H49: =ROUND(((1+$H$4)^(30/360))^(C49/(EDATE(D49-B49,1)-(D49-B49))),9) | I49: =TRUNC((G49*H49-G49),8) | J49: =G49+I49 | K49: JUROS | L49: AMORTIZAÇÃO | M49: AMEX | N49: RESIDUAL
A50: =IF(DAY(D50)=DAY($L$1+1),A49+1,A49) | B50: =IF(DAY(D50)=DAY($L$1+1),1,B49+1) | C50: =IF(DAY(D50)=DAY($L$1+1),1,C49+1) | D50: =D49+1 | E50: =IF(DAY(D50)=DAY($L$1+1),TRUNC((N49),8),E49) | F50: =TRUNC(((1+VLOOKUP(A50,IPCA!$A$2:$C$140,3,0)))^(C50/(EDATE(D50-C50,1)-(D50-C50))),8) | G50: =TRUNC((E50*F50),8) | H50: =ROUND(((1+$H$4)^(30/360))^(C50/(EDATE(D50-B50,1)-(D50-B50))),9) | I50: =TRUNC((G50*H50-G50),8) | J50: =G50+I50 | K50: 0 | L50: =TRUNC(G50*VLOOKUP(D50,'Amort TS'!$G$3:$H$140,2,0),8) | M50: 0 | N50: =J50-K50-L50-M50
A51: =IF(DAY(D51)=DAY($L$1+1),A50+1,A50) | B51: =IF(DAY(D51)=DAY($L$1+1),1,B50+1) | C51: =IF(DAY(D51)=DAY($L$1+1),1,C50+1) | D51: =D50+1 | E51: =IF(DAY(D51)=DAY($L$1+1),TRUNC((N50),8),E50) | F51: =TRUNC(((1+VLOOKUP(A51,IPCA!$A$2:$C$140,3,0)))^(C51/(EDATE(D51-C51,1)-(D51-C51))),8) | G51: =TRUNC((E51*F51),8) | H51: =ROUND(((1+$H$4)^(30/360))^(C51/(EDATE(D51-B51,1)-(D51-B51))),9) | I51: =TRUNC((G51*H51-G51),8) | J51: =G51+I51 | K51: =K50*L48 | L51: =L50*L48 | M51: =M50*L48 | N51: =N50*L48
A52: =IF(DAY(D52)=DAY($L$1+1),A51+1,A51) | B52: =IF(DAY(D52)=DAY($L$1+1),1,B51+1) | C52: =IF(DAY(D52)=DAY($L$1+1),1,C51+1) | D52: =D51+1 | E52: =IF(DAY(D52)=DAY($L$1+1),TRUNC((N51),8),E51) | F52: =TRUNC(((1+VLOOKUP(A52,IPCA!$A$2:$C$140,3,0)))^(C52/(EDATE(D52-C52,1)-(D52-C52))),8) | G52: =TRUNC((E52*F52),8) | H52: =ROUND(((1+$H$4)^(30/360))^(C52/(EDATE(D52-B52,1)-(D52-B52))),9) | I52: =TRUNC((G52*H52-G52),8) | J52: =G52+I52
A53: =IF(DAY(D53)=DAY($L$1+1),A52+1,A52) | B53: =IF(DAY(D53)=DAY($L$1+1),1,B52+1) | C53: =IF(DAY(D53)=DAY($L$1+1),1,C52+1) | D53: =D52+1 | E53: =IF(DAY(D53)=DAY($L$1+1),TRUNC((#REF!),8),E52) | F53: =TRUNC(((1+VLOOKUP(A53,IPCA!$A$2:$C$140,3,0)))^(C53/(EDATE(D53-C53,1)-(D53-C53))),8) | G53: =TRUNC((E53*F53),8) | H53: =ROUND(((1+$H$4)^(30/360))^(C53/(EDATE(D53-B53,1)-(D53-B53))),9) | I53: =TRUNC((G53*H53-G53),8) | J53: =G53+I53
A54: =IF(DAY(D54)=DAY($L$1+1),A53+1,A53) | B54: =IF(DAY(D54)=DAY($L$1+1),1,B53+1) | C54: =IF(DAY(D54)=DAY($L$1+1),1,C53+1) | D54: =D53+1 | E54: =IF(DAY(D54)=DAY($L$1+1),TRUNC((#REF!),8),E53) | F54: =TRUNC(((1+VLOOKUP(A54,IPCA!$A$2:$C$140,3,0)))^(C54/(EDATE(D54-C54,1)-(D54-C54))),8) | G54: =TRUNC((E54*F54),8) | H54: =ROUND(((1+$H$4)^(30/360))^(C54/(EDATE(D54-B54,1)-(D54-B54))),9) | I54: =TRUNC((G54*H54-G54),8) | J54: =G54+I54
A55: =IF(DAY(D55)=DAY($L$1+1),A54+1,A54) | B55: =IF(DAY(D55)=DAY($L$1+1),1,B54+1) | C55: =IF(DAY(D55)=DAY($L$1+1),1,C54+1) | D55: =D54+1 | E55: =IF(DAY(D55)=DAY($L$1+1),TRUNC((#REF!),8),E54) | F55: =TRUNC(((1+VLOOKUP(A55,IPCA!$A$2:$C$140,3,0)))^(C55/(EDATE(D55-C55,1)-(D55-C55))),8) | G55: =TRUNC((E55*F55),8) | H55: =ROUND(((1+$H$4)^(30/360))^(C55/(EDATE(D55-B55,1)-(D55-B55))),9) | I55: =TRUNC((G55*H55-G55),8) | J55: =G55+I55
A56: =IF(DAY(D56)=DAY($L$1+1),A55+1,A55) | B56: =IF(DAY(D56)=DAY($L$1+1),1,B55+1) | C56: =IF(DAY(D56)=DAY($L$1+1),1,C55+1) | D56: =D55+1 | E56: =IF(DAY(D56)=DAY($L$1+1),TRUNC((#REF!),8),E55) | F56: =TRUNC(((1+VLOOKUP(A56,IPCA!$A$2:$C$140,3,0)))^(C56/(EDATE(D56-C56,1)-(D56-C56))),8) | G56: =TRUNC((E56*F56),8) | H56: =ROUND(((1+$H$4)^(30/360))^(C56/(EDATE(D56-B56,1)-(D56-B56))),9) | I56: =TRUNC((G56*H56-G56),8) | J56: =G56+I56
A57: =IF(DAY(D57)=DAY($L$1+1),A56+1,A56) | B57: =IF(DAY(D57)=DAY($L$1+1),1,B56+1) | C57: =IF(DAY(D57)=DAY($L$1+1),1,C56+1) | D57: =D56+1 | E57: =IF(DAY(D57)=DAY($L$1+1),TRUNC((#REF!),8),E56) | F57: =TRUNC(((1+VLOOKUP(A57,IPCA!$A$2:$C$140,3,0)))^(C57/(EDATE(D57-C57,1)-(D57-C57))),8) | G57: =TRUNC((E57*F57),8) | H57: =ROUND(((1+$H$4)^(30/360))^(C57/(EDATE(D57-B57,1)-(D57-B57))),9) | I57: =TRUNC((G57*H57-G57),8) | J57: =G57+I57
A58: =IF(DAY(D58)=DAY($L$1+1),A57+1,A57) | B58: =IF(DAY(D58)=DAY($L$1+1),1,B57+1) | C58: =IF(DAY(D58)=DAY($L$1+1),1,C57+1) | D58: =D57+1 | E58: =IF(DAY(D58)=DAY($L$1+1),TRUNC((#REF!),8),E57) | F58: =TRUNC(((1+VLOOKUP(A58,IPCA!$A$2:$C$140,3,0)))^(C58/(EDATE(D58-C58,1)-(D58-C58))),8) | G58: =TRUNC((E58*F58),8) | H58: =ROUND(((1+$H$4)^(30/360))^(C58/(EDATE(D58-B58,1)-(D58-B58))),9) | I58: =TRUNC((G58*H58-G58),8) | J58: =G58+I58
A59: =IF(DAY(D59)=DAY($L$1+1),A58+1,A58) | B59: =IF(DAY(D59)=DAY($L$1+1),1,B58+1) | C59: =IF(DAY(D59)=DAY($L$1+1),1,C58+1) | D59: =D58+1 | E59: =IF(DAY(D59)=DAY($L$1+1),TRUNC((#REF!),8),E58) | F59: =TRUNC(((1+VLOOKUP(A59,IPCA!$A$2:$C$140,3,0)))^(C59/(EDATE(D59-C59,1)-(D59-C59))),8) | G59: =TRUNC((E59*F59),8) | H59: =ROUND(((1+$H$4)^(30/360))^(C59/(EDATE(D59-B59,1)-(D59-B59))),9) | I59: =TRUNC((G59*H59-G59),8) | J59: =G59+I59
A60: =IF(DAY(D60)=DAY($L$1+1),A59+1,A59) | B60: =IF(DAY(D60)=DAY($L$1+1),1,B59+1) | C60: =IF(DAY(D60)=DAY($L$1+1),1,C59+1) | D60: =D59+1 | E60: =IF(DAY(D60)=DAY($L$1+1),TRUNC((N59),8),E59) | F60: =TRUNC(((1+VLOOKUP(A60,IPCA!$A$2:$C$140,3,0)))^(C60/(EDATE(D60-C60,1)-(D60-C60))),8) | G60: =TRUNC((E60*F60),8) | H60: =ROUND(((1+$H$4)^(30/360))^(C60/(EDATE(D60-B60,1)-(D60-B60))),9) | I60: =TRUNC((G60*H60-G60),8) | J60: =G60+I60
A61: =IF(DAY(D61)=DAY($L$1+1),A60+1,A60) | B61: =IF(DAY(D61)=DAY($L$1+1),1,B60+1) | C61: =IF(DAY(D61)=DAY($L$1+1),1,C60+1) | D61: =D60+1 | E61: =IF(DAY(D61)=DAY($L$1+1),TRUNC((N60),8),E60) | F61: =TRUNC(((1+VLOOKUP(A61,IPCA!$A$2:$C$140,3,0)))^(C61/(EDATE(D61-C61,1)-(D61-C61))),8) | G61: =TRUNC((E61*F61),8) | H61: =ROUND(((1+$H$4)^(30/360))^(C61/(EDATE(D61-B61,1)-(D61-B61))),9) | I61: =TRUNC((G61*H61-G61),8) | J61: =G61+I61 | K61: 725187
A62: =IF(DAY(D62)=DAY($L$1+1),A61+1,A61) | B62: =IF(DAY(D62)=DAY($L$1+1),1,B61+1) | C62: =IF(DAY(D62)=DAY($L$1+1),1,C61+1) | D62: =D61+1 | E62: =IF(DAY(D62)=DAY($L$1+1),TRUNC((N61),8),E61) | F62: =TRUNC(((1+VLOOKUP(A62,IPCA!$A$2:$C$140,3,0)))^(C62/(EDATE(D62-C62,1)-(D62-C62))),8) | G62: =TRUNC((E62*F62),8) | H62: =ROUND(((1+$H$4)^(30/360))^(C62/(EDATE(D62-B62,1)-(D62-B62))),9) | I62: =TRUNC((G62*H62-G62),8) | J62: =G62+I62
A63: =IF(DAY(D63)=DAY($L$1+1),A62+1,A62) | B63: =IF(DAY(D63)=DAY($L$1+1),1,B62+1) | C63: =IF(DAY(D63)=DAY($L$1+1),1,C62+1) | D63: =D62+1 | E63: =IF(DAY(D63)=DAY($L$1+1),TRUNC((N62),8),E62) | F63: =TRUNC(((1+VLOOKUP(A63,IPCA!$A$2:$C$140,3,0)))^(C63/(EDATE(D63-C63,1)-(D63-C63))),8) | G63: =TRUNC((E63*F63),8) | H63: =ROUND(((1+$H$4)^(30/360))^(C63/(EDATE(D63-B63,1)-(D63-B63))),9) | I63: =TRUNC((G63*H63-G63),8) | J63: =G63+I63
A64: =IF(DAY(D64)=DAY($L$1+1),A63+1,A63) | B64: =IF(DAY(D64)=DAY($L$1+1),1,B63+1) | C64: =IF(DAY(D64)=DAY($L$1+1),1,C63+1) | D64: =D63+1 | E64: =IF(DAY(D64)=DAY($L$1+1),TRUNC((N63),8),E63) | F64: =TRUNC(((1+VLOOKUP(A64,IPCA!$A$2:$C$140,3,0)))^(C64/(EDATE(D64-C64,1)-(D64-C64))),8) | G64: =TRUNC((E64*F64),8) | H64: =ROUND(((1+$H$4)^(30/360))^(C64/(EDATE(D64-B64,1)-(D64-B64))),9) | I64: =TRUNC((G64*H64-G64),8) | J64: =G64+I64
A65: =IF(DAY(D65)=DAY($L$1+1),A64+1,A64) | B65: =IF(DAY(D65)=DAY($L$1+1),1,B64+1) | C65: =IF(DAY(D65)=DAY($L$1+1),1,C64+1) | D65: =D64+1 | E65: =IF(DAY(D65)=DAY($L$1+1),TRUNC((N64),8),E64) | F65: =TRUNC(((1+VLOOKUP(A65,IPCA!$A$2:$C$140,3,0)))^(C65/(EDATE(D65-C65,1)-(D65-C65))),8) | G65: =TRUNC((E65*F65),8) | H65: =ROUND(((1+$H$4)^(30/360))^(C65/(EDATE(D65-B65,1)-(D65-B65))),9) | I65: =TRUNC((G65*H65-G65),8) | J65: =G65+I65
A66: =IF(DAY(D66)=DAY($L$1+1),A65+1,A65) | B66: =IF(DAY(D66)=DAY($L$1+1),1,B65+1) | C66: =IF(DAY(D66)=DAY($L$1+1),1,C65+1) | D66: =D65+1 | E66: =IF(DAY(D66)=DAY($L$1+1),TRUNC((N65),8),E65) | F66: =TRUNC(((1+VLOOKUP(A66,IPCA!$A$2:$C$140,3,0)))^(C66/(EDATE(D66-C66,1)-(D66-C66))),8) | G66: =TRUNC((E66*F66),8) | H66: =ROUND(((1+$H$4)^(30/360))^(C66/(EDATE(D66-B66,1)-(D66-B66))),9) | I66: =TRUNC((G66*H66-G66),8) | J66: =G66+I66
A67: =IF(DAY(D67)=DAY($L$1+1),A66+1,A66) | B67: =IF(DAY(D67)=DAY($L$1+1),1,B66+1) | C67: =IF(DAY(D67)=DAY($L$1+1),1,C66+1) | D67: =D66+1 | E67: =IF(DAY(D67)=DAY($L$1+1),TRUNC((N66),8),E66) | F67: =TRUNC(((1+VLOOKUP(A67,IPCA!$A$2:$C$140,3,0)))^(C67/(EDATE(D67-C67,1)-(D67-C67))),8) | G67: =TRUNC((E67*F67),8) | H67: =ROUND(((1+$H$4)^(30/360))^(C67/(EDATE(D67-B67,1)-(D67-B67))),9) | I67: =TRUNC((G67*H67-G67),8) | J67: =G67+I67
A68: =IF(DAY(D68)=DAY($L$1+1),A67+1,A67) | B68: =IF(DAY(D68)=DAY($L$1+1),1,B67+1) | C68: =IF(DAY(D68)=DAY($L$1+1),1,C67+1) | D68: =D67+1 | E68: =IF(DAY(D68)=DAY($L$1+1),TRUNC((N67),8),E67) | F68: =TRUNC(((1+VLOOKUP(A68,IPCA!$A$2:$C$140,3,0)))^(C68/(EDATE(D68-C68,1)-(D68-C68))),8) | G68: =TRUNC((E68*F68),8) | H68: =ROUND(((1+$H$4)^(30/360))^(C68/(EDATE(D68-B68,1)-(D68-B68))),9) | I68: =TRUNC((G68*H68-G68),8) | J68: =G68+I68
A69: =IF(DAY(D69)=DAY($L$1+1),A68+1,A68) | B69: =IF(DAY(D69)=DAY($L$1+1),1,B68+1) | C69: =IF(DAY(D69)=DAY($L$1+1),1,C68+1) | D69: =D68+1 | E69: =IF(DAY(D69)=DAY($L$1+1),TRUNC((N68),8),E68) | F69: =TRUNC(((1+VLOOKUP(A69,IPCA!$A$2:$C$140,3,0)))^(C69/(EDATE(D69-C69,1)-(D69-C69))),8) | G69: =TRUNC((E69*F69),8) | H69: =ROUND(((1+$H$4)^(30/360))^(C69/(EDATE(D69-B69,1)-(D69-B69))),9) | I69: =TRUNC((G69*H69-G69),8) | J69: =G69+I69
A70: =IF(DAY(D70)=DAY($L$1+1),A69+1,A69) | B70: =IF(DAY(D70)=DAY($L$1+1),1,B69+1) | C70: =IF(DAY(D70)=DAY($L$1+1),1,C69+1) | D70: =D69+1 | E70: =IF(DAY(D70)=DAY($L$1+1),TRUNC((N69),8),E69) | F70: =TRUNC(((1+VLOOKUP(A70,IPCA!$A$2:$C$140,3,0)))^(C70/(EDATE(D70-C70,1)-(D70-C70))),8) | G70: =TRUNC((E70*F70),8) | H70: =ROUND(((1+$H$4)^(30/360))^(C70/(EDATE(D70-B70,1)-(D70-B70))),9) | I70: =TRUNC((G70*H70-G70),8) | J70: =G70+I70
A71: =IF(DAY(D71)=DAY($L$1+1),A70+1,A70) | B71: =IF(DAY(D71)=DAY($L$1+1),1,B70+1) | C71: =IF(DAY(D71)=DAY($L$1+1),1,C70+1) | D71: =D70+1 | E71: =IF(DAY(D71)=DAY($L$1+1),TRUNC((N70),8),E70) | F71: =TRUNC(((1+VLOOKUP(A71,IPCA!$A$2:$C$140,3,0)))^(C71/(EDATE(D71-C71,1)-(D71-C71))),8) | G71: =TRUNC((E71*F71),8) | H71: =ROUND(((1+$H$4)^(30/360))^(C71/(EDATE(D71-B71,1)-(D71-B71))),9) | I71: =TRUNC((G71*H71-G71),8) | J71: =G71+I71
A72: =IF(DAY(D72)=DAY($L$1+1),A71+1,A71) | B72: =IF(DAY(D72)=DAY($L$1+1),1,B71+1) | C72: =IF(DAY(D72)=DAY($L$1+1),1,C71+1) | D72: =D71+1 | E72: =IF(DAY(D72)=DAY($L$1+1),TRUNC((N71),8),E71) | F72: =TRUNC(((1+VLOOKUP(A72,IPCA!$A$2:$C$140,3,0)))^(C72/(EDATE(D72-C72,1)-(D72-C72))),8) | G72: =TRUNC((E72*F72),8) | H72: =ROUND(((1+$H$4)^(30/360))^(C72/(EDATE(D72-B72,1)-(D72-B72))),9) | I72: =TRUNC((G72*H72-G72),8) | J72: =G72+I72
A73: =IF(DAY(D73)=DAY($L$1+1),A72+1,A72) | B73: =IF(DAY(D73)=DAY($L$1+1),1,B72+1) | C73: =IF(DAY(D73)=DAY($L$1+1),1,C72+1) | D73: =D72+1 | E73: =IF(DAY(D73)=DAY($L$1+1),TRUNC((N72),8),E72) | F73: =TRUNC(((1+VLOOKUP(A73,IPCA!$A$2:$C$140,3,0)))^(C73/(EDATE(D73-C73,1)-(D73-C73))),8) | G73: =TRUNC((E73*F73),8) | H73: =ROUND(((1+$H$4)^(30/360))^(C73/(EDATE(D73-B73,1)-(D73-B73))),9) | I73: =TRUNC((G73*H73-G73),8) | J73: =G73+I73
... A78: =IF(DAY(D78)=DAY($L$1+1),A77+1,A77) | B78: =IF(DAY(D78)=DAY($L$1+1),1,B77+1) | C78: =IF(DAY(D78)=DAY($L$1+1),1,C77+1) | D78: =D77+1 | E78: =IF(DAY(D78)=DAY($L$1+1),TRUNC((N77),8),E77) | F78: =TRUNC(((1+VLOOKUP(A78,IPCA!$A$2:$C$140,3,0)))^(C78/(EDATE(D78-C78,1)-(D78-C78))),8) | G78: =TRUNC((E78*F78),8) | H78: =ROUND(((1+$H$4)^(30/360))^(C78/(EDATE(D78-B78,1)-(D78-B78))),9) | I78: =TRUNC((G78*H78-G78),8) | J78: =G78+I78
A79: =IF(DAY(D79)=DAY($L$1+1),A78+1,A78) | B79: =IF(DAY(D79)=DAY($L$1+1),1,B78+1) | C79: =IF(DAY(D79)=DAY($L$1+1),1,C78+1) | D79: =D78+1 | E79: =IF(DAY(D79)=DAY($L$1+1),TRUNC((N78),8),E78) | F79: =TRUNC(((1+VLOOKUP(A79,IPCA!$A$2:$C$140,3,0)))^(C79/(EDATE(D79-C79,1)-(D79-C79))),8) | G79: =TRUNC((E79*F79),8) | H79: =ROUND(((1+$H$4)^(30/360))^(C79/(EDATE(D79-B79,1)-(D79-B79))),9) | I79: =TRUNC((G79*H79-G79),8) | J79: =G79+I79 | K79: Cri Integralizado | L79: =L48+K61
A80: =IF(DAY(D80)=DAY($L$1+1),A79+1,A79) | B80: =IF(DAY(D80)=DAY($L$1+1),1,B79+1) | C80: =IF(DAY(D80)=DAY($L$1+1),1,C79+1) | D80: =D79+1 | E80: =IF(DAY(D80)=DAY($L$1+1),TRUNC((N79),8),E79) | F80: =TRUNC(((1+VLOOKUP(A80,IPCA!$A$2:$C$140,3,0)))^(C80/(EDATE(D80-C80,1)-(D80-C80))),8) | G80: =TRUNC((E80*F80),8) | H80: =ROUND(((1+$H$4)^(30/360))^(C80/(EDATE(D80-B80,1)-(D80-B80))),9) | I80: =TRUNC((G80*H80-G80),8) | J80: =G80+I80 | K80: JUROS | L80: AMORTIZAÇÃO | M80: AMEX | N80: RESIDUAL
A81: =IF(DAY(D81)=DAY($L$1+1),A80+1,A80) | B81: =IF(DAY(D81)=DAY($L$1+1),1,B80+1) | C81: =IF(DAY(D81)=DAY($L$1+1),1,C80+1) | D81: =D80+1 | E81: =IF(DAY(D81)=DAY($L$1+1),TRUNC((N80),8),E80) | F81: =TRUNC(((1+VLOOKUP(A81,IPCA!$A$2:$C$140,3,0)))^(C81/(EDATE(D81-C81,1)-(D81-C81))),8) | G81: =TRUNC((E81*F81),8) | H81: =ROUND(((1+$H$4)^(30/360))^(C81/(EDATE(D81-B81,1)-(D81-B81))),9) | I81: =TRUNC((G81*H81-G81),8) | J81: =G81+I81 | K81: 0 | L81: =TRUNC(G81*VLOOKUP(D81,'Amort TS'!$G$3:$H$140,2,0),8) | M81: 0 | N81: =J81-K81-L81-M81
A82: =IF(DAY(D82)=DAY($L$1+1),A81+1,A81) | B82: =IF(DAY(D82)=DAY($L$1+1),1,B81+1) | C82: =IF(DAY(D82)=DAY($L$1+1),1,C81+1) | D82: =D81+1 | E82: =IF(DAY(D82)=DAY($L$1+1),TRUNC((N81),8),E81) | F82: =TRUNC(((1+VLOOKUP(A82,IPCA!$A$2:$C$140,3,0)))^(C82/(EDATE(D82-C82,1)-(D82-C82))),8) | G82: =TRUNC((E82*F82),8) | H82: =ROUND(((1+$H$4)^(30/360))^(C82/(EDATE(D82-B82,1)-(D82-B82))),9) | I82: =TRUNC((G82*H82-G82),8) | J82: =G82+I82 | K82: =K81*L79 | L82: =L81*L79 | M82: =M81*L79 | N82: =N81*L79
A83: =IF(DAY(D83)=DAY($L$1+1),A82+1,A82) | B83: =IF(DAY(D83)=DAY($L$1+1),1,B82+1) | C83: =IF(DAY(D83)=DAY($L$1+1),1,C82+1) | D83: =D82+1 | E83: =IF(DAY(D83)=DAY($L$1+1),TRUNC((N82),8),E82) | F83: =TRUNC(((1+VLOOKUP(A83,IPCA!$A$2:$C$140,3,0)))^(C83/(EDATE(D83-C83,1)-(D83-C83))),8) | G83: =TRUNC((E83*F83),8) | H83: =ROUND(((1+$H$4)^(30/360))^(C83/(EDATE(D83-B83,1)-(D83-B83))),9) | I83: =TRUNC((G83*H83-G83),8) | J83: =G83+I83
A84: =IF(DAY(D84)=DAY($L$1+1),A83+1,A83) | B84: =IF(DAY(D84)=DAY($L$1+1),1,B83+1) | C84: =IF(DAY(D84)=DAY($L$1+1),1,C83+1) | D84: =D83+1 | E84: =IF(DAY(D84)=DAY($L$1+1),TRUNC((#REF!),8),E83) | F84: =TRUNC(((1+VLOOKUP(A84,IPCA!$A$2:$C$140,3,0)))^(C84/(EDATE(D84-C84,1)-(D84-C84))),8) | G84: =TRUNC((E84*F84),8) | H84: =ROUND(((1+$H$4)^(30/360))^(C84/(EDATE(D84-B84,1)-(D84-B84))),9) | I84: =TRUNC((G84*H84-G84),8) | J84: =G84+I84
A85: =IF(DAY(D85)=DAY($L$1+1),A84+1,A84) | B85: =IF(DAY(D85)=DAY($L$1+1),1,B84+1) | C85: =IF(DAY(D85)=DAY($L$1+1),1,C84+1) | D85: =D84+1 | E85: =IF(DAY(D85)=DAY($L$1+1),TRUNC((#REF!),8),E84) | F85: =TRUNC(((1+VLOOKUP(A85,IPCA!$A$2:$C$140,3,0)))^(C85/(EDATE(D85-C85,1)-(D85-C85))),8) | G85: =TRUNC((E85*F85),8) | H85: =ROUND(((1+$H$4)^(30/360))^(C85/(EDATE(D85-B85,1)-(D85-B85))),9) | I85: =TRUNC((G85*H85-G85),8) | J85: =G85+I85
A86: =IF(DAY(D86)=DAY($L$1+1),A85+1,A85) | B86: =IF(DAY(D86)=DAY($L$1+1),1,B85+1) | C86: =IF(DAY(D86)=DAY($L$1+1),1,C85+1) | D86: =D85+1 | E86: =IF(DAY(D86)=DAY($L$1+1),TRUNC((#REF!),8),E85) | F86: =TRUNC(((1+VLOOKUP(A86,IPCA!$A$2:$C$140,3,0)))^(C86/(EDATE(D86-C86,1)-(D86-C86))),8) | G86: =TRUNC((E86*F86),8) | H86: =ROUND(((1+$H$4)^(30/360))^(C86/(EDATE(D86-B86,1)-(D86-B86))),9) | I86: =TRUNC((G86*H86-G86),8) | J86: =G86+I86
A87: =IF(DAY(D87)=DAY($L$1+1),A86+1,A86) | B87: =IF(DAY(D87)=DAY($L$1+1),1,B86+1) | C87: =IF(DAY(D87)=DAY($L$1+1),1,C86+1) | D87: =D86+1 | E87: =IF(DAY(D87)=DAY($L$1+1),TRUNC((#REF!),8),E86) | F87: =TRUNC(((1+VLOOKUP(A87,IPCA!$A$2:$C$140,3,0)))^(C87/(EDATE(D87-C87,1)-(D87-C87))),8) | G87: =TRUNC((E87*F87),8) | H87: =ROUND(((1+$H$4)^(30/360))^(C87/(EDATE(D87-B87,1)-(D87-B87))),9) | I87: =TRUNC((G87*H87-G87),8) | J87: =G87+I87
A88: =IF(DAY(D88)=DAY($L$1+1),A87+1,A87) | B88: =IF(DAY(D88)=DAY($L$1+1),1,B87+1) | C88: =IF(DAY(D88)=DAY($L$1+1),1,C87+1) | D88: =D87+1 | E88: =IF(DAY(D88)=DAY($L$1+1),TRUNC((#REF!),8),E87) | F88: =TRUNC(((1+VLOOKUP(A88,IPCA!$A$2:$C$140,3,0)))^(C88/(EDATE(D88-C88,1)-(D88-C88))),8) | G88: =TRUNC((E88*F88),8) | H88: =ROUND(((1+$H$4)^(30/360))^(C88/(EDATE(D88-B88,1)-(D88-B88))),9) | I88: =TRUNC((G88*H88-G88),8) | J88: =G88+I88
A89: =IF(DAY(D89)=DAY($L$1+1),A88+1,A88) | B89: =IF(DAY(D89)=DAY($L$1+1),1,B88+1) | C89: =IF(DAY(D89)=DAY($L$1+1),1,C88+1) | D89: =D88+1 | E89: =IF(DAY(D89)=DAY($L$1+1),TRUNC((#REF!),8),E88) | F89: =TRUNC(((1+VLOOKUP(A89,IPCA!$A$2:$C$140,3,0)))^(C89/(EDATE(D89-C89,1)-(D89-C89))),8) | G89: =TRUNC((E89*F89),8) | H89: =ROUND(((1+$H$4)^(30/360))^(C89/(EDATE(D89-B89,1)-(D89-B89))),9) | I89: =TRUNC((G89*H89-G89),8) | J89: =G89+I89
A90: =IF(DAY(D90)=DAY($L$1+1),A89+1,A89) | B90: =IF(DAY(D90)=DAY($L$1+1),1,B89+1) | C90: =IF(DAY(D90)=DAY($L$1+1),1,C89+1) | D90: =D89+1 | E90: =IF(DAY(D90)=DAY($L$1+1),TRUNC((#REF!),8),E89) | F90: =TRUNC(((1+VLOOKUP(A90,IPCA!$A$2:$C$140,3,0)))^(C90/(EDATE(D90-C90,1)-(D90-C90))),8) | G90: =TRUNC((E90*F90),8) | H90: =ROUND(((1+$H$4)^(30/360))^(C90/(EDATE(D90-B90,1)-(D90-B90))),9) | I90: =TRUNC((G90*H90-G90),8) | J90: =G90+I90
A91: =IF(DAY(D91)=DAY($L$1+1),A90+1,A90) | B91: =IF(DAY(D91)=DAY($L$1+1),1,B90+1) | C91: =IF(DAY(D91)=DAY($L$1+1),1,C90+1) | D91: =D90+1 | E91: =IF(DAY(D91)=DAY($L$1+1),TRUNC((#REF!),8),E90) | F91: =TRUNC(((1+VLOOKUP(A91,IPCA!$A$2:$C$140,3,0)))^(C91/(EDATE(D91-C91,1)-(D91-C91))),8) | G91: =TRUNC((E91*F91),8) | H91: =ROUND(((1+$H$4)^(30/360))^(C91/(EDATE(D91-B91,1)-(D91-B91))),9) | I91: =TRUNC((G91*H91-G91),8) | J91: =G91+I91
A92: =IF(DAY(D92)=DAY($L$1+1),A91+1,A91) | B92: =IF(DAY(D92)=DAY($L$1+1),1,B91+1) | C92: =IF(DAY(D92)=DAY($L$1+1),1,C91+1) | D92: =D91+1 | E92: =IF(DAY(D92)=DAY($L$1+1),TRUNC((#REF!),8),E91) | F92: =TRUNC(((1+VLOOKUP(A92,IPCA!$A$2:$C$140,3,0)))^(C92/(EDATE(D92-C92,1)-(D92-C92))),8) | G92: =TRUNC((E92*F92),8) | H92: =ROUND(((1+$H$4)^(30/360))^(C92/(EDATE(D92-B92,1)-(D92-B92))),9) | I92: =TRUNC((G92*H92-G92),8) | J92: =G92+I92
A93: =IF(DAY(D93)=DAY($L$1+1),A92+1,A92) | B93: =IF(DAY(D93)=DAY($L$1+1),1,B92+1) | C93: =IF(DAY(D93)=DAY($L$1+1),1,C92+1) | D93: =D92+1 | E93: =IF(DAY(D93)=DAY($L$1+1),TRUNC((N92),8),E92) | F93: =TRUNC(((1+VLOOKUP(A93,IPCA!$A$2:$C$140,3,0)))^(C93/(EDATE(D93-C93,1)-(D93-C93))),8) | G93: =TRUNC((E93*F93),8) | H93: =ROUND(((1+$H$4)^(30/360))^(C93/(EDATE(D93-B93,1)-(D93-B93))),9) | I93: =TRUNC((G93*H93-G93),8) | J93: =G93+I93
A94: =IF(DAY(D94)=DAY($L$1+1),A93+1,A93) | B94: =IF(DAY(D94)=DAY($L$1+1),1,B93+1) | C94: =IF(DAY(D94)=DAY($L$1+1),1,C93+1) | D94: =D93+1 | E94: =IF(DAY(D94)=DAY($L$1+1),TRUNC((N93),8),E93) | F94: =TRUNC(((1+VLOOKUP(A94,IPCA!$A$2:$C$140,3,0)))^(C94/(EDATE(D94-C94,1)-(D94-C94))),8) | G94: =TRUNC((E94*F94),8) | H94: =ROUND(((1+$H$4)^(30/360))^(C94/(EDATE(D94-B94,1)-(D94-B94))),9) | I94: =TRUNC((G94*H94-G94),8) | J94: =G94+I94
A95: =IF(DAY(D95)=DAY($L$1+1),A94+1,A94) | B95: =IF(DAY(D95)=DAY($L$1+1),1,B94+1) | C95: =IF(DAY(D95)=DAY($L$1+1),1,C94+1) | D95: =D94+1 | E95: =IF(DAY(D95)=DAY($L$1+1),TRUNC((N94),8),E94) | F95: =TRUNC(((1+VLOOKUP(A95,IPCA!$A$2:$C$140,3,0)))^(C95/(EDATE(D95-C95,1)-(D95-C95))),8) | G95: =TRUNC((E95*F95),8) | H95: =ROUND(((1+$H$4)^(30/360))^(C95/(EDATE(D95-B95,1)-(D95-B95))),9) | I95: =TRUNC((G95*H95-G95),8) | J95: =G95+I95
A96: =IF(DAY(D96)=DAY($L$1+1),A95+1,A95) | B96: =IF(DAY(D96)=DAY($L$1+1),1,B95+1) | C96: =IF(DAY(D96)=DAY($L$1+1),1,C95+1) | D96: =D95+1 | E96: =IF(DAY(D96)=DAY($L$1+1),TRUNC((N95),8),E95) | F96: =TRUNC(((1+VLOOKUP(A96,IPCA!$A$2:$C$140,3,0)))^(C96/(EDATE(D96-C96,1)-(D96-C96))),8) | G96: =TRUNC((E96*F96),8) | H96: =ROUND(((1+$H$4)^(30/360))^(C96/(EDATE(D96-B96,1)-(D96-B96))),9) | I96: =TRUNC((G96*H96-G96),8) | J96: =G96+I96
A97: =IF(DAY(D97)=DAY($L$1+1),A96+1,A96) | B97: =IF(DAY(D97)=DAY($L$1+1),1,B96+1) | C97: =IF(DAY(D97)=DAY($L$1+1),1,C96+1) | D97: =D96+1 | E97: =IF(DAY(D97)=DAY($L$1+1),TRUNC((N96),8),E96) | F97: =TRUNC(((1+VLOOKUP(A97,IPCA!$A$2:$C$140,3,0)))^(C97/(EDATE(D97-C97,1)-(D97-C97))),8) | G97: =TRUNC((E97*F97),8) | H97: =ROUND(((1+$H$4)^(30/360))^(C97/(EDATE(D97-B97,1)-(D97-B97))),9) | I97: =TRUNC((G97*H97-G97),8) | J97: =G97+I97
A98: =IF(DAY(D98)=DAY($L$1+1),A97+1,A97) | B98: =IF(DAY(D98)=DAY($L$1+1),1,B97+1) | C98: =IF(DAY(D98)=DAY($L$1+1),1,C97+1) | D98: =D97+1 | E98: =IF(DAY(D98)=DAY($L$1+1),TRUNC((N97),8),E97) | F98: =TRUNC(((1+VLOOKUP(A98,IPCA!$A$2:$C$140,3,0)))^(C98/(EDATE(D98-C98,1)-(D98-C98))),8) | G98: =TRUNC((E98*F98),8) | H98: =ROUND(((1+$H$4)^(30/360))^(C98/(EDATE(D98-B98,1)-(D98-B98))),9) | I98: =TRUNC((G98*H98-G98),8) | J98: =G98+I98
A99: =IF(DAY(D99)=DAY($L$1+1),A98+1,A98) | B99: =IF(DAY(D99)=DAY($L$1+1),1,B98+1) | C99: =IF(DAY(D99)=DAY($L$1+1),1,C98+1) | D99: =D98+1 | E99: =IF(DAY(D99)=DAY($L$1+1),TRUNC((N98),8),E98) | F99: =TRUNC(((1+VLOOKUP(A99,IPCA!$A$2:$C$140,3,0)))^(C99/(EDATE(D99-C99,1)-(D99-C99))),8) | G99: =TRUNC((E99*F99),8) | H99: =ROUND(((1+$H$4)^(30/360))^(C99/(EDATE(D99-B99,1)-(D99-B99))),9) | I99: =TRUNC((G99*H99-G99),8) | J99: =G99+I99
A100: =IF(DAY(D100)=DAY($L$1+1),A99+1,A99) | B100: =IF(DAY(D100)=DAY($L$1+1),1,B99+1) | C100: =IF(DAY(D100)=DAY($L$1+1),1,C99+1) | D100: =D99+1 | E100: =IF(DAY(D100)=DAY($L$1+1),TRUNC((N99),8),E99) | F100: =TRUNC(((1+VLOOKUP(A100,IPCA!$A$2:$C$140,3,0)))^(C100/(EDATE(D100-C100,1)-(D100-C100))),8) | G100: =TRUNC((E100*F100),8) | H100: =ROUND(((1+$H$4)^(30/360))^(C100/(EDATE(D100-B100,1)-(D100-B100))),9) | I100: =TRUNC((G100*H100-G100),8) | J100: =G100+I100
A101: =IF(DAY(D101)=DAY($L$1+1),A100+1,A100) | B101: =IF(DAY(D101)=DAY($L$1+1),1,B100+1) | C101: =IF(DAY(D101)=DAY($L$1+1),1,C100+1) | D101: =D100+1 | E101: =IF(DAY(D101)=DAY($L$1+1),TRUNC((N100),8),E100) | F101: =TRUNC(((1+VLOOKUP(A101,IPCA!$A$2:$C$140,3,0)))^(C101/(EDATE(D101-C101,1)-(D101-C101))),8) | G101: =TRUNC((E101*F101),8) | H101: =ROUND(((1+$H$4)^(30/360))^(C101/(EDATE(D101-B101,1)-(D101-B101))),9) | I101: =TRUNC((G101*H101-G101),8) | J101: =G101+I101
A102: =IF(DAY(D102)=DAY($L$1+1),A101+1,A101) | B102: =IF(DAY(D102)=DAY($L$1+1),1,B101+1) | C102: =IF(DAY(D102)=DAY($L$1+1),1,C101+1) | D102: =D101+1 | E102: =IF(DAY(D102)=DAY($L$1+1),TRUNC((N101),8),E101) | F102: =TRUNC(((1+VLOOKUP(A102,IPCA!$A$2:$C$140,3,0)))^(C102/(EDATE(D102-C102,1)-(D102-C102))),8) | G102: =TRUNC((E102*F102),8) | H102: =ROUND(((1+$H$4)^(30/360))^(C102/(EDATE(D102-B102,1)-(D102-B102))),9) | I102: =TRUNC((G102*H102-G102),8) | J102: =G102+I102
A103: =IF(DAY(D103)=DAY($L$1+1),A102+1,A102) | B103: =IF(DAY(D103)=DAY($L$1+1),1,B102+1) | C103: =IF(DAY(D103)=DAY($L$1+1),1,C102+1) | D103: =D102+1 | E103: =IF(DAY(D103)=DAY($L$1+1),TRUNC((N102),8),E102) | F103: =TRUNC(((1+VLOOKUP(A103,IPCA!$A$2:$C$140,3,0)))^(C103/(EDATE(D103-C103,1)-(D103-C103))),8) | G103: =TRUNC((E103*F103),8) | H103: =ROUND(((1+$H$4)^(30/360))^(C103/(EDATE(D103-B103,1)-(D103-B103))),9) | I103: =TRUNC((G103*H103-G103),8) | J103: =G103+I103
A104: =IF(DAY(D104)=DAY($L$1+1),A103+1,A103) | B104: =IF(DAY(D104)=DAY($L$1+1),1,B103+1) | C104: =IF(DAY(D104)=DAY($L$1+1),1,C103+1) | D104: =D103+1 | E104: =IF(DAY(D104)=DAY($L$1+1),TRUNC((N103),8),E103) | F104: =TRUNC(((1+VLOOKUP(A104,IPCA!$A$2:$C$140,3,0)))^(C104/(EDATE(D104-C104,1)-(D104-C104))),8) | G104: =TRUNC((E104*F104),8) | H104: =ROUND(((1+$H$4)^(30/360))^(C104/(EDATE(D104-B104,1)-(D104-B104))),9) | I104: =TRUNC((G104*H104-G104),8) | J104: =G104+I104
... A108: =IF(DAY(D108)=DAY($L$1+1),A107+1,A107) | B108: =IF(DAY(D108)=DAY($L$1+1),1,B107+1) | C108: =IF(DAY(D108)=DAY($L$1+1),1,C107+1) | D108: =D107+1 | E108: =IF(DAY(D108)=DAY($L$1+1),TRUNC((N107),8),E107) | F108: =TRUNC(((1+VLOOKUP(A108,IPCA!$A$2:$C$140,3,0)))^(C108/(EDATE(D108-C108,1)-(D108-C108))),8) | G108: =TRUNC((E108*F108),8) | H108: =ROUND(((1+$H$4)^(30/360))^(C108/(EDATE(D108-B108,1)-(D108-B108))),9) | I108: =TRUNC((G108*H108-G108),8) | J108: =G108+I108
A109: =IF(DAY(D109)=DAY($L$1+1),A108+1,A108) | B109: =IF(DAY(D109)=DAY($L$1+1),1,B108+1) | C109: =IF(DAY(D109)=DAY($L$1+1),1,C108+1) | D109: =D108+1 | E109: =IF(DAY(D109)=DAY($L$1+1),TRUNC((N108),8),E108) | F109: =TRUNC(((1+VLOOKUP(A109,IPCA!$A$2:$C$140,3,0)))^(C109/(EDATE(D109-C109,1)-(D109-C109))),8) | G109: =TRUNC((E109*F109),8) | H109: =ROUND(((1+$H$4)^(30/360))^(C109/(EDATE(D109-B109,1)-(D109-B109))),9) | I109: =TRUNC((G109*H109-G109),8) | J109: =G109+I109 | K109: Cri Integralizado | L109: =L79
A110: =IF(DAY(D110)=DAY($L$1+1),A109+1,A109) | B110: =IF(DAY(D110)=DAY($L$1+1),1,B109+1) | C110: =IF(DAY(D110)=DAY($L$1+1),1,C109+1) | D110: =D109+1 | E110: =IF(DAY(D110)=DAY($L$1+1),TRUNC((N109),8),E109) | F110: =TRUNC(((1+VLOOKUP(A110,IPCA!$A$2:$C$140,3,0)))^(C110/(EDATE(D110-C110,1)-(D110-C110))),8) | G110: =TRUNC((E110*F110),8) | H110: =ROUND(((1+$H$4)^(30/360))^(C110/(EDATE(D110-B110,1)-(D110-B110))),9) | I110: =TRUNC((G110*H110-G110),8) | J110: =G110+I110 | K110: JUROS | L110: AMORTIZAÇÃO | M110: AMEX | N110: RESIDUAL
A111: =IF(DAY(D111)=DAY($L$1+1),A110+1,A110) | B111: =IF(DAY(D111)=DAY($L$1+1),1,B110+1) | C111: =IF(DAY(D111)=DAY($L$1+1),1,C110+1) | D111: =D110+1 | E111: =IF(DAY(D111)=DAY($L$1+1),TRUNC((N110),8),E110) | F111: =TRUNC(((1+VLOOKUP(A111,IPCA!$A$2:$C$140,3,0)))^(C111/(EDATE(D111-C111,1)-(D111-C111))),8) | G111: =TRUNC((E111*F111),8) | H111: =ROUND(((1+$H$4)^(30/360))^(C111/(EDATE(D111-B111,1)-(D111-B111))),9) | I111: =TRUNC((G111*H111-G111),8) | J111: =G111+I111 | K111: 0 | L111: =TRUNC(G111*VLOOKUP(D111,'Amort TS'!$G$3:$H$140,2,0),8) | M111: 0 | N111: =J111-K111-L111-M111
...

Sheet Amort TS
F1: TABELA DE AMORTIZAÇÃO DOS CRI
J2: DADOS DA PMT | Q2: CONTABILIDADE | R2: CORREÇÃO
C3: TRIMESTRE | D3: MÊS | E3: ANO | F3: Evento | G3: Data | H3: Amortização | J3: JUROS | K3: AMORTIZAÇÃO | L3: PMT | M3: AMEX | N3: PMT C/ AMEX | O3: CRI INTEGRALIZADO | P3: SALDO DEVEDOR (EVENTO) = AmorTs | Q3: SALDO DEVEDOR (ÚLTIMO DIA DO MÊS)
A4: =CONCATENATE(C4,D4,E4) | B4: =CONCATENATE(D4,E4) | C4: =IF(D4>=1,IF(D4<=3,"1",IF(D4>=4,IF(D4<=6,"2",IF(D4>=7,IF(D4<=9,"3",IF(D4>=10,IF(D4<=12,"4","-")))))))) | D4: =MONTH(G4) | E4: =YEAR(G4) | F4: 1 | G4: 44767 | H4: 0 | I4: 29 | J4: =IFERROR((VLOOKUP($G4,'22F1187231'!$D$3:$N$4160,8,1))*O4,0) | K4: =VLOOKUP(G4,'22F1187231'!$D$5:$L$4163,9,0)*O4 | L4: =SUM(J4:K4) | M4: =(VLOOKUP($G4,'22F1187231'!$D$5:$N$4163,10,1))*O4 | N4: =SUM(L4:M4) | O4: 1113210 | P4: =VLOOKUP(G4,'22F1187231'!$D$5:$J$4160,7,0)*O4-(SUM(J4:K4,M4)) | Q4: =(VLOOKUP(EOMONTH(G4,0),'22F1187231'!$D$5:$J$4160,7,0))*O4 | R4: =(VLOOKUP(G4,'22F1187231'!$D$5:$J$4160,4,0)-VLOOKUP(G4,'22F1187231'!$D$5:$J$4160,2,0))*O4 | T4: CVM / PENTAGONO
A5: =CONCATENATE(C5,D5,E5) | B5: =CONCATENATE(D5,E5) | C5: =IF(D5>=1,IF(D5<=3,"1",IF(D5>=4,IF(D5<=6,"2",IF(D5>=7,IF(D5<=9,"3",IF(D5>=10,IF(D5<=12,"4","-")))))))) | D5: =MONTH(G5) | E5: =YEAR(G5) | F5: =F4+1 | G5: 44798 | H5: 0 | I5: 30 | J5: =IFERROR((VLOOKUP($G5,'22F1187231'!$D$3:$N$4160,8,1))*O5,0) | K5: =VLOOKUP(G5,'22F1187231'!$D$5:$L$4163,9,0)*O5 | L5: =SUM(J5:K5) | M5: =(VLOOKUP($G5,'22F1187231'!$D$5:$N$4163,10,1))*O5 | N5: =SUM(L5:M5) | O5: 1113210 | P5: =VLOOKUP(G5,'22F1187231'!$D$5:$J$4160,7,0)*O5-(SUM(J5:K5,M5)) | Q5: =(VLOOKUP(EOMONTH(G5,0),'22F1187231'!$D$5:$J$4160,7,0))*O5 | R5: =(VLOOKUP(G5,'22F1187231'!$D$5:$J$4160,4,0)-VLOOKUP(G5,'22F1187231'!$D$5:$J$4160,2,0))*O5 | T5: SET/2023
A6: =CONCATENATE(C6,D6,E6) | B6: =CONCATENATE(D6,E6) | C6: =IF(D6>=1,IF(D6<=3,"1",IF(D6>=4,IF(D6<=6,"2",IF(D6>=7,IF(D6<=9,"3",IF(D6>=10,IF(D6<=12,"4","-")))))))) | D6: =MONTH(G6) | E6: =YEAR(G6) | F6: =F5+1 | G6: 44829 | H6: 0 | I6: 31 | J6: =IFERROR((VLOOKUP($G6,'22F1187231'!$D$3:$N$4160,8,1))*O6,0) | K6: =VLOOKUP(G6,'22F1187231'!$D$5:$L$4163,9,0)*O6 | L6: =SUM(J6:K6) | M6: =(VLOOKUP($G6,'22F1187231'!$D$5:$N$4163,10,1))*O6 | N6: =SUM(L6:M6) | O6: 1113210 | P6: =VLOOKUP(G6,'22F1187231'!$D$5:$J$4160,7,0)*O6-(SUM(J6:K6,M6)) | Q6: =(VLOOKUP(EOMONTH(G6,0),'22F1187231'!$D$5:$J$4160,7,0))*O6 | R6: =(VLOOKUP(G6,'22F1187231'!$D$5:$J$4160,4,0)-VLOOKUP(G6,'22F1187231'!$D$5:$J$4160,2,0))*O6 | T6: Circulante: | U6: =SUM(N18:N29)
A7: =CONCATENATE(C7,D7,E7) | B7: =CONCATENATE(D7,E7) | C7: =IF(D7>=1,IF(D7<=3,"1",IF(D7>=4,IF(D7<=6,"2",IF(D7>=7,IF(D7<=9,"3",IF(D7>=10,IF(D7<=12,"4","-")))))))) | D7: =MONTH(G7) | E7: =YEAR(G7) | F7: =F6+1 | G7: 44859 | H7: 0 | I7: 32 | J7: =IFERROR((VLOOKUP($G7,'22F1187231'!$D$3:$N$4160,8,1))*O7,0) | K7: =VLOOKUP(G7,'22F1187231'!$D$5:$L$4163,9,0)*O7 | L7: =SUM(J7:K7) | M7: =(VLOOKUP($G7,'22F1187231'!$D$5:$N$4163,10,1))*O7 | N7: =SUM(L7:M7) | O7: 1113210 | P7: =VLOOKUP(G7,'22F1187231'!$D$5:$J$4160,7,0)*O7-(SUM(J7:K7,M7)) | Q7: =(VLOOKUP(EOMONTH(G7,0),'22F1187231'!$D$5:$J$4160,7,0))*O7 | R7: =(VLOOKUP(G7,'22F1187231'!$D$5:$J$4160,4,0)-VLOOKUP(G7,'22F1187231'!$D$5:$J$4160,2,0))*O7 | T7: Não Circulante: | U7: =P17-U6
A8: =CONCATENATE(C8,D8,E8) | B8: =CONCATENATE(D8,E8) | C8: =IF(D8>=1,IF(D8<=3,"1",IF(D8>=4,IF(D8<=6,"2",IF(D8>=7,IF(D8<=9,"3",IF(D8>=10,IF(D8<=12,"4","-")))))))) | D8: =MONTH(G8) | E8: =YEAR(G8) | F8: =F7+1 | G8: 44890 | H8: 0 | I8: 33 | J8: =IFERROR((VLOOKUP($G8,'22F1187231'!$D$3:$N$4160,8,1))*O8,0) | K8: =VLOOKUP(G8,'22F1187231'!$D$5:$L$4163,9,0)*O8 | L8: =SUM(J8:K8) | M8: =(VLOOKUP($G8,'22F1187231'!$D$5:$N$4163,10,1))*O8 | N8: =SUM(L8:M8) | O8: 1113210 | P8: =VLOOKUP(G8,'22F1187231'!$D$5:$J$4160,7,0)*O8-(SUM(J8:K8,M8)) | Q8: =(VLOOKUP(EOMONTH(G8,0),'22F1187231'!$D$5:$J$4160,7,0))*O8 | R8: =(VLOOKUP(G8,'22F1187231'!$D$5:$J$4160,4,0)-VLOOKUP(G8,'22F1187231'!$D$5:$J$4160,2,0))*O8
A9: =CONCATENATE(C9,D9,E9) | B9: =CONCATENATE(D9,E9) | C9: =IF(D9>=1,IF(D9<=3,"1",IF(D9>=4,IF(D9<=6,"2",IF(D9>=7,IF(D9<=9,"3",IF(D9>=10,IF(D9<=12,"4","-")))))))) | D9: =MONTH(G9) | E9: =YEAR(G9) | F9: =F8+1 | G9: 44920 | H9: 0 | I9: 34 | J9: =IFERROR((VLOOKUP($G9,'22F1187231'!$D$3:$N$4160,8,1))*O9,0) | K9: =VLOOKUP(G9,'22F1187231'!$D$5:$L$4163,9,0)*O9 | L9: =SUM(J9:K9) | M9: =(VLOOKUP($G9,'22F1187231'!$D$5:$N$4163,10,1))*O9 | N9: =SUM(L9:M9) | O9: 1113210 | P9: =VLOOKUP(G9,'22F1187231'!$D$5:$J$4160,7,0)*O9-(SUM(J9:K9,M9)) | Q9: =(VLOOKUP(EOMONTH(G9,0),'22F1187231'!$D$5:$J$4160,7,0))*O9 | R9: =(VLOOKUP(G9,'22F1187231'!$D$5:$J$4160,4,0)-VLOOKUP(G9,'22F1187231'!$D$5:$J$4160,2,0))*O9
A10: =CONCATENATE(C10,D10,E10) | B10: =CONCATENATE(D10,E10) | C10: =IF(D10>=1,IF(D10<=3,"1",IF(D10>=4,IF(D10<=6,"2",IF(D10>=7,IF(D10<=9,"3",IF(D10>=10,IF(D10<=12,"4","-")))))))) | D10: =MONTH(G10) | E10: =YEAR(G10) | F10: =F9+1 | G10: 44951 | H10: 0 | I10: 35 | J10: =IFERROR((VLOOKUP($G10,'22F1187231'!$D$3:$N$4160,8,1))*O10,0) | K10: =VLOOKUP(G10,'22F1187231'!$D$5:$L$4163,9,0)*O10 | L10: =SUM(J10:K10) | M10: =(VLOOKUP($G10,'22F1187231'!$D$5:$N$4163,10,1))*O10 | N10: =SUM(L10:M10) | O10: 1113210 | P10: =VLOOKUP(G10,'22F1187231'!$D$5:$J$4160,7,0)*O10-(SUM(J10:K10,M10)) | Q10: =(VLOOKUP(EOMONTH(G10,0),'22F1187231'!$D$5:$J$4160,7,0))*O10 | R10: =(VLOOKUP(G10,'22F1187231'!$D$5:$J$4160,4,0)-VLOOKUP(G10,'22F1187231'!$D$5:$J$4160,2,0))*O10 | T10: CONFERÊNCIA
A11: =CONCATENATE(C11,D11,E11) | B11: =CONCATENATE(D11,E11) | C11: =IF(D11>=1,IF(D11<=3,"1",IF(D11>=4,IF(D11<=6,"2",IF(D11>=7,IF(D11<=9,"3",IF(D11>=10,IF(D11<=12,"4","-")))))))) | D11: =MONTH(G11) | E11: =YEAR(G11) | F11: =F10+1 | G11: 44982 | H11: 0 | I11: 36 | J11: =IFERROR((VLOOKUP($G11,'22F1187231'!$D$3:$N$4160,8,1))*O11,0) | K11: =VLOOKUP(G11,'22F1187231'!$D$5:$L$4163,9,0)*O11 | L11: =SUM(J11:K11) | M11: =(VLOOKUP($G11,'22F1187231'!$D$5:$N$4163,10,1))*O11 | N11: =SUM(L11:M11) | O11: 1113210 | P11: =VLOOKUP(G11,'22F1187231'!$D$5:$J$4160,7,0)*O11-(SUM(J11:K11,M11)) | Q11: =(VLOOKUP(EOMONTH(G11,0),'22F1187231'!$D$5:$J$4160,7,0))*O11 | R11: =(VLOOKUP(G11,'22F1187231'!$D$5:$J$4160,4,0)-VLOOKUP(G11,'22F1187231'!$D$5:$J$4160,2,0))*O11 | T11: PAGAMENTO | U11: INICIO PERIODO | V11: FINAL PERÍODO | W11: BUSCAR SALDO DIA
A12: =CONCATENATE(C12,D12,E12) | B12: =CONCATENATE(D12,E12) | C12: =IF(D12>=1,IF(D12<=3,"1",IF(D12>=4,IF(D12<=6,"2",IF(D12>=7,IF(D12<=9,"3",IF(D12>=10,IF(D12<=12,"4","-")))))))) | D12: =MONTH(G12) | E12: =YEAR(G12) | F12: =F11+1 | G12: 45010 | H12: 0 | I12: 37 | J12: =IFERROR((VLOOKUP($G12,'22F1187231'!$D$3:$N$4160,8,1))*O12,0) | K12: =VLOOKUP(G12,'22F1187231'!$D$5:$L$4163,9,0)*O12 | L12: =SUM(J12:K12) | M12: =(VLOOKUP($G12,'22F1187231'!$D$5:$N$4163,10,1))*O12 | N12: =SUM(L12:M12) | O12: 1113210 | P12: =VLOOKUP(G12,'22F1187231'!$D$5:$J$4160,7,0)*O12-(SUM(J12:K12,M12)) | Q12: =(VLOOKUP(EOMONTH(G12,0),'22F1187231'!$D$5:$J$4160,7,0))*O12 | R12: =(VLOOKUP(G12,'22F1187231'!$D$5:$J$4160,4,0)-VLOOKUP(G12,'22F1187231'!$D$5:$J$4160,2,0))*O12 | U12: 44470 | V12: 44834 | W12: 44824
A13: =CONCATENATE(C13,D13,E13) | B13: =CONCATENATE(D13,E13) | C13: =IF(D13>=1,IF(D13<=3,"1",IF(D13>=4,IF(D13<=6,"2",IF(D13>=7,IF(D13<=9,"3",IF(D13>=10,IF(D13<=12,"4","-")))))))) | D13: =MONTH(G13) | E13: =YEAR(G13) | F13: =F12+1 | G13: 45041 | H13: 0 | I13: 38 | J13: =IFERROR((VLOOKUP($G13,'22F1187231'!$D$3:$N$4160,8,1))*O13,0) | K13: =VLOOKUP(G13,'22F1187231'!$D$5:$L$4163,9,0)*O13 | L13: =SUM(J13:K13) | M13: =(VLOOKUP($G13,'22F1187231'!$D$5:$N$4163,10,1))*O13 | N13: =SUM(L13:M13) | O13: 1113210 | P13: =VLOOKUP(G13,'22F1187231'!$D$5:$J$4160,7,0)*O13-(SUM(J13:K13,M13)) | Q13: =(VLOOKUP(EOMONTH(G13,0),'22F1187231'!$D$5:$J$4160,7,0))*O13 | R13: =(VLOOKUP(G13,'22F1187231'!$D$5:$J$4160,4,0)-VLOOKUP(G13,'22F1187231'!$D$5:$J$4160,2,0))*O13 | T13: Juros | U13: =SUMIFS(J:J,G:G,">="&$U$12,G:G,"<="&$V$12)
A14: =CONCATENATE(C14,D14,E14) | B14: =CONCATENATE(D14,E14) | C14: =IF(D14>=1,IF(D14<=3,"1",IF(D14>=4,IF(D14<=6,"2",IF(D14>=7,IF(D14<=9,"3",IF(D14>=10,IF(D14<=12,"4","-")))))))) | D14: =MONTH(G14) | E14: =YEAR(G14) | F14: =F13+1 | G14: 45071 | H14: 0 | I14: 39 | J14: =IFERROR((VLOOKUP($G14,'22F1187231'!$D$3:$N$4160,8,1))*O14,0) | K14: =VLOOKUP(G14,'22F1187231'!$D$5:$L$4163,9,0)*O14 | L14: =SUM(J14:K14) | M14: =(VLOOKUP($G14,'22F1187231'!$D$5:$N$4163,10,1))*O14 | N14: =SUM(L14:M14) | O14: 1113210 | P14: =VLOOKUP(G14,'22F1187231'!$D$5:$J$4160,7,0)*O14-(SUM(J14:K14,M14)) | Q14: =(VLOOKUP(EOMONTH(G14,0),'22F1187231'!$D$5:$J$4160,7,0))*O14 | R14: =(VLOOKUP(G14,'22F1187231'!$D$5:$J$4160,4,0)-VLOOKUP(G14,'22F1187231'!$D$5:$J$4160,2,0))*O14 | T14: Amortização | U14: =SUMIFS(K:K,G:G,">="&$U$12,G:G,"<="&$V$12)
A15: =CONCATENATE(C15,D15,E15) | B15: =CONCATENATE(D15,E15) | C15: =IF(D15>=1,IF(D15<=3,"1",IF(D15>=4,IF(D15<=6,"2",IF(D15>=7,IF(D15<=9,"3",IF(D15>=10,IF(D15<=12,"4","-")))))))) | D15: =MONTH(G15) | E15: =YEAR(G15) | F15: =F14+1 | G15: 45102 | H15: 0 | I15: 40 | J15: =IFERROR((VLOOKUP($G15,'22F1187231'!$D$3:$N$4160,8,1))*O15,0) | K15: =VLOOKUP(G15,'22F1187231'!$D$5:$L$4163,9,0)*O15 | L15: =SUM(J15:K15) | M15: =(VLOOKUP($G15,'22F1187231'!$D$5:$N$4163,10,1))*O15 | N15: =SUM(L15:M15) | O15: 1113210 | P15: =VLOOKUP(G15,'22F1187231'!$D$5:$J$4160,7,0)*O15-(SUM(J15:K15,M15)) | Q15: =(VLOOKUP(EOMONTH(G15,0),'22F1187231'!$D$5:$J$4160,7,0))*O15 | R15: =(VLOOKUP(G15,'22F1187231'!$D$5:$J$4160,4,0)-VLOOKUP(G15,'22F1187231'!$D$5:$J$4160,2,0))*O15 | T15: Amex | U15: =SUMIFS(M:M,G:G,">="&$U$12,G:G,"<="&$V$12)
A16: =CONCATENATE(C16,D16,E16) | B16: =CONCATENATE(D16,E16) | C16: =IF(D16>=1,IF(D16<=3,"1",IF(D16>=4,IF(D16<=6,"2",IF(D16>=7,IF(D16<=9,"3",IF(D16>=10,IF(D16<=12,"4","-")))))))) | D16: =MONTH(G16) | E16: =YEAR(G16) | F16: =F15+1 | G16: 45132 | H16: 0.004083 | I16: 41 | J16: =IFERROR((VLOOKUP($G16,'22F1187231'!$D$3:$N$4160,8,1))*O16,0) | K16: =VLOOKUP(G16,'22F1187231'!$D$5:$L$4163,9,0)*O16 | L16: =SUM(J16:K16) | M16: =(VLOOKUP($G16,'22F1187231'!$D$5:$N$4163,10,1))*O16 | N16: =SUM(L16:M16) | O16: 1113210 | P16: =VLOOKUP(G16,'22F1187231'!$D$5:$J$4160,7,0)*O16-(SUM(J16:K16,M16)) | Q16: =(VLOOKUP(EOMONTH(G16,0),'22F1187231'!$D$5:$J$4160,7,0))*O16 | R16: =(VLOOKUP(G16,'22F1187231'!$D$5:$J$4160,4,0)-VLOOKUP(G16,'22F1187231'!$D$5:$J$4160,2,0))*O16 | T16: Correcao | U16: =SUMIFS(R:R,G:G,">="&$U$12,G:G,"<="&$V$12)
A17: =CONCATENATE(C17,D17,E17) | B17: =CONCATENATE(D17,E17) | C17: =IF(D17>=1,IF(D17<=3,"1",IF(D17>=4,IF(D17<=6,"2",IF(D17>=7,IF(D17<=9,"3",IF(D17>=10,IF(D17<=12,"4","-")))))))) | D17: =MONTH(G17) | E17: =YEAR(G17) | F17: =F16+1 | G17: 45163 | H17: 0.004123 | I17: 42 | J17: =IFERROR((VLOOKUP($G17,'22F1187231'!$D$3:$N$4160,8,1))*O17,0) | K17: =VLOOKUP(G17,'22F1187231'!$D$5:$L$4163,9,0)*O17 | L17: =SUM(J17:K17) | M17: =(VLOOKUP($G17,'22F1187231'!$D$5:$N$4163,10,1))*O17 | N17: =SUM(L17:M17) | O17: 1113210 | P17: =VLOOKUP(G17,'22F1187231'!$D$5:$J$4160,7,0)*O17-(SUM(J17:K17,M17)) | Q17: =(VLOOKUP(EOMONTH(G17,0),'22F1187231'!$D$5:$J$4160,7,0))*O17 | R17: =(VLOOKUP(G17,'22F1187231'!$D$5:$J$4160,4,0)-VLOOKUP(G17,'22F1187231'!$D$5:$J$4160,2,0))*O17 | T17: Saldo Operação | U17: ='22F1187231'!N82
A18: =CONCATENATE(C18,D18,E18) | B18: =CONCATENATE(D18,E18) | C18: =IF(D18>=1,IF(D18<=3,"1",IF(D18>=4,IF(D18<=6,"2",IF(D18>=7,IF(D18<=9,"3",IF(D18>=10,IF(D18<=12,"4","-")))))))) | D18: =MONTH(G18) | E18: =YEAR(G18) | F18: =F17+1 | G18: 45194 | H18: 0.004164 | I18: 43 | J18: =IFERROR((VLOOKUP($G18,'22F1187231'!$D$3:$N$4160,8,1))*O18,0) | K18: =VLOOKUP(G18,'22F1187231'!$D$5:$L$4163,9,0)*O18 | L18: =SUM(J18:K18) | M18: =(VLOOKUP($G18,'22F1187231'!$D$5:$N$4163,10,1))*O18 | N18: =SUM(L18:M18) | O18: 1113210 | P18: =VLOOKUP(G18,'22F1187231'!$D$5:$J$4160,7,0)*O18-(SUM(J18:K18,M18)) | Q18: =(VLOOKUP(EOMONTH(G18,0),'22F1187231'!$D$5:$J$4160,7,0))*O18 | R18: =(VLOOKUP(G18,'22F1187231'!$D$5:$J$4160,4,0)-VLOOKUP(G18,'22F1187231'!$D$5:$J$4160,2,0))*O18
A19: =CONCATENATE(C19,D19,E19) | B19: =CONCATENATE(D19,E19) | C19: =IF(D19>=1,IF(D19<=3,"1",IF(D19>=4,IF(D19<=6,"2",IF(D19>=7,IF(D19<=9,"3",IF(D19>=10,IF(D19<=12,"4","-")))))))) | D19: =MONTH(G19) | E19: =YEAR(G19) | F19: =F18+1 | G19: 45224 | H19: 0.004216 | I19: 44 | J19: =IFERROR((VLOOKUP($G19,'22F1187231'!$D$3:$N$4160,8,1))*O19,0) | K19: =VLOOKUP(G19,'22F1187231'!$D$5:$L$4163,9,0)*O19 | L19: =SUM(J19:K19) | M19: =(VLOOKUP($G19,'22F1187231'!$D$5:$N$4163,10,1))*O19 | N19: =SUM(L19:M19) | O19: 1113210 | P19: =VLOOKUP(G19,'22F1187231'!$D$5:$J$4160,7,0)*O19-(SUM(J19:K19,M19)) | Q19: =(VLOOKUP(EOMONTH(G19,0),'22F1187231'!$D$5:$J$4160,7,0))*O19 | R19: =(VLOOKUP(G19,'22F1187231'!$D$5:$J$4160,4,0)-VLOOKUP(G19,'22F1187231'!$D$5:$J$4160,2,0))*O19
A20: =CONCATENATE(C20,D20,E20) | B20: =CONCATENATE(D20,E20) | C20: =IF(D20>=1,IF(D20<=3,"1",IF(D20>=4,IF(D20<=6,"2",IF(D20>=7,IF(D20<=9,"3",IF(D20>=10,IF(D20<=12,"4","-")))))))) | D20: =MONTH(G20) | E20: =YEAR(G20) | F20: =F19+1 | G20: 45255 | H20: 0.004258 | I20: 45 | J20: =IFERROR((VLOOKUP($G20,'22F1187231'!$D$3:$N$4160,8,1))*O20,0) | K20: =VLOOKUP(G20,'22F1187231'!$D$5:$L$4163,9,0)*O20 | L20: =SUM(J20:K20) | M20: =(VLOOKUP($G20,'22F1187231'!$D$5:$N$4163,10,1))*O20 | N20: =SUM(L20:M20) | O20: 1113210 | P20: =VLOOKUP(G20,'22F1187231'!$D$5:$J$4160,7,0)*O20-(SUM(J20:K20,M20)) | Q20: =(VLOOKUP(EOMONTH(G20,0),'22F1187231'!$D$5:$J$4160,7,0))*O20 | R20: =(VLOOKUP(G20,'22F1187231'!$D$5:$J$4160,4,0)-VLOOKUP(G20,'22F1187231'!$D$5:$J$4160,2,0))*O20 | T20: Curto Prazo | U20: =SUM(N7:N18) | V20: Direitos Creditórios a Receber( Ativo/Passivo Circulante)
A21: =CONCATENATE(C21,D21,E21) | B21: =CONCATENATE(D21,E21) | C21: =IF(D21>=1,IF(D21<=3,"1",IF(D21>=4,IF(D21<=6,"2",IF(D21>=7,IF(D21<=9,"3",IF(D21>=10,IF(D21<=12,"4","-")))))))) | D21: =MONTH(G21) | E21: =YEAR(G21) | F21: =F20+1 | G21: 45285 | H21: 0.004388 | I21: 46 | J21: =IFERROR((VLOOKUP($G21,'22F1187231'!$D$3:$N$4160,8,1))*O21,0) | K21: =VLOOKUP(G21,'22F1187231'!$D$5:$L$4163,9,0)*O21 | L21: =SUM(J21:K21) | M21: =(VLOOKUP($G21,'22F1187231'!$D$5:$N$4163,10,1))*O21 | N21: =SUM(L21:M21) | O21: 1113210 | P21: =VLOOKUP(G21,'22F1187231'!$D$5:$J$4160,7,0)*O21-(SUM(J21:K21,M21)) | Q21: =(VLOOKUP(EOMONTH(G21,0),'22F1187231'!$D$5:$J$4160,7,0))*O21 | R21: =(VLOOKUP(G21,'22F1187231'!$D$5:$J$4160,4,0)-VLOOKUP(G21,'22F1187231'!$D$5:$J$4160,2,0))*O21 | T21: Longo Prazo | U21: =P6-U20 | V21: Direitos Creditórios a Receber( Ativo/Passivo Não Circulante)
A22: =CONCATENATE(C22,D22,E22) | B22: =CONCATENATE(D22,E22) | C22: =IF(D22>=1,IF(D22<=3,"1",IF(D22>=4,IF(D22<=6,"2",IF(D22>=7,IF(D22<=9,"3",IF(D22>=10,IF(D22<=12,"4","-")))))))) | D22: =MONTH(G22) | E22: =YEAR(G22) | F22: =F21+1 | G22: 45316 | H22: 0.004605 | I22: 47 | J22: =IFERROR((VLOOKUP($G22,'22F1187231'!$D$3:$N$4160,8,1))*O22,0) | K22: =VLOOKUP(G22,'22F1187231'!$D$5:$L$4163,9,0)*O22 | L22: =SUM(J22:K22) | M22: =(VLOOKUP($G22,'22F1187231'!$D$5:$N$4163,10,1))*O22 | N22: =SUM(L22:M22) | O22: 1113210 | P22: =VLOOKUP(G22,'22F1187231'!$D$5:$J$4160,7,0)*O22-(SUM(J22:K22,M22)) | Q22: =(VLOOKUP(EOMONTH(G22,0),'22F1187231'!$D$5:$J$4160,7,0))*O22 | R22: =(VLOOKUP(G22,'22F1187231'!$D$5:$J$4160,4,0)-VLOOKUP(G22,'22F1187231'!$D$5:$J$4160,2,0))*O22
A23: =CONCATENATE(C23,D23,E23) | B23: =CONCATENATE(D23,E23) | C23: =IF(D23>=1,IF(D23<=3,"1",IF(D23>=4,IF(D23<=6,"2",IF(D23>=7,IF(D23<=9,"3",IF(D23>=10,IF(D23<=12,"4","-")))))))) | D23: =MONTH(G23) | E23: =YEAR(G23) | F23: =F22+1 | G23: 45347 | H23: 0.004686 | I23: 48 | J23: =IFERROR((VLOOKUP($G23,'22F1187231'!$D$3:$N$4160,8,1))*O23,0) | K23: =VLOOKUP(G23,'22F1187231'!$D$5:$L$4163,9,0)*O23 | L23: =SUM(J23:K23) | M23: =(VLOOKUP($G23,'22F1187231'!$D$5:$N$4163,10,1))*O23 | N23: =SUM(L23:M23) | O23: 1113210 | P23: =VLOOKUP(G23,'22F1187231'!$D$5:$J$4160,7,0)*O23-(SUM(J23:K23,M23)) | Q23: =(VLOOKUP(EOMONTH(G23,0),'22F1187231'!$D$5:$J$4160,7,0))*O23 | R23: =(VLOOKUP(G23,'22F1187231'!$D$5:$J$4160,4,0)-VLOOKUP(G23,'22F1187231'!$D$5:$J$4160,2,0))*O23 | T23: PAGAMENTO | U23: Período (01/10/20 a 30/09/21)
A24: =CONCATENATE(C24,D24,E24) | B24: =CONCATENATE(D24,E24) | C24: =IF(D24>=1,IF(D24<=3,"1",IF(D24>=4,IF(D24<=6,"2",IF(D24>=7,IF(D24<=9,"3",IF(D24>=10,IF(D24<=12,"4","-")))))))) | D24: =MONTH(G24) | E24: =YEAR(G24) | F24: =F23+1 | G24: 45376 | H24: 0.004747 | I24: 49 | J24: =IFERROR((VLOOKUP($G24,'22F1187231'!$D$3:$N$4160,8,1))*O24,0) | K24: =VLOOKUP(G24,'22F1187231'!$D$5:$L$4163,9,0)*O24 | L24: =SUM(J24:K24) | M24: =(VLOOKUP($G24,'22F1187231'!$D$5:$N$4163,10,1))*O24 | N24: =SUM(L24:M24) | O24: 1113210 | P24: =VLOOKUP(G24,'22F1187231'!$D$5:$J$4160,7,0)*O24-(SUM(J24:K24,M24)) | Q24: =(VLOOKUP(EOMONTH(G24,0),'22F1187231'!$D$5:$J$4160,7,0))*O24 | R24: =(VLOOKUP(G24,'22F1187231'!$D$5:$J$4160,4,0)-VLOOKUP(G24,'22F1187231'!$D$5:$J$4160,2,0))*O24
A25: =CONCATENATE(C25,D25,E25) | B25: =CONCATENATE(D25,E25) | C25: =IF(D25>=1,IF(D25<=3,"1",IF(D25>=4,IF(D25<=6,"2",IF(D25>=7,IF(D25<=9,"3",IF(D25>=10,IF(D25<=12,"4","-")))))))) | D25: =MONTH(G25) | E25: =YEAR(G25) | F25: =F24+1 | G25: 45407 | H25: 0.004797 | I25: 50 | J25: =IFERROR((VLOOKUP($G25,'22F1187231'!$D$3:$N$4160,8,1))*O25,0) | K25: =VLOOKUP(G25,'22F1187231'!$D$5:$L$4163,9,0)*O25 | L25: =SUM(J25:K25) | M25: =(VLOOKUP($G25,'22F1187231'!$D$5:$N$4163,10,1))*O25 | N25: =SUM(L25:M25) | O25: 1113210 | P25: =VLOOKUP(G25,'22F1187231'!$D$5:$J$4160,7,0)*O25-(SUM(J25:K25,M25)) | Q25: =(VLOOKUP(EOMONTH(G25,0),'22F1187231'!$D$5:$J$4160,7,0))*O25 | R25: =(VLOOKUP(G25,'22F1187231'!$D$5:$J$4160,4,0)-VLOOKUP(G25,'22F1187231'!$D$5:$J$4160,2,0))*O25 | T25: Juros | U25: =SUM(J8:J19)
A26: =CONCATENATE(C26,D26,E26) | B26: =CONCATENATE(D26,E26) | C26: =IF(D26>=1,IF(D26<=3,"1",IF(D26>=4,IF(D26<=6,"2",IF(D26>=7,IF(D26<=9,"3",IF(D26>=10,IF(D26<=12,"4","-")))))))) | D26: =MONTH(G26) | E26: =YEAR(G26) | F26: =F25+1 | G26: 45437 | H26: 0.004847 | I26: 51 | J26: =IFERROR((VLOOKUP($G26,'22F1187231'!$D$3:$N$4160,8,1))*O26,0) | K26: =VLOOKUP(G26,'22F1187231'!$D$5:$L$4163,9,0)*O26 | L26: =SUM(J26:K26) | M26: =(VLOOKUP($G26,'22F1187231'!$D$5:$N$4163,10,1))*O26 | N26: =SUM(L26:M26) | O26: 1113210 | P26: =VLOOKUP(G26,'22F1187231'!$D$5:$J$4160,7,0)*O26-(SUM(J26:K26,M26)) | Q26: =(VLOOKUP(EOMONTH(G26,0),'22F1187231'!$D$5:$J$4160,7,0))*O26 | R26: =(VLOOKUP(G26,'22F1187231'!$D$5:$J$4160,4,0)-VLOOKUP(G26,'22F1187231'!$D$5:$J$4160,2,0))*O26 | T26: Amortização | U26: =SUM(K8:K19)
A27: =CONCATENATE(C27,D27,E27) | B27: =CONCATENATE(D27,E27) | C27: =IF(D27>=1,IF(D27<=3,"1",IF(D27>=4,IF(D27<=6,"2",IF(D27>=7,IF(D27<=9,"3",IF(D27>=10,IF(D27<=12,"4","-")))))))) | D27: =MONTH(G27) | E27: =YEAR(G27) | F27: =F26+1 | G27: 45468 | H27: 0.004899 | I27: 52 | J27: =IFERROR((VLOOKUP($G27,'22F1187231'!$D$3:$N$4160,8,1))*O27,0) | K27: =VLOOKUP(G27,'22F1187231'!$D$5:$L$4163,9,0)*O27 | L27: =SUM(J27:K27) | M27: =(VLOOKUP($G27,'22F1187231'!$D$5:$N$4163,10,1))*O27 | N27: =SUM(L27:M27) | O27: 1113210 | P27: =VLOOKUP(G27,'22F1187231'!$D$5:$J$4160,7,0)*O27-(SUM(J27:K27,M27)) | Q27: =(VLOOKUP(EOMONTH(G27,0),'22F1187231'!$D$5:$J$4160,7,0))*O27 | R27: =(VLOOKUP(G27,'22F1187231'!$D$5:$J$4160,4,0)-VLOOKUP(G27,'22F1187231'!$D$5:$J$4160,2,0))*O27 | T27: Amex | U27: =SUM(M7:M18)
A28: =CONCATENATE(C28,D28,E28) | B28: =CONCATENATE(D28,E28) | C28: =IF(D28>=1,IF(D28<=3,"1",IF(D28>=4,IF(D28<=6,"2",IF(D28>=7,IF(D28<=9,"3",IF(D28>=10,IF(D28<=12,"4","-")))))))) | D28: =MONTH(G28) | E28: =YEAR(G28) | F28: =F27+1 | G28: 45498 | H28: 0.004951 | I28: 53 | J28: =IFERROR((VLOOKUP($G28,'22F1187231'!$D$3:$N$4160,8,1))*O28,0) | K28: =VLOOKUP(G28,'22F1187231'!$D$5:$L$4163,9,0)*O28 | L28: =SUM(J28:K28) | M28: =(VLOOKUP($G28,'22F1187231'!$D$5:$N$4163,10,1))*O28 | N28: =SUM(L28:M28) | O28: 1113210 | P28: =VLOOKUP(G28,'22F1187231'!$D$5:$J$4160,7,0)*O28-(SUM(J28:K28,M28)) | Q28: =(VLOOKUP(EOMONTH(G28,0),'22F1187231'!$D$5:$J$4160,7,0))*O28 | R28: =(VLOOKUP(G28,'22F1187231'!$D$5:$J$4160,4,0)-VLOOKUP(G28,'22F1187231'!$D$5:$J$4160,2,0))*O28 | T28: Amort + Amex | U28: =SUM(K8:K19)+SUM(M8:M19)
A29: =CONCATENATE(C29,D29,E29) | B29: =CONCATENATE(D29,E29) | C29: =IF(D29>=1,IF(D29<=3,"1",IF(D29>=4,IF(D29<=6,"2",IF(D29>=7,IF(D29<=9,"3",IF(D29>=10,IF(D29<=12,"4","-")))))))) | D29: =MONTH(G29) | E29: =YEAR(G29) | F29: =F28+1 | G29: 45529 | H29: 0.005003 | I29: 54 | J29: =IFERROR((VLOOKUP($G29,'22F1187231'!$D$3:$N$4160,8,1))*O29,0) | K29: =VLOOKUP(G29,'22F1187231'!$D$5:$L$4163,9,0)*O29 | L29: =SUM(J29:K29) | M29: =(VLOOKUP($G29,'22F1187231'!$D$5:$N$4163,10,1))*O29 | N29: =SUM(L29:M29) | O29: 1113210 | P29: =VLOOKUP(G29,'22F1187231'!$D$5:$J$4160,7,0)*O29-(SUM(J29:K29,M29)) | Q29: =(VLOOKUP(EOMONTH(G29,0),'22F1187231'!$D$5:$J$4160,7,0))*O29 | R29: =(VLOOKUP(G29,'22F1187231'!$D$5:$J$4160,4,0)-VLOOKUP(G29,'22F1187231'!$D$5:$J$4160,2,0))*O29 | T29: Correção | U29: =SUM(R7:R18)
A30: =CONCATENATE(C30,D30,E30) | B30: =CONCATENATE(D30,E30) | C30: =IF(D30>=1,IF(D30<=3,"1",IF(D30>=4,IF(D30<=6,"2",IF(D30>=7,IF(D30<=9,"3",IF(D30>=10,IF(D30<=12,"4","-")))))))) | D30: =MONTH(G30) | E30: =YEAR(G30) | F30: =F29+1 | G30: 45560 | H30: 0.005057 | I30: 55 | J30: =IFERROR((VLOOKUP($G30,'22F1187231'!$D$3:$N$4160,8,1))*O30,0) | K30: =VLOOKUP(G30,'22F1187231'!$D$5:$L$4163,9,0)*O30 | L30: =SUM(J30:K30) | M30: =(VLOOKUP($G30,'22F1187231'!$D$5:$N$4163,10,1))*O30 | N30: =SUM(L30:M30) | O30: 1113210 | P30: =VLOOKUP(G30,'22F1187231'!$D$5:$J$4160,7,0)*O30-(SUM(J30:K30,M30)) | Q30: =(VLOOKUP(EOMONTH(G30,0),'22F1187231'!$D$5:$J$4160,7,0))*O30 | R30: =(VLOOKUP(G30,'22F1187231'!$D$5:$J$4160,4,0)-VLOOKUP(G30,'22F1187231'!$D$5:$J$4160,2,0))*O30
A31: =CONCATENATE(C31,D31,E31) | B31: =CONCATENATE(D31,E31) | C31: =IF(D31>=1,IF(D31<=3,"1",IF(D31>=4,IF(D31<=6,"2",IF(D31>=7,IF(D31<=9,"3",IF(D31>=10,IF(D31<=12,"4","-")))))))) | D31: =MONTH(G31) | E31: =YEAR(G31) | F31: 56 | G31: 45590 | H31: 0.005124 | I31: 56 | J31: =IFERROR((VLOOKUP($G31,'22F1187231'!$D$3:$N$4160,8,1))*O31,0) | K31: =VLOOKUP(G31,'22F1187231'!$D$5:$L$4163,9,0)*O31 | L31: =SUM(J31:K31) | M31: =(VLOOKUP($G31,'22F1187231'!$D$5:$N$4163,10,1))*O31 | N31: =SUM(L31:M31) | O31: 1113210 | P31: =VLOOKUP(G31,'22F1187231'!$D$5:$J$4160,7,0)*O31-(SUM(J31:K31,M31)) | Q31: =(VLOOKUP(EOMONTH(G31,0),'22F1187231'!$D$5:$J$4160,7,0))*O31 | R31: =(VLOOKUP(G31,'22F1187231'!$D$5:$J$4160,4,0)-VLOOKUP(G31,'22F1187231'!$D$5:$J$4160,2,0))*O31
A32: =CONCATENATE(C32,D32,E32) | B32: =CONCATENATE(D32,E32) | C32: =IF(D32>=1,IF(D32<=3,"1",IF(D32>=4,IF(D32<=6,"2",IF(D32>=7,IF(D32<=9,"3",IF(D32>=10,IF(D32<=12,"4","-")))))))) | D32: =MONTH(G32) | E32: =YEAR(G32) | F32: =F31+1 | G32: 45621 | H32: 0.005179 | I32: 57 | J32: =IFERROR((VLOOKUP($G32,'22F1187231'!$D$3:$N$4160,8,1))*O32,0) | K32: =VLOOKUP(G32,'22F1187231'!$D$5:$L$4163,9,0)*O32 | L32: =SUM(J32:K32) | M32: =(VLOOKUP($G32,'22F1187231'!$D$5:$N$4163,10,1))*O32 | N32: =SUM(L32:M32) | O32: 1113210 | P32: =VLOOKUP(G32,'22F1187231'!$D$5:$J$4160,7,0)*O32-(SUM(J32:K32,M32)) | Q32: =(VLOOKUP(EOMONTH(G32,0),'22F1187231'!$D$5:$J$4160,7,0))*O32 | R32: =(VLOOKUP(G32,'22F1187231'!$D$5:$J$4160,4,0)-VLOOKUP(G32,'22F1187231'!$D$5:$J$4160,2,0))*O32
A33: =CONCATENATE(C33,D33,E33) | B33: =CONCATENATE(D33,E33) | C33: =IF(D33>=1,IF(D33<=3,"1",IF(D33>=4,IF(D33<=6,"2",IF(D33>=7,IF(D33<=9,"3",IF(D33>=10,IF(D33<=12,"4","-")))))))) | D33: =MONTH(G5) | E33: =YEAR(G5) | F33: =F32+1 | G33: 45651 | H33: 0.005331 | I33: 58 | J33: =IFERROR((VLOOKUP($G33,'22F1187231'!$D$3:$N$4160,8,1))*O33,0) | K33: =VLOOKUP(G33,'22F1187231'!$D$5:$L$4163,9,0)*O33 | L33: =SUM(J33:K33) | M33: =(VLOOKUP($G33,'22F1187231'!$D$5:$N$4163,10,1))*O33 | N33: =SUM(L33:M33) | O33: 1113210 | P33: =VLOOKUP(G33,'22F1187231'!$D$5:$J$4160,7,0)*O33-(SUM(J33:K33,M33)) | Q33: =(VLOOKUP(EOMONTH(G33,0),'22F1187231'!$D$5:$J$4160,7,0))*O33 | R33: =(VLOOKUP(G33,'22F1187231'!$D$5:$J$4160,4,0)-VLOOKUP(G33,'22F1187231'!$D$5:$J$4160,2,0))*O33 | T33: *preencher apenas as células em amarelo para informe trimestral
A34: =CONCATENATE(C34,D34,E34) | B34: =CONCATENATE(D34,E34) | C34: =IF(D34>=1,IF(D34<=3,"1",IF(D34>=4,IF(D34<=6,"2",IF(D34>=7,IF(D34<=9,"3",IF(D34>=10,IF(D34<=12,"4","-")))))))) | D34: =MONTH(G6) | E34: =YEAR(G6) | F34: =F33+1 | G34: 45682 | H34: 0.005578 | I34: 59 | J34: =IFERROR((VLOOKUP($G34,'22F1187231'!$D$3:$N$4160,8,1))*O34,0) | K34: =VLOOKUP(G34,'22F1187231'!$D$5:$L$4163,9,0)*O34 | L34: =SUM(J34:K34) | M34: =(VLOOKUP($G34,'22F1187231'!$D$5:$N$4163,10,1))*O34 | N34: =SUM(L34:M34) | O34: 1113210 | P34: =VLOOKUP(G34,'22F1187231'!$D$5:$J$4160,7,0)*O34-(SUM(J34:K34,M34)) | Q34: =(VLOOKUP(EOMONTH(G34,0),'22F1187231'!$D$5:$J$4160,7,0))*O34 | R34: =(VLOOKUP(G34,'22F1187231'!$D$5:$J$4160,4,0)-VLOOKUP(G34,'22F1187231'!$D$5:$J$4160,2,0))*O34 | T34: PAGAMENTO | U34: TRIMESTRE | V34: ANO | W34: MÊS FECHAMENTO
A35: =CONCATENATE(C35,D35,E35) | B35: =CONCATENATE(D35,E35) | C35: =IF(D35>=1,IF(D35<=3,"1",IF(D35>=4,IF(D35<=6,"2",IF(D35>=7,IF(D35<=9,"3",IF(D35>=10,IF(D35<=12,"4","-")))))))) | D35: =MONTH(G7) | E35: =YEAR(G7) | F35: =F34+1 | G35: 45713 | H35: 0.005677 | I35: 60 | J35: =IFERROR((VLOOKUP($G35,'22F1187231'!$D$3:$N$4160,8,1))*O35,0) | K35: =VLOOKUP(G35,'22F1187231'!$D$5:$L$4163,9,0)*O35 | L35: =SUM(J35:K35) | M35: =(VLOOKUP($G35,'22F1187231'!$D$5:$N$4163,10,1))*O35 | N35: =SUM(L35:M35) | O35: 1113210 | P35: =VLOOKUP(G35,'22F1187231'!$D$5:$J$4160,7,0)*O35-(SUM(J35:K35,M35)) | Q35: =(VLOOKUP(EOMONTH(G35,0),'22F1187231'!$D$5:$J$4160,7,0))*O35 | R35: =(VLOOKUP(G35,'22F1187231'!$D$5:$J$4160,4,0)-VLOOKUP(G35,'22F1187231'!$D$5:$J$4160,2,0))*O35 | U35: 3 | V35: 2022 | W35: =U35*2
A36: =CONCATENATE(C36,D36,E36) | B36: =CONCATENATE(D36,E36) | C36: =IF(D36>=1,IF(D36<=3,"1",IF(D36>=4,IF(D36<=6,"2",IF(D36>=7,IF(D36<=9,"3",IF(D36>=10,IF(D36<=12,"4","-")))))))) | D36: =MONTH(G8) | E36: =YEAR(G8) | F36: =F35+1 | G36: 45741 | H36: 0.005756 | I36: 61 | J36: =IFERROR((VLOOKUP($G36,'22F1187231'!$D$3:$N$4160,8,1))*O36,0) | K36: =VLOOKUP(G36,'22F1187231'!$D$5:$L$4163,9,0)*O36 | L36: =SUM(J36:K36) | M36: =(VLOOKUP($G36,'22F1187231'!$D$5:$N$4163,10,1))*O36 | N36: =SUM(L36:M36) | O36: 1113210 | P36: =VLOOKUP(G36,'22F1187231'!$D$5:$J$4160,7,0)*O36-(SUM(J36:K36,M36)) | Q36: =(VLOOKUP(EOMONTH(G36,0),'22F1187231'!$D$5:$J$4160,7,0))*O36 | R36: =(VLOOKUP(G36,'22F1187231'!$D$5:$J$4160,4,0)-VLOOKUP(G36,'22F1187231'!$D$5:$J$4160,2,0))*O36 | T36: Juros | U36: =SUMIFS($J$1:$J$140,$C$1:$C$140,$U$35,E1:E140,$V$35)
A37: =CONCATENATE(C37,D37,E37) | B37: =CONCATENATE(D37,E37) | C37: =IF(D37>=1,IF(D37<=3,"1",IF(D37>=4,IF(D37<=6,"2",IF(D37>=7,IF(D37<=9,"3",IF(D37>=10,IF(D37<=12,"4","-")))))))) | D37: =MONTH(G9) | E37: =YEAR(G9) | F37: =F36+1 | G37: 45772 | H37: 0.005822 | I37: 62 | J37: =IFERROR((VLOOKUP($G37,'22F1187231'!$D$3:$N$4160,8,1))*O37,0) | K37: =VLOOKUP(G37,'22F1187231'!$D$5:$L$4163,9,0)*O37 | L37: =SUM(J37:K37) | M37: =(VLOOKUP($G37,'22F1187231'!$D$5:$N$4163,10,1))*O37 | N37: =SUM(L37:M37) | O37: 1113210 | P37: =VLOOKUP(G37,'22F1187231'!$D$5:$J$4160,7,0)*O37-(SUM(J37:K37,M37)) | Q37: =(VLOOKUP(EOMONTH(G37,0),'22F1187231'!$D$5:$J$4160,7,0))*O37 | R37: =(VLOOKUP(G37,'22F1187231'!$D$5:$J$4160,4,0)-VLOOKUP(G37,'22F1187231'!$D$5:$J$4160,2,0))*O37 | T37: Amortização | U37: =SUMIFS($K$4:$K$140,$C$4:$C$140,$U$35,E4:E140,$V$35)
A38: =CONCATENATE(C38,D38,E38) | B38: =CONCATENATE(D38,E38) | C38: =IF(D38>=1,IF(D38<=3,"1",IF(D38>=4,IF(D38<=6,"2",IF(D38>=7,IF(D38<=9,"3",IF(D38>=10,IF(D38<=12,"4","-")))))))) | D38: =MONTH(G10) | E38: =YEAR(G10) | F38: =F37+1 | G38: 45802 | H38: 0.005889 | I38: 63 | J38: =IFERROR((VLOOKUP($G38,'22F1187231'!$D$3:$N$4160,8,1))*O38,0) | K38: =VLOOKUP(G38,'22F1187231'!$D$5:$L$4163,9,0)*O38 | L38: =SUM(J38:K38) | M38: =(VLOOKUP($G38,'22F1187231'!$D$5:$N$4163,10,1))*O38 | N38: =SUM(L38:M38) | O38: 1113210 | P38: =VLOOKUP(G38,'22F1187231'!$D$5:$J$4160,7,0)*O38-(SUM(J38:K38,M38)) | Q38: =(VLOOKUP(EOMONTH(G38,0),'22F1187231'!$D$5:$J$4160,7,0))*O38 | R38: =(VLOOKUP(G38,'22F1187231'!$D$5:$J$4160,4,0)-VLOOKUP(G38,'22F1187231'!$D$5:$J$4160,2,0))*O38 | T38: Amex | U38: =SUMIFS($M$3:$M$140,$C$3:$C$140,$U$35,E3:E140,$V$35)
A39: =CONCATENATE(C39,D39,E39) | B39: =CONCATENATE(D39,E39) | C39: =IF(D39>=1,IF(D39<=3,"1",IF(D39>=4,IF(D39<=6,"2",IF(D39>=7,IF(D39<=9,"3",IF(D39>=10,IF(D39<=12,"4","-")))))))) | D39: =MONTH(G11) | E39: =YEAR(G11) | F39: =F38+1 | G39: 45833 | H39: 0.005957 | I39: 64 | J39: =IFERROR((VLOOKUP($G39,'22F1187231'!$D$3:$N$4160,8,1))*O39,0) | K39: =VLOOKUP(G39,'22F1187231'!$D$5:$L$4163,9,0)*O39 | L39: =SUM(J39:K39) | M39: =(VLOOKUP($G39,'22F1187231'!$D$5:$N$4163,10,1))*O39 | N39: =SUM(L39:M39) | O39: 1113210 | P39: =VLOOKUP(G39,'22F1187231'!$D$5:$J$4160,7,0)*O39-(SUM(J39:K39,M39)) | Q39: =(VLOOKUP(EOMONTH(G39,0),'22F1187231'!$D$5:$J$4160,7,0))*O39 | R39: =(VLOOKUP(G39,'22F1187231'!$D$5:$J$4160,4,0)-VLOOKUP(G39,'22F1187231'!$D$5:$J$4160,2,0))*O39 | T39: Amort + Amex | U39: =SUM(U37:U38)
A40: =CONCATENATE(C40,D40,E40) | B40: =CONCATENATE(D40,E40) | C40: =IF(D40>=1,IF(D40<=3,"1",IF(D40>=4,IF(D40<=6,"2",IF(D40>=7,IF(D40<=9,"3",IF(D40>=10,IF(D40<=12,"4","-")))))))) | D40: =MONTH(G12) | E40: =YEAR(G12) | F40: =F39+1 | G40: 45863 | H40: 0.006027 | I40: 65 | J40: =IFERROR((VLOOKUP($G40,'22F1187231'!$D$3:$N$4160,8,1))*O40,0) | K40: =VLOOKUP(G40,'22F1187231'!$D$5:$L$4163,9,0)*O40 | L40: =SUM(J40:K40) | M40: =(VLOOKUP($G40,'22F1187231'!$D$5:$N$4163,10,1))*O40 | N40: =SUM(L40:M40) | O40: 1113210 | P40: =VLOOKUP(G40,'22F1187231'!$D$5:$J$4160,7,0)*O40-(SUM(J40:K40,M40)) | Q40: =(VLOOKUP(EOMONTH(G40,0),'22F1187231'!$D$5:$J$4160,7,0))*O40 | R40: =(VLOOKUP(G40,'22F1187231'!$D$5:$J$4160,4,0)-VLOOKUP(G40,'22F1187231'!$D$5:$J$4160,2,0))*O40 | T40: Saldo Operação | U40: =IFERROR(VLOOKUP(CONCATENATE(U35,W35,V35),$A$3:$R$999,15,0),"-")
A41: =CONCATENATE(C41,D41,E41) | B41: =CONCATENATE(D41,E41) | C41: =IF(D41>=1,IF(D41<=3,"1",IF(D41>=4,IF(D41<=6,"2",IF(D41>=7,IF(D41<=9,"3",IF(D41>=10,IF(D41<=12,"4","-")))))))) | D41: =MONTH(G13) | E41: =YEAR(G13) | F41: =F40+1 | G41: 45894 | H41: 0.006098 | I41: 66 | J41: =IFERROR((VLOOKUP($G41,'22F1187231'!$D$3:$N$4160,8,1))*O41,0) | K41: =VLOOKUP(G41,'22F1187231'!$D$5:$L$4163,9,0)*O41 | L41: =SUM(J41:K41) | M41: =(VLOOKUP($G41,'22F1187231'!$D$5:$N$4163,10,1))*O41 | N41: =SUM(L41:M41) | O41: 1113210 | P41: =VLOOKUP(G41,'22F1187231'!$D$5:$J$4160,7,0)*O41-(SUM(J41:K41,M41)) | Q41: =(VLOOKUP(EOMONTH(G41,0),'22F1187231'!$D$5:$J$4160,7,0))*O41 | R41: =(VLOOKUP(G41,'22F1187231'!$D$5:$J$4160,4,0)-VLOOKUP(G41,'22F1187231'!$D$5:$J$4160,2,0))*O41
A42: =CONCATENATE(C42,D42,E42) | B42: =CONCATENATE(D42,E42) | C42: =IF(D42>=1,IF(D42<=3,"1",IF(D42>=4,IF(D42<=6,"2",IF(D42>=7,IF(D42<=9,"3",IF(D42>=10,IF(D42<=12,"4","-")))))))) | D42: =MONTH(G14) | E42: =YEAR(G14) | F42: =F41+1 | G42: 45925 | H42: 0.00617 | I42: 67 | J42: =IFERROR((VLOOKUP($G42,'22F1187231'!$D$3:$N$4160,8,1))*O42,0) | K42: =VLOOKUP(G42,'22F1187231'!$D$5:$L$4163,9,0)*O42 | L42: =SUM(J42:K42) | M42: =(VLOOKUP($G42,'22F1187231'!$D$5:$N$4163,10,1))*O42 | N42: =SUM(L42:M42) | O42: 1113210 | P42: =VLOOKUP(G42,'22F1187231'!$D$5:$J$4160,7,0)*O42-(SUM(J42:K42,M42)) | Q42: =(VLOOKUP(EOMONTH(G42,0),'22F1187231'!$D$5:$J$4160,7,0))*O42 | R42: =(VLOOKUP(G42,'22F1187231'!$D$5:$J$4160,4,0)-VLOOKUP(G42,'22F1187231'!$D$5:$J$4160,2,0))*O42 | T42: *preencher apenas as células em amarelo para informe anual
A43: =CONCATENATE(C43,D43,E43) | B43: =CONCATENATE(D43,E43) | C43: =IF(D43>=1,IF(D43<=3,"1",IF(D43>=4,IF(D43<=6,"2",IF(D43>=7,IF(D43<=9,"3",IF(D43>=10,IF(D43<=12,"4","-")))))))) | D43: =MONTH(G15) | E43: =YEAR(G15) | F43: =F42+1 | G43: 45955 | H43: 0.006257 | I43: 68 | J43: =IFERROR((VLOOKUP($G43,'22F1187231'!$D$3:$N$4160,8,1))*O43,0) | K43: =VLOOKUP(G43,'22F1187231'!$D$5:$L$4163,9,0)*O43 | L43: =SUM(J43:K43) | M43: =(VLOOKUP($G43,'22F1187231'!$D$5:$N$4163,10,1))*O43 | N43: =SUM(L43:M43) | O43: 1113210 | P43: =VLOOKUP(G43,'22F1187231'!$D$5:$J$4160,7,0)*O43-(SUM(J43:K43,M43)) | Q43: =(VLOOKUP(EOMONTH(G43,0),'22F1187231'!$D$5:$J$4160,7,0))*O43 | R43: =(VLOOKUP(G43,'22F1187231'!$D$5:$J$4160,4,0)-VLOOKUP(G43,'22F1187231'!$D$5:$J$4160,2,0))*O43 | T43: PAGAMENTO | U43: ANO
A44: =CONCATENATE(C44,D44,E44) | B44: =CONCATENATE(D44,E44) | C44: =IF(D44>=1,IF(D44<=3,"1",IF(D44>=4,IF(D44<=6,"2",IF(D44>=7,IF(D44<=9,"3",IF(D44>=10,IF(D44<=12,"4","-")))))))) | D44: =MONTH(G16) | E44: =YEAR(G16) | F44: =F43+1 | G44: 45986 | H44: 0.006332 | I44: 69 | J44: =IFERROR((VLOOKUP($G44,'22F1187231'!$D$3:$N$4160,8,1))*O44,0) | K44: =VLOOKUP(G44,'22F1187231'!$D$5:$L$4163,9,0)*O44 | L44: =SUM(J44:K44) | M44: =(VLOOKUP($G44,'22F1187231'!$D$5:$N$4163,10,1))*O44 | N44: =SUM(L44:M44) | O44: 1113210 | P44: =VLOOKUP(G44,'22F1187231'!$D$5:$J$4160,7,0)*O44-(SUM(J44:K44,M44)) | Q44: =(VLOOKUP(EOMONTH(G44,0),'22F1187231'!$D$5:$J$4160,7,0))*O44 | R44: =(VLOOKUP(G44,'22F1187231'!$D$5:$J$4160,4,0)-VLOOKUP(G44,'22F1187231'!$D$5:$J$4160,2,0))*O44 | U44: 2022 | V44: 12
A45: =CONCATENATE(C45,D45,E45) | B45: =CONCATENATE(D45,E45) | C45: =IF(D45>=1,IF(D45<=3,"1",IF(D45>=4,IF(D45<=6,"2",IF(D45>=7,IF(D45<=9,"3",IF(D45>=10,IF(D45<=12,"4","-")))))))) | D45: =MONTH(G17) | E45: =YEAR(G17) | F45: =F44+1 | G45: 46016 | H45: 0.006513 | I45: 70 | J45: =IFERROR((VLOOKUP($G45,'22F1187231'!$D$3:$N$4160,8,1))*O45,0) | K45: =VLOOKUP(G45,'22F1187231'!$D$5:$L$4163,9,0)*O45 | L45: =SUM(J45:K45) | M45: =(VLOOKUP($G45,'22F1187231'!$D$5:$N$4163,10,1))*O45 | N45: =SUM(L45:M45) | O45: 1113210 | P45: =VLOOKUP(G45,'22F1187231'!$D$5:$J$4160,7,0)*O45-(SUM(J45:K45,M45)) | Q45: =(VLOOKUP(EOMONTH(G45,0),'22F1187231'!$D$5:$J$4160,7,0))*O45 | R45: =(VLOOKUP(G45,'22F1187231'!$D$5:$J$4160,4,0)-VLOOKUP(G45,'22F1187231'!$D$5:$J$4160,2,0))*O45 | T45: Juros | U45: =SUMIF($E$3:$E$121,$U$44,$J$3:$J$93)
A46: =CONCATENATE(C46,D46,E46) | B46: =CONCATENATE(D46,E46) | C46: =IF(D46>=1,IF(D46<=3,"1",IF(D46>=4,IF(D46<=6,"2",IF(D46>=7,IF(D46<=9,"3",IF(D46>=10,IF(D46<=12,"4","-")))))))) | D46: =MONTH(G18) | E46: =YEAR(G18) | F46: =F45+1 | G46: 46047 | H46: 0.0068 | I46: 71 | J46: =IFERROR((VLOOKUP($G46,'22F1187231'!$D$3:$N$4160,8,1))*O46,0) | K46: =VLOOKUP(G46,'22F1187231'!$D$5:$L$4163,9,0)*O46 | L46: =SUM(J46:K46) | M46: =(VLOOKUP($G46,'22F1187231'!$D$5:$N$4163,10,1))*O46 | N46: =SUM(L46:M46) | O46: 1113210 | P46: =VLOOKUP(G46,'22F1187231'!$D$5:$J$4160,7,0)*O46-(SUM(J46:K46,M46)) | Q46: =(VLOOKUP(EOMONTH(G46,0),'22F1187231'!$D$5:$J$4160,7,0))*O46 | R46: =(VLOOKUP(G46,'22F1187231'!$D$5:$J$4160,4,0)-VLOOKUP(G46,'22F1187231'!$D$5:$J$4160,2,0))*O46 | T46: Amortização | U46: =SUMIF($E$3:$E$121,$U$44,$K$3:$K$93)
A47: =CONCATENATE(C47,D47,E47) | B47: =CONCATENATE(D47,E47) | C47: =IF(D47>=1,IF(D47<=3,"1",IF(D47>=4,IF(D47<=6,"2",IF(D47>=7,IF(D47<=9,"3",IF(D47>=10,IF(D47<=12,"4","-")))))))) | D47: =MONTH(G19) | E47: =YEAR(G19) | F47: =F46+1 | G47: 46078 | H47: 0.006925 | I47: 72 | J47: =IFERROR((VLOOKUP($G47,'22F1187231'!$D$3:$N$4160,8,1))*O47,0) | K47: =VLOOKUP(G47,'22F1187231'!$D$5:$L$4163,9,0)*O47 | L47: =SUM(J47:K47) | M47: =(VLOOKUP($G47,'22F1187231'!$D$5:$N$4163,10,1))*O47 | N47: =SUM(L47:M47) | O47: 1113210 | P47: =VLOOKUP(G47,'22F1187231'!$D$5:$J$4160,7,0)*O47-(SUM(J47:K47,M47)) | Q47: =(VLOOKUP(EOMONTH(G47,0),'22F1187231'!$D$5:$J$4160,7,0))*O47 | R47: =(VLOOKUP(G47,'22F1187231'!$D$5:$J$4160,4,0)-VLOOKUP(G47,'22F1187231'!$D$5:$J$4160,2,0))*O47 | T47: Amex | U47: =SUMIF($E$3:$E$121,$U$44,$M$3:$M$93)
A48: =CONCATENATE(C48,D48,E48) | B48: =CONCATENATE(D48,E48) | C48: =IF(D48>=1,IF(D48<=3,"1",IF(D48>=4,IF(D48<=6,"2",IF(D48>=7,IF(D48<=9,"3",IF(D48>=10,IF(D48<=12,"4","-")))))))) | D48: =MONTH(G20) | E48: =YEAR(G20) | F48: =F47+1 | G48: 46106 | H48: 0.007028 | I48: 73 | J48: =IFERROR((VLOOKUP($G48,'22F1187231'!$D$3:$N$4160,8,1))*O48,0) | K48: =VLOOKUP(G48,'22F1187231'!$D$5:$L$4163,9,0)*O48 | L48: =SUM(J48:K48) | M48: =(VLOOKUP($G48,'22F1187231'!$D$5:$N$4163,10,1))*O48 | N48: =SUM(L48:M48) | O48: 1113210 | P48: =VLOOKUP(G48,'22F1187231'!$D$5:$J$4160,7,0)*O48-(SUM(J48:K48,M48)) | Q48: =(VLOOKUP(EOMONTH(G48,0),'22F1187231'!$D$5:$J$4160,7,0))*O48 | R48: =(VLOOKUP(G48,'22F1187231'!$D$5:$J$4160,4,0)-VLOOKUP(G48,'22F1187231'!$D$5:$J$4160,2,0))*O48 | T48: Saldo Operação | U48: =IFERROR(VLOOKUP(CONCATENATE(V44,U44),$B$3:$R$999,14,0),"-")
A49: =CONCATENATE(C49,D49,E49) | B49: =CONCATENATE(D49,E49) | C49: =IF(D49>=1,IF(D49<=3,"1",IF(D49>=4,IF(D49<=6,"2",IF(D49>=7,IF(D49<=9,"3",IF(D49>=10,IF(D49<=12,"4","-")))))))) | D49: =MONTH(G21) | E49: =YEAR(G21) | F49: =F48+1 | G49: 46137 | H49: 0.007118 | I49: 74 | J49: =IFERROR((VLOOKUP($G49,'22F1187231'!$D$3:$N$4160,8,1))*O49,0) | K49: =VLOOKUP(G49,'22F1187231'!$D$5:$L$4163,9,0)*O49 | L49: =SUM(J49:K49) | M49: =(VLOOKUP($G49,'22F1187231'!$D$5:$N$4163,10,1))*O49 | N49: =SUM(L49:M49) | O49: 1113210 | P49: =VLOOKUP(G49,'22F1187231'!$D$5:$J$4160,7,0)*O49-(SUM(J49:K49,M49)) | Q49: =(VLOOKUP(EOMONTH(G49,0),'22F1187231'!$D$5:$J$4160,7,0))*O49 | R49: =(VLOOKUP(G49,'22F1187231'!$D$5:$J$4160,4,0)-VLOOKUP(G49,'22F1187231'!$D$5:$J$4160,2,0))*O49
A50: =CONCATENATE(C50,D50,E50) | B50: =CONCATENATE(D50,E50) | C50: =IF(D50>=1,IF(D50<=3,"1",IF(D50>=4,IF(D50<=6,"2",IF(D50>=7,IF(D50<=9,"3",IF(D50>=10,IF(D50<=12,"4","-")))))))) | D50: =MONTH(G22) | E50: =YEAR(G22) | F50: =F49+1 | G50: 46167 | H50: 0.007209 | I50: 75 | J50: =IFERROR((VLOOKUP($G50,'22F1187231'!$D$3:$N$4160,8,1))*O50,0) | K50: =VLOOKUP(G50,'22F1187231'!$D$5:$L$4163,9,0)*O50 | L50: =SUM(J50:K50) | M50: =(VLOOKUP($G50,'22F1187231'!$D$5:$N$4163,10,1))*O50 | N50: =SUM(L50:M50) | O50: 1113210 | P50: =VLOOKUP(G50,'22F1187231'!$D$5:$J$4160,7,0)*O50-(SUM(J50:K50,M50)) | Q50: =(VLOOKUP(EOMONTH(G50,0),'22F1187231'!$D$5:$J$4160,7,0))*O50 | R50: =(VLOOKUP(G50,'22F1187231'!$D$5:$J$4160,4,0)-VLOOKUP(G50,'22F1187231'!$D$5:$J$4160,2,0))*O50
A51: =CONCATENATE(C51,D51,E51) | B51: =CONCATENATE(D51,E51) | C51: =IF(D51>=1,IF(D51<=3,"1",IF(D51>=4,IF(D51<=6,"2",IF(D51>=7,IF(D51<=9,"3",IF(D51>=10,IF(D51<=12,"4","-")))))))) | D51: =MONTH(G23) | E51: =YEAR(G23) | F51: =F50+1 | G51: 46198 | H51: 0.007303 | I51: 76 | J51: =IFERROR((VLOOKUP($G51,'22F1187231'!$D$3:$N$4160,8,1))*O51,0) | K51: =VLOOKUP(G51,'22F1187231'!$D$5:$L$4163,9,0)*O51 | L51: =SUM(J51:K51) | M51: =(VLOOKUP($G51,'22F1187231'!$D$5:$N$4163,10,1))*O51 | N51: =SUM(L51:M51) | O51: 1113210 | P51: =VLOOKUP(G51,'22F1187231'!$D$5:$J$4160,7,0)*O51-(SUM(J51:K51,M51)) | Q51: =(VLOOKUP(EOMONTH(G51,0),'22F1187231'!$D$5:$J$4160,7,0))*O51 | R51: =(VLOOKUP(G51,'22F1187231'!$D$5:$J$4160,4,0)-VLOOKUP(G51,'22F1187231'!$D$5:$J$4160,2,0))*O51
A52: =CONCATENATE(C52,D52,E52) | B52: =CONCATENATE(D52,E52) | C52: =IF(D52>=1,IF(D52<=3,"1",IF(D52>=4,IF(D52<=6,"2",IF(D52>=7,IF(D52<=9,"3",IF(D52>=10,IF(D52<=12,"4","-")))))))) | D52: =MONTH(G24) | E52: =YEAR(G24) | F52: =F51+1 | G52: 46228 | H52: 0.007398 | I52: 77 | J52: =IFERROR((VLOOKUP($G52,'22F1187231'!$D$3:$N$4160,8,1))*O52,0) | K52: =VLOOKUP(G52,'22F1187231'!$D$5:$L$4163,9,0)*O52 | L52: =SUM(J52:K52) | M52: =(VLOOKUP($G52,'22F1187231'!$D$5:$N$4163,10,1))*O52 | N52: =SUM(L52:M52) | O52: 1113210 | P52: =VLOOKUP(G52,'22F1187231'!$D$5:$J$4160,7,0)*O52-(SUM(J52:K52,M52)) | Q52: =(VLOOKUP(EOMONTH(G52,0),'22F1187231'!$D$5:$J$4160,7,0))*O52 | R52: =(VLOOKUP(G52,'22F1187231'!$D$5:$J$4160,4,0)-VLOOKUP(G52,'22F1187231'!$D$5:$J$4160,2,0))*O52
A53: =CONCATENATE(C53,D53,E53) | B53: =CONCATENATE(D53,E53) | C53: =IF(D53>=1,IF(D53<=3,"1",IF(D53>=4,IF(D53<=6,"2",IF(D53>=7,IF(D53<=9,"3",IF(D53>=10,IF(D53<=12,"4","-")))))))) | D53: =MONTH(G25) | E53: =YEAR(G25) | F53: =F52+1 | G53: 46259 | H53: 0.007495 | I53: 78 | J53: =IFERROR((VLOOKUP($G53,'22F1187231'!$D$3:$N$4160,8,1))*O53,0) | K53: =VLOOKUP(G53,'22F1187231'!$D$5:$L$4163,9,0)*O53 | L53: =SUM(J53:K53) | M53: =(VLOOKUP($G53,'22F1187231'!$D$5:$N$4163,10,1))*O53 | N53: =SUM(L53:M53) | O53: 1113210 | P53: =VLOOKUP(G53,'22F1187231'!$D$5:$J$4160,7,0)*O53-(SUM(J53:K53,M53)) | Q53: =(VLOOKUP(EOMONTH(G53,0),'22F1187231'!$D$5:$J$4160,7,0))*O53 | R53: =(VLOOKUP(G53,'22F1187231'!$D$5:$J$4160,4,0)-VLOOKUP(G53,'22F1187231'!$D$5:$J$4160,2,0))*O53
A54: =CONCATENATE(C54,D54,E54) | B54: =CONCATENATE(D54,E54) | C54: =IF(D54>=1,IF(D54<=3,"1",IF(D54>=4,IF(D54<=6,"2",IF(D54>=7,IF(D54<=9,"3",IF(D54>=10,IF(D54<=12,"4","-")))))))) | D54: =MONTH(G26) | E54: =YEAR(G26) | F54: =F53+1 | G54: 46290 | H54: 0.007595 | I54: 79 | J54: =IFERROR((VLOOKUP($G54,'22F1187231'!$D$3:$N$4160,8,1))*O54,0) | K54: =VLOOKUP(G54,'22F1187231'!$D$5:$L$4163,9,0)*O54 | L54: =SUM(J54:K54) | M54: =(VLOOKUP($G54,'22F1187231'!$D$5:$N$4163,10,1))*O54 | N54: =SUM(L54:M54) | O54: 1113210 | P54: =VLOOKUP(G54,'22F1187231'!$D$5:$J$4160,7,0)*O54-(SUM(J54:K54,M54)) | Q54: =(VLOOKUP(EOMONTH(G54,0),'22F1187231'!$D$5:$J$4160,7,0))*O54 | R54: =(VLOOKUP(G54,'22F1187231'!$D$5:$J$4160,4,0)-VLOOKUP(G54,'22F1187231'!$D$5:$J$4160,2,0))*O54
A55: =CONCATENATE(C55,D55,E55) | B55: =CONCATENATE(D55,E55) | C55: =IF(D55>=1,IF(D55<=3,"1",IF(D55>=4,IF(D55<=6,"2",IF(D55>=7,IF(D55<=9,"3",IF(D55>=10,IF(D55<=12,"4","-")))))))) | D55: =MONTH(G27) | E55: =YEAR(G27) | F55: =F54+1 | G55: 46320 | H55: 0.007711 | I55: 80 | J55: =IFERROR((VLOOKUP($G55,'22F1187231'!$D$3:$N$4160,8,1))*O55,0) | K55: =VLOOKUP(G55,'22F1187231'!$D$5:$L$4163,9,0)*O55 | L55: =SUM(J55:K55) | M55: =(VLOOKUP($G55,'22F1187231'!$D$5:$N$4163,10,1))*O55 | N55: =SUM(L55:M55) | O55: 1113210 | P55: =VLOOKUP(G55,'22F1187231'!$D$5:$J$4160,7,0)*O55-(SUM(J55:K55,M55)) | Q55: =(VLOOKUP(EOMONTH(G55,0),'22F1187231'!$D$5:$J$4160,7,0))*O55 | R55: =(VLOOKUP(G55,'22F1187231'!$D$5:$J$4160,4,0)-VLOOKUP(G55,'22F1187231'!$D$5:$J$4160,2,0))*O55
A56: =CONCATENATE(C56,D56,E56) | B56: =CONCATENATE(D56,E56) | C56: =IF(D56>=1,IF(D56<=3,"1",IF(D56>=4,IF(D56<=6,"2",IF(D56>=7,IF(D56<=9,"3",IF(D56>=10,IF(D56<=12,"4","-")))))))) | D56: =MONTH(G28) | E56: =YEAR(G28) | F56: =F55+1 | G56: 46351 | H56: 0.007815 | I56: 81 | J56: =IFERROR((VLOOKUP($G56,'22F1187231'!$D$3:$N$4160,8,1))*O56,0) | K56: =VLOOKUP(G56,'22F1187231'!$D$5:$L$4163,9,0)*O56 | L56: =SUM(J56:K56) | M56: =(VLOOKUP($G56,'22F1187231'!$D$5:$N$4163,10,1))*O56 | N56: =SUM(L56:M56) | O56: 1113210 | P56: =VLOOKUP(G56,'22F1187231'!$D$5:$J$4160,7,0)*O56-(SUM(J56:K56,M56)) | Q56: =(VLOOKUP(EOMONTH(G56,0),'22F1187231'!$D$5:$J$4160,7,0))*O56 | R56: =(VLOOKUP(G56,'22F1187231'!$D$5:$J$4160,4,0)-VLOOKUP(G56,'22F1187231'!$D$5:$J$4160,2,0))*O56
A57: =CONCATENATE(C57,D57,E57) | B57: =CONCATENATE(D57,E57) | C57: =IF(D57>=1,IF(D57<=3,"1",IF(D57>=4,IF(D57<=6,"2",IF(D57>=7,IF(D57<=9,"3",IF(D57>=10,IF(D57<=12,"4","-")))))))) | D57: =MONTH(G29) | E57: =YEAR(G29) | F57: =F56+1 | G57: 46381 | H57: 0.008038 | I57: 82 | J57: =IFERROR((VLOOKUP($G57,'22F1187231'!$D$3:$N$4160,8,1))*O57,0) | K57: =VLOOKUP(G57,'22F1187231'!$D$5:$L$4163,9,0)*O57 | L57: =SUM(J57:K57) | M57: =(VLOOKUP($G57,'22F1187231'!$D$5:$N$4163,10,1))*O57 | N57: =SUM(L57:M57) | O57: 1113210 | P57: =VLOOKUP(G57,'22F1187231'!$D$5:$J$4160,7,0)*O57-(SUM(J57:K57,M57)) | Q57: =(VLOOKUP(EOMONTH(G57,0),'22F1187231'!$D$5:$J$4160,7,0))*O57 | R57: =(VLOOKUP(G57,'22F1187231'!$D$5:$J$4160,4,0)-VLOOKUP(G57,'22F1187231'!$D$5:$J$4160,2,0))*O57
A58: =CONCATENATE(C58,D58,E58) | B58: =CONCATENATE(D58,E58) | C58: =IF(D58>=1,IF(D58<=3,"1",IF(D58>=4,IF(D58<=6,"2",IF(D58>=7,IF(D58<=9,"3",IF(D58>=10,IF(D58<=12,"4","-")))))))) | D58: =MONTH(G30) | E58: =YEAR(G30) | F58: =F57+1 | G58: 46412 | H58: 0.008381 | I58: 83 | J58: =IFERROR((VLOOKUP($G58,'22F1187231'!$D$3:$N$4160,8,1))*O58,0) | K58: =VLOOKUP(G58,'22F1187231'!$D$5:$L$4163,9,0)*O58 | L58: =SUM(J58:K58) | M58: =(VLOOKUP($G58,'22F1187231'!$D$5:$N$4163,10,1))*O58 | N58: =SUM(L58:M58) | O58: 1113210 | P58: =VLOOKUP(G58,'22F1187231'!$D$5:$J$4160,7,0)*O58-(SUM(J58:K58,M58)) | Q58: =(VLOOKUP(EOMONTH(G58,0),'22F1187231'!$D$5:$J$4160,7,0))*O58 | R58: =(VLOOKUP(G58,'22F1187231'!$D$5:$J$4160,4,0)-VLOOKUP(G58,'22F1187231'!$D$5:$J$4160,2,0))*O58
A59: =CONCATENATE(C59,D59,E59) | B59: =CONCATENATE(D59,E59) | C59: =IF(D59>=1,IF(D59<=3,"1",IF(D59>=4,IF(D59<=6,"2",IF(D59>=7,IF(D59<=9,"3",IF(D59>=10,IF(D59<=12,"4","-")))))))) | D59: =MONTH(G31) | E59: =YEAR(G31) | F59: =F58+1 | G59: 46443 | H59: 0.008544 | I59: 84 | J59: =IFERROR((VLOOKUP($G59,'22F1187231'!$D$3:$N$4160,8,1))*O59,0) | K59: =VLOOKUP(G59,'22F1187231'!$D$5:$L$4163,9,0)*O59 | L59: =SUM(J59:K59) | M59: =(VLOOKUP($G59,'22F1187231'!$D$5:$N$4163,10,1))*O59 | N59: =SUM(L59:M59) | O59: 1113210 | P59: =VLOOKUP(G59,'22F1187231'!$D$5:$J$4160,7,0)*O59-(SUM(J59:K59,M59)) | Q59: =(VLOOKUP(EOMONTH(G59,0),'22F1187231'!$D$5:$J$4160,7,0))*O59 | R59: =(VLOOKUP(G59,'22F1187231'!$D$5:$J$4160,4,0)-VLOOKUP(G59,'22F1187231'!$D$5:$J$4160,2,0))*O59
A60: =CONCATENATE(C60,D60,E60) | B60: =CONCATENATE(D60,E60) | C60: =IF(D60>=1,IF(D60<=3,"1",IF(D60>=4,IF(D60<=6,"2",IF(D60>=7,IF(D60<=9,"3",IF(D60>=10,IF(D60<=12,"4","-")))))))) | D60: =MONTH(G32) | E60: =YEAR(G32) | F60: =F59+1 | G60: 46471 | H60: 0.008684 | I60: 85 | J60: =IFERROR((VLOOKUP($G60,'22F1187231'!$D$3:$N$4160,8,1))*O60,0) | K60: =VLOOKUP(G60,'22F1187231'!$D$5:$L$4163,9,0)*O60 | L60: =SUM(J60:K60) | M60: =(VLOOKUP($G60,'22F1187231'!$D$5:$N$4163,10,1))*O60 | N60: =SUM(L60:M60) | O60: 1113210 | P60: =VLOOKUP(G60,'22F1187231'!$D$5:$J$4160,7,0)*O60-(SUM(J60:K60,M60)) | Q60: =(VLOOKUP(EOMONTH(G60,0),'22F1187231'!$D$5:$J$4160,7,0))*O60 | R60: =(VLOOKUP(G60,'22F1187231'!$D$5:$J$4160,4,0)-VLOOKUP(G60,'22F1187231'!$D$5:$J$4160,2,0))*O60
... A140: =CONCATENATE(C140,D140,E140) | B140: =CONCATENATE(D140,E140) | C140: =IF(D140>=1,IF(D140<=3,"1",IF(D140>=4,IF(D140<=6,"2",IF(D140>=7,IF(D140<=9,"3",IF(D140>=10,IF(D140<=12,"4","-")))))))) | D140: =MONTH(G112) | E140: =YEAR(G112) | F140: =F139+1 | G140: 48908 | H140: 1 | I140: 165 | J140: =IFERROR((VLOOKUP($G140,'22F1187231'!$D$3:$N$4160,8,1))*O140,0) | K140: =VLOOKUP(G140,'22F1187231'!$D$5:$L$4163,9,0)*O140 | L140: =SUM(J140:K140) | M140: =(VLOOKUP($G140,'22F1187231'!$D$5:$N$4163,10,1))*O140 | N140: =SUM(L140:M140) | O140: 1113210 | P140: =VLOOKUP(G140,'22F1187231'!$D$5:$J$4160,7,0)*O140-(SUM(J140:K140,M140)) | Q140: =(VLOOKUP(EOMONTH(G140,0),'22F1187231'!$D$5:$J$4160,7,0))*O140 | R140: =(VLOOKUP(G140,'22F1187231'!$D$5:$J$4160,4,0)-VLOOKUP(G140,'22F1187231'!$D$5:$J$4160,2,0))*O140
A141: =CONCATENATE(C141,D141,E141) | B141: =CONCATENATE(D141,E141) | C141: =IF(D141>=1,IF(D141<=3,"1",IF(D141>=4,IF(D141<=6,"2",IF(D141>=7,IF(D141<=9,"3",IF(D141>=10,IF(D141<=12,"4","-")))))))) | D141: =MONTH(G113) | E141: =YEAR(G113)
A142: =CONCATENATE(C142,D142,E142) | B142: =CONCATENATE(D142,E142) | C142: =IF(D142>=1,IF(D142<=3,"1",IF(D142>=4,IF(D142<=6,"2",IF(D142>=7,IF(D142<=9,"3",IF(D142>=10,IF(D142<=12,"4","-")))))))) | D142: =MONTH(G114) | E142: =YEAR(G114)
A143: =CONCATENATE(C143,D143,E143) | B143: =CONCATENATE(D143,E143) | C143: =IF(D143>=1,IF(D143<=3,"1",IF(D143>=4,IF(D143<=6,"2",IF(D143>=7,IF(D143<=9,"3",IF(D143>=10,IF(D143<=12,"4","-")))))))) | D143: =MONTH(G115) | E143: =YEAR(G115)

Sheet IPCA
A1: EVENTO | B1: MÊS/ANO | C1: VARIAÇÃO
A2: 1 | B2: 44706 | C2: 0.0047000727
A3: =A2+1 | B3: 44737 | C3: 0.0067005776
A4: =A3+1 | B4: 44767 | C4: -0.0068000341
A5: =A4+1 | B5: 44798 | C5: -0.003599529
A6: =A5+1 | B6: 44829 | C6: -0.0029003564
A7: =A6+1 | B7: 44859 | C7: 0.0059007839
A8: =A7+1 | B8: 44890 | C8: 0.0040996078
A9: =A8+1 | B9: 44920 | C9: 0.0061996829
A10: =A9+1 | B10: 44951 | C10: 0.0052995865
A11: =A10+1 | B11: 44982 | C11: 0.008399914
A12: =A11+1 | B12: 45010 | C12: 0.0071003357
A13: =A12+1 | B13: 45041 | C13: 0.0061001533
A14: =A13+1 | B14: 45071 | C14: 0.0022992516
... A36: =A35+1 | B36: 45741 | C36: 0.0056002543
A37: =A36+1 | B37: 45772 | C37: =C36
A38: =A37+1 | B38: 45802 | C38: =C37
A39: =A38+1 | B39: 45833 | C39: =C38
A40: =A39+1 | B40: 45863 | C40: =C39
A41: =A40+1 | B41: 45894 | C41: =C40
A42: =A41+1 | B42: 45925 | C42: =C41
A43: =A42+1 | B43: 45955 | C43: =C42
A44: =A43+1 | B44: 45986 | C44: =C43
A45: =A44+1 | B45: 46016 | C45: =C44
A46: =A45+1 | B46: 46047 | C46: =C45
A47: =A46+1 | B47: 46078 | C47: =C46
A48: =A47+1 | B48: 46106 | C48: =C47
... A140: =A139+1 | B140: 48908 | C140: =C139

Sheet  Nexus
C4: RELATÓRIO DE PAGAMENTOS
C6: CERTIFICADO DE RECEBÍVEIS IMOBILIÁRIOS
F8: =CONCATENATE("Evento ",F23)
F9: =F24
E11: Série: | F11: 46ª
B12: Data da Emissão: | C12: 43906 | E12: Emissão: | F12: 1ª
B13: PU de Emissão: | C13: 1 | E13: Código IF (CETIP): | F13: 20F1187231 | K13: QUANTIDADE | L13: JUROS | M13: AMORT | N13: AMEX | O13: TOTAL
B14: CRI emitidos: | C14: 100000000 | E14: Código ISIN: | L14: =C23 | M14: =C25 | N14: =C26
B15: CRI integralizados: | C15: =K17 | J15: Investidor 01: | K15: 2541355 | L15: =IFERROR($L$14*K15,0) | M15: =$M$14*K15 | N15: =N14*K15 | O15: =SUM(L15:N15)
B16: Valor total de Emissão: | C16: =C14*C13 | E16: Pagamentos | J16: Investidor 02: | K16: 635339 | L16: =IFERROR($L$14*K16,0) | M16: =$M$14*K16 | N16: =N14*K16 | O16: =SUM(L16:N16)
B17: Taxa Remuneração: | C17: 0.095 | E17: Remuneração: | F17: Mensal | J17: TOTAL | K17: =SUM(K15:K16) | L17: =SUM(L15:L16) | M17: =SUM(M15:M16) | O17: =SUM(L17:N17)
B18: Indexador Correção: | C18: IPCA | E18: Correção: | F18: Mensal
B19: Dia dos Eventos: | C19: 25 | E19: Amortização: | F19: Mensal
B23: Juros por Unidade: | C23: =VLOOKUP(F24,'22F1187231'!D5:N4161,8,0) | E23: Evento: | F23: 1
B24: % Amortização: | C24: =VLOOKUP(F23,'Amort TS'!F4:H140,3,0) | E24: Data do Evento: | F24: 45376
B25: Amortização por Unidade: | C25: =VLOOKUP(F24,'22F1187231'!D5:N4161,9,0) | E25: Pagamentos
B26: Amortização Extraordinária por Unidade: | C26: =VLOOKUP(F24,'22F1187231'!D5:N4161,10,0) | E26: Investidor 01: | F26: =$C$27*K15
B27: Pagamento Total por Unidade: | C27: =IFERROR(SUM(C26+C25+C23),0) | E27: Investidor 02: | F27: =$C$27*K16
B28: Pagamento Total CRI Circulação: | C28: =C27*$C$15
B32: Saldo Devedor Unitário | C32: =VLOOKUP(F24,'22F1187231'!D5:N4161,11,0)
B33: Saldo Devedor Total | C33: =C32*$C$15
B36: José Roque | C36: (41) 3027-2040 / 99931-2040 | E36: jose.roque@ethosgroup.com.br
B37: Andressa, Laura e Amanda | C37: (41) 3149-7103 | E37: securitizacao@ethosgroup.com.br
B38: Ricardo dos Santos Rosa | C38: (41) 3149-7103 | E38: ricardo.rosa@ethosgroup.com.br
B39: Edinéia Boruck | C39: (41) 3149-7103 | E39: edineia.boruck@ethosgroup.com.br

Sheet Filtros Estatisticos
C1: 08/07/2025 16:10:08
A2: 1 | B2: 1
A3: 5 | B3: 5
A4: 2 | B4: 2
A5: 6 | B5: 6

Sheet PU Operacao
B2: 152
B3: 252
B4: 54598.186
B5: 05/08/2025 23:10:37
A6: 2025-08-06 | B6: 165 | C6: 100000
